Workbook

Sheet changes made
B2: date | C2: edits
B3: 46099 | C3: "calculations" tab 1. addition of annual interest columns 2. replaced formulas for all of cummulative balances (col Y - AB) 3. edited formula for the reference table of BRS, FRS and ERS (AG7:AI7) "output for phase 1" tab 1. edited formula for eligibility checks (D26, D28, D30)
B4: 46100 | C4: "output for phase 1" 1. change heading of "options for retirement sum" to "options for retirement sum at [toggle]" - toggle options: "55", "65",["66","67","68","69","70"] - add explanation behind the toggle age - for 66-70, only include the age where they choose to start receiving life payouts 55: age where you choose your retirement sum 65: age where you make a final decision on your retirement sum 66-70: age where you choose to start receiving LIFE payouts 2. merge the 2 tables of projected retirement sums at 65 and 70 into 1 using toggle for age "retirement sum needed" 1. added amt needed (PV) in cell A8, B8
B5: 46107 | C5: "output for phase 1" 1. options for retirement sum graph to not include MA in the total CPF savings

Sheet questions
A2: Q1 | B2: current age | C2: =(TODAY()-C3)/365 -> 27.391781 | E2: retrieve from db/my info
A3: Q1a | B3: birth date | C3: 36110 | E3: client to fill in
A4: Q1b | B4: year when age 55 | C4: =YEAR(C3)+55 -> 2053 | E4: calculate from client's info
A5: Q1c | B5: year when age 65 | C5: =YEAR(C3)+65 -> 2063 | E5: no fill, just a header
A6: Q2 | B6: age intend to retire | C6: 60
A7: Q3 | B7: monthly income required to retire | C7: 5500
A8: Q4 | B8: age expectancy | C8: 85
A9: Q5 | B9: current wage
A10: Q5a | B10: monthly income | C10: 10000
A11: Q5b | B11: bonus (months) | C11: 1
A12: Q5c | B12: yearly increment | C12: 0.03
A13: Q6 | B13: years till retirement | C13: =C6-C2 -> 32.608219
A14: Q7 | B14: current cpf balances
A15: Q7a | B15: OA | C15: 7500
A16: Q7b | B16: SA | C16: 2500
A17: Q7c | B17: MA | C17: 2500
A18: Q8 | B18: using OA for mortgage | C18: yes
A19: Q8a | B19: date when mortgage is fully paid | C19: 53206
A20: Q8b | B20: how much mortgage | C20: 700
A21: Q9 | B21: do you own a property with a remaining lease until at least age 95 | C21: yes

Sheet calculations
A1: date | B1: age | C1: current income | D1: Additional income | E1: cpf allocation cap check | G1: cpf allocation | L1: cpf withdrawal | M1: interest | S1: extra interest | Y1: cummulative balance | AC1: projected retirement sum
E2: ordinary wage | F2: additional wage | G2: Total Contribution | H2: OA | I2: SA | J2: MA | K2: RA | L2: OA - mortgage | M2: OA | N2: SA/RA | O2: MA | P2: OA annual | Q2: SA/RA annual | R2: MA annual | S2: OA | T2: SA/RA | U2: MA | V2: OA annual | W2: SA/RA annual | X2: MA annual | Y2: OA | Z2: SA | AA2: MA | AB2: RA | AC2: BRS | AD2: FRS | AE2: ERS
A3: =EOMONTH(today(),0) -> 46112 | B3: =round(YEARFRAC(EOMONTH(questions!$C$3, 0),A3,1),2) -> 27.33 | C3: =if(B3<questions!C6,questions!C10,0) -> 10000 | D3: =IF(MONTH(A3)=12,C3*questions!$C$11,0) -> 0 | E3: =MIN(C3,IF(YEAR(A3)=2025,7600,8000)) -> 8000 | F3: =MIN(102000-E3*12,D3) -> 0 | G3: {=if(YEAR(A3)=2025,XLOOKUP(B3,Lookup!$A$3:$A$7,Lookup!$D$3:$D$7,,1)*SUM(E3:F3), XLOOKUP(B3,Lookup!$A$14:$A$18,Lookup!$D$14:$D$18,,1)*SUM(E3:F3))} -> 2960 | H3: {=if(YEAR(A3)=2025,XLOOKUP(B3,Lookup!$F$3:$F$10,Lookup!$G$3:$G$10,,1)*G3, XLOOKUP(B3,Lookup!$F$14:$F$21,Lookup!$G$14:$G$21,,1)*G3)} -> 1840.232 | I3: {=if(B3<55, if(YEAR(A3)=2025,XLOOKUP(B3,Lookup!$F$3:$F$10,Lookup!$H$3:$H$10,,1)*G3, XLOOKUP(B3,Lookup!$F$14:$F$21,Lookup!$H$14:$H$21,,1)*G3),0)} -> 479.816 | J3: {=if(YEAR(A3)=2025,XLOOKUP(B3,Lookup!$F$3:$F$10,Lookup!$I$3:$I$10,,1)*G3, XLOOKUP(B3,Lookup!$F$14:$F$21,Lookup!$I$14:$I$21,,1)*G3)} -> 639.952 | K3: {=if(B3>54, if(YEAR(A3)=2025,XLOOKUP(B3,Lookup!$F$3:$F$10,Lookup!$H$3:$H$10,,1)*G3, XLOOKUP(B3,Lookup!$F$14:$F$21,Lookup!$H$14:$H$21,,1)*G3),0)} -> 0 | L3: =IF(and(A3<questions!$C$19,questions!$C$18="yes"),questions!$C$20,0) -> 700 | M3: =(questions!$C$15+H3)*Lookup!A$26/12 -> 19.458817 | N3: =(questions!$C$16+I3)*Lookup!B$26/12 -> 9.93272 | O3: =(questions!$C$17+J3)*Lookup!C$26/12 -> 10.466507 | P3: =IF(year($A3)=year($A2), P2+M3, M3) -> 19.458817 | Q3: =IF(year(A3)=year(A2), Q2+N3, N3) -> 9.93272 | R3: =IF(year(A3)=year(A2), R2+O3, O3) -> 10.466507 | S3: =min(20000,questions!C15)*0.01/12 -> 6.25 | T3: =min(60000-min(20000,questions!C15),questions!C16)*0.01/12 -> 2.0833333 | U3: =min(60000-min(60000-min(20000,questions!C15),questions!C16)-min(20000,questions!C15),questions!C17)*0.01/12 -> 2.0833333 | V3: =IF(year($A3)=year($A2), V2+S3, S3) -> 6.25 | W3: =IF(year($A3)=year($A2), W2+T3, T3) -> 2.0833333 | X3: =IF(year($A3)=year($A2), X2+U3, U3) -> 2.0833333 | Y3: =if(month($A3)=12,max(0,questions!C15+H3+P3+V3-L3),max(0,questions!C15+H3-L3)) -> 8640.232 | Z3: =if(month($A3)=12,max(0,questions!C16+I3+Q3+W3),max(0,questions!C16+I3)) -> 2979.816 | AA3: =if(month($A3)=12,max(0,questions!C17+J3+R3+X3),max(0,questions!C17+J3)) -> 3139.952 | AB3: =if(month($A3)=12,max(0,questions!C16+K3+Q3+W3),max(0,questions!C16+K3)) -> 2500 | AC3: {=IFS(B3<66, XLOOKUP(year(A3),Lookup!$K$13:$K1000,Lookup!$L$13:$L1000,"missing",,1),B3>65,XLOOKUP(questions!$C$5,Lookup!$K$13:$K1000,Lookup!$L$13:$L1000,"missing",,1))} -> 110200 | AD3: {=IFS(B3<66, XLOOKUP(year(A3),Lookup!$K$13:$K1000,Lookup!$M$13:$M1000,"missing",,1),B3>65, XLOOKUP(questions!$C$5,Lookup!$K$13:$K1000,Lookup!$M$13:$M1000,"missing",,1))} -> 220400 | AE3: {=IFS(B3<66, XLOOKUP(year(A3),Lookup!$K$13:$K1000,Lookup!$N$13:$N1000,"missing",,1),B3>65,XLOOKUP(questions!$C$5,Lookup!$K$13:$K1000,Lookup!$N$13:$N1000,"missing",,1))} -> 440800
A4: =eomonth(EDATE(A3,1),0) -> 46142 | B4: =round(YEARFRAC(EOMONTH(questions!$C$3, 0),A4,1),2) -> 27.41 | C4: =IF(B4<questions!$C$6,if(MONTH(A4)=1,C3*(1+questions!$C$12),C3),0) -> 10000 | D4: =IF(MONTH(A4)=12,C4*questions!$C$11,0) -> 0 | E4: =MIN(C4,IF(YEAR(A4)=2025,7600,8000)) -> 8000 | F4: =MIN(102000-E4*12,D4) -> 0 | G4: {=if(YEAR(A4)=2025,XLOOKUP(B4,Lookup!$A$3:$A$7,Lookup!$D$3:$D$7,,1)*SUM(E4:F4), XLOOKUP(B4,Lookup!$A$14:$A$18,Lookup!$D$14:$D$18,,1)*SUM(E4:F4))} -> 2960 | H4: {=if(YEAR(A4)=2025,XLOOKUP(B4,Lookup!$F$3:$F$10,Lookup!$G$3:$G$10,,1)*G4, XLOOKUP(B4,Lookup!$F$14:$F$21,Lookup!$G$14:$G$21,,1)*G4)} -> 1840.232 | I4: {=if(B4<55, if(YEAR(A4)=2025,XLOOKUP(B4,Lookup!$F$3:$F$10,Lookup!$H$3:$H$10,,1)*G4, XLOOKUP(B4,Lookup!$F$14:$F$21,Lookup!$H$14:$H$21,,1)*G4),0)} -> 479.816 | J4: {=if(YEAR(A4)=2025,XLOOKUP(B4,Lookup!$F$3:$F$10,Lookup!$I$3:$I$10,,1)*G4, XLOOKUP(B4,Lookup!$F$14:$F$21,Lookup!$I$14:$I$21,,1)*G4)} -> 639.952 | K4: {=if(B4>54, if(YEAR(A4)=2025,XLOOKUP(B4,Lookup!$F$3:$F$10,Lookup!$H$3:$H$10,,1)*G4, XLOOKUP(B4,Lookup!$F$14:$F$21,Lookup!$H$14:$H$21,,1)*G4),0)} -> 0 | L4: =IF(and(A4<questions!$C$19,questions!$C$18="yes"),questions!$C$20,0) -> 700 | M4: =(Y3+H4)*Lookup!A$26/12 -> 21.8343 | N4: =if(B4<55, (Z3+I4)*Lookup!B$26/12, (AB3+K4)*Lookup!B$26/12) -> 11.532107 | O4: =(AA3+J4)*Lookup!C$26/12 -> 12.59968 | P4: =IF(year(A4)=year(A3), P3+M4, M4) -> 41.293117 | Q4: =IF(year(A4)=year(A3), Q3+N4, N4) -> 21.464827 | R4: =IF(year(A4)=year(A3), R3+O4, O4) -> 23.066187 | S4: =if(B4<55,min(20000,Y3)*0.01/12,min(20000,Y3)*0.02/12) -> 7.2001933 | T4: =if(B4<=55,min(60000-min(20000,Y3),Z3)*0.01/12,min(30000-min(20000,Y3),AB3)*0.02/12+min(30000,AB3)*0.01/12) -> 2.48318 | U4: =if(B4<55,min(60000-min(60000-min(20000,Y3),Z3)-min(20000,Y3),AA3)*0.01/12,min(30000-min(30000-min(20000,Y3),AB3)-min(20000,Y3),AA3)*0.02/12+min(30000-min(30000-min(20000,Y3),AB3)-min(20000,Y3),AA3)*0.01/12) -> 2.6166267 | V4: =IF(year($A4)=year($A3), V3+S4, S4) -> 13.450193 | W4: =IF(year($A4)=year($A3), W3+T4, T4) -> 4.5665133 | X4: =IF(year($A4)=year($A3), X3+U4, U4) -> 4.69996 | Y4: =IFS( B4<55, MAX( Y3 + IF(MONTH(A4)=12, P4+V4, 0) + H4 - L4 + MAX(0, IF(AA3 >= VLOOKUP(YEAR(A4), Lookup!$Q:$R, 2), Z3 + IF(MONTH(A4)=12, Q4+W4, 0) + I4 + AA3 + IF(MONTH(A4)=12, R4+X4, 0) - VLOOKUP(YEAR(A4), Lookup!$Q:$R, 2) + J4, Z3 + IF(MONTH(A4)=12, Q4+W4, 0) + I4 ) - VLOOKUP(YEAR(A4), Lookup!$K:$M, 3) ), 0), B4=55, IF(Z3>=AD4, MAX(Y3 + IF(MONTH(A4)=12, P4+V4, 0) + H4 - L4, 0), MAX(MAX(0, Y3-(AD4-Z3)) + IF(MONTH(A4)=12, P4+V4, 0) + H4 - L4, 0) ), B4>55, IF(AB3>=$AH$7, MAX(Y3 + IF(MONTH(A4)=12, P4+V4, 0) + H4 - L4 + K4 + Z3, 0), MAX(Y3 + IF(MONTH(A4)=12, P4+V4, 0) + H4 - L4, 0) ) ) -> 9780.464 | Z4: =IFS( B4<55, MIN( IF(AA3 >= VLOOKUP(YEAR(A4), Lookup!$Q:$R, 2), Z3 + IF(MONTH(A4)=12, Q4+W4, 0) + I4 + AA3 + IF(MONTH(A4)=12, R4+X4, 0) - VLOOKUP(YEAR(A4), Lookup!$Q:$R, 2) + J4, Z3 + IF(MONTH(A4)=12, Q4+W4, 0) + I4 ), VLOOKUP(YEAR(A4), Lookup!$K:$M, 3) ), B4=55, IF(Z3 >= AD4, Z3 - AD4, 0), B4>55, 0 ) -> 3459.632 | AA4: =IFS( B4<65, IF(AA3+J4 < VLOOKUP(YEAR(A4), Lookup!$Q:$R, 2), AA3 + IF(MONTH(A4)=12, R3+X3, 0) + J4, MIN( AA3 + IF(MONTH(A4)=12, R3+X3, 0) + J4 , VLOOKUP(YEAR(A4), Lookup!$Q:$R, 2) ) ), B4>=65, IF(AA3+J4 < VLOOKUP(questions!$C$5, Lookup!$Q:$R, 2), AA3 + IF(MONTH(A4)=12, R3+X3, 0) + J4 , MIN( AA3 + IF(MONTH(A4)=12, R3+X3, 0) + J4, VLOOKUP(questions!$C$5, Lookup!$Q:$R, 2) ) ) ) -> 3779.904 | AB4: =IFS( B4<55, 0, B4=55, MIN(Y3+Z3, AD4), B4>55, IF(AB3 < $AH$7, MIN(AB3 + IF(MONTH(A4)=12, Q4+W4, 0) + K4, $AH$7), AB3 + IF(MONTH(A4)=12, Q4+W4, 0) + K4 ) ) -> 0 | AC4: {=IFS(B4<66, XLOOKUP(year(A4),Lookup!$K$13:$K1000,Lookup!$L$13:$L1000,"missing",,1),B4>65,XLOOKUP(questions!$C$5,Lookup!$K$13:$K1000,Lookup!$L$13:$L1000,"missing",,1))} -> 110200 | AD4: {=IFS(B4<66, XLOOKUP(year(A4),Lookup!$K$13:$K1000,Lookup!$M$13:$M1000,"missing",,1),B4>65, XLOOKUP(questions!$C$5,Lookup!$K$13:$K1000,Lookup!$M$13:$M1000,"missing",,1))} -> 220400 | AE4: {=IFS(B4<66, XLOOKUP(year(A4),Lookup!$K$13:$K1000,Lookup!$N$13:$N1000,"missing",,1),B4>65,XLOOKUP(questions!$C$5,Lookup!$K$13:$K1000,Lookup!$N$13:$N1000,"missing",,1))} -> 440800 | AG4: {=INDEX(calculations!Y:Y, XLOOKUP(55,calculations!B:B,row(calculations!Y:Y)) - 1)} -> 641964.18 | AH4: {=INDEX(calculations!Z:Z, XLOOKUP(55,calculations!B:B,row(calculations!Z:Z)) - 1)} -> 549331.94 | AI4: {=INDEX(calculations!AA:AA, XLOOKUP(55,calculations!B:B,row(calculations!AA:AA)) - 1)} -> 199993.8 | AJ4: =SUM(AG4:AH4) -> 1191296.1
A5: =eomonth(EDATE(A4,1),0) -> 46173 | B5: =round(YEARFRAC(EOMONTH(questions!$C$3, 0),A5,1),2) -> 27.5 | C5: =IF(B5<questions!$C$6,if(MONTH(A5)=1,C4*(1+questions!$C$12),C4),0) -> 10000 | D5: =IF(MONTH(A5)=12,C5*questions!$C$11,0) -> 0 | E5: =MIN(C5,IF(YEAR(A5)=2025,7600,8000)) -> 8000 | F5: =MIN(102000-E5*12,D5) -> 0 | G5: {=if(YEAR(A5)=2025,XLOOKUP(B5,Lookup!$A$3:$A$7,Lookup!$D$3:$D$7,,1)*SUM(E5:F5), XLOOKUP(B5,Lookup!$A$14:$A$18,Lookup!$D$14:$D$18,,1)*SUM(E5:F5))} -> 2960 | H5: {=if(YEAR(A5)=2025,XLOOKUP(B5,Lookup!$F$3:$F$10,Lookup!$G$3:$G$10,,1)*G5, XLOOKUP(B5,Lookup!$F$14:$F$21,Lookup!$G$14:$G$21,,1)*G5)} -> 1840.232 | I5: {=if(B5<55, if(YEAR(A5)=2025,XLOOKUP(B5,Lookup!$F$3:$F$10,Lookup!$H$3:$H$10,,1)*G5, XLOOKUP(B5,Lookup!$F$14:$F$21,Lookup!$H$14:$H$21,,1)*G5),0)} -> 479.816 | J5: {=if(YEAR(A5)=2025,XLOOKUP(B5,Lookup!$F$3:$F$10,Lookup!$I$3:$I$10,,1)*G5, XLOOKUP(B5,Lookup!$F$14:$F$21,Lookup!$I$14:$I$21,,1)*G5)} -> 639.952 | K5: {=if(B5>54, if(YEAR(A5)=2025,XLOOKUP(B5,Lookup!$F$3:$F$10,Lookup!$H$3:$H$10,,1)*G5, XLOOKUP(B5,Lookup!$F$14:$F$21,Lookup!$H$14:$H$21,,1)*G5),0)} -> 0 | L5: =IF(and(A5<questions!$C$19,questions!$C$18="yes"),questions!$C$20,0) -> 700 | M5: =(Y4+H5)*Lookup!A$26/12 -> 24.209783 | N5: =if(B5<55, (Z4+I5)*Lookup!B$26/12, (AB4+K5)*Lookup!B$26/12) -> 13.131493 | O5: =(AA4+J5)*Lookup!C$26/12 -> 14.732853 | P5: =IF(year(A5)=year(A4), P4+M5, M5) -> 65.5029 | Q5: =IF(year(A5)=year(A4), Q4+N5, N5) -> 34.59632 | R5: =IF(year(A5)=year(A4), R4+O5, O5) -> 37.79904 | S5: =if(B5<55,min(20000,Y4)*0.01/12,min(20000,Y4)*0.02/12) -> 8.1503867 | T5: =if(B5<=55,min(60000-min(20000,Y4),Z4)*0.01/12,min(30000-min(20000,Y4),AB4)*0.02/12+min(30000,AB4)*0.01/12) -> 2.8830267 | U5: =if(B5<55,min(60000-min(60000-min(20000,Y4),Z4)-min(20000,Y4),AA4)*0.01/12,min(30000-min(30000-min(20000,Y4),AB4)-min(20000,Y4),AA4)*0.02/12+min(30000-min(30000-min(20000,Y4),AB4)-min(20000,Y4),AA4)*0.01/12) -> 3.14992 | V5: =IF(year($A5)=year($A4), V4+S5, S5) -> 21.60058 | W5: =IF(year($A5)=year($A4), W4+T5, T5) -> 7.44954 | X5: =IF(year($A5)=year($A4), X4+U5, U5) -> 7.84988 | Y5: =IFS( B5<55, MAX( Y4 + IF(MONTH(A5)=12, P5+V5, 0) + H5 - L5 + MAX(0, IF(AA4 >= VLOOKUP(YEAR(A5), Lookup!$Q:$R, 2), Z4 + IF(MONTH(A5)=12, Q5+W5, 0) + I5 + AA4 + IF(MONTH(A5)=12, R5+X5, 0) - VLOOKUP(YEAR(A5), Lookup!$Q:$R, 2) + J5, Z4 + IF(MONTH(A5)=12, Q5+W5, 0) + I5 ) - VLOOKUP(YEAR(A5), Lookup!$K:$M, 3) ), 0), B5=55, IF(Z4>=AD5, MAX(Y4 + IF(MONTH(A5)=12, P5+V5, 0) + H5 - L5, 0), MAX(MAX(0, Y4-(AD5-Z4)) + IF(MONTH(A5)=12, P5+V5, 0) + H5 - L5, 0) ), B5>55, IF(AB4>=$AH$7, MAX(Y4 + IF(MONTH(A5)=12, P5+V5, 0) + H5 - L5 + K5 + Z4, 0), MAX(Y4 + IF(MONTH(A5)=12, P5+V5, 0) + H5 - L5, 0) ) ) -> 10920.696 | Z5: =IFS( B5<55, MIN( IF(AA4 >= VLOOKUP(YEAR(A5), Lookup!$Q:$R, 2), Z4 + IF(MONTH(A5)=12, Q5+W5, 0) + I5 + AA4 + IF(MONTH(A5)=12, R5+X5, 0) - VLOOKUP(YEAR(A5), Lookup!$Q:$R, 2) + J5, Z4 + IF(MONTH(A5)=12, Q5+W5, 0) + I5 ), VLOOKUP(YEAR(A5), Lookup!$K:$M, 3) ), B5=55, IF(Z4 >= AD5, Z4 - AD5, 0), B5>55, 0 ) -> 3939.448 | AA5: =IFS( B5<65, IF(AA4+J5 < VLOOKUP(YEAR(A5), Lookup!$Q:$R, 2), AA4 + IF(MONTH(A5)=12, R4+X4, 0) + J5, MIN( AA4 + IF(MONTH(A5)=12, R4+X4, 0) + J5 , VLOOKUP(YEAR(A5), Lookup!$Q:$R, 2) ) ), B5>=65, IF(AA4+J5 < VLOOKUP(questions!$C$5, Lookup!$Q:$R, 2), AA4 + IF(MONTH(A5)=12, R4+X4, 0) + J5 , MIN( AA4 + IF(MONTH(A5)=12, R4+X4, 0) + J5, VLOOKUP(questions!$C$5, Lookup!$Q:$R, 2) ) ) ) -> 4419.856 | AB5: =IFS( B5<55, 0, B5=55, MIN(Y4+Z4, AD5), B5>55, IF(AB4 < $AH$7, MIN(AB4 + IF(MONTH(A5)=12, Q5+W5, 0) + K5, $AH$7), AB4 + IF(MONTH(A5)=12, Q5+W5, 0) + K5 ) ) -> 0 | AC5: {=IFS(B5<66, XLOOKUP(year(A5),Lookup!$K$13:$K1000,Lookup!$L$13:$L1000,"missing",,1),B5>65,XLOOKUP(questions!$C$5,Lookup!$K$13:$K1000,Lookup!$L$13:$L1000,"missing",,1))} -> 110200 | AD5: {=IFS(B5<66, XLOOKUP(year(A5),Lookup!$K$13:$K1000,Lookup!$M$13:$M1000,"missing",,1),B5>65, XLOOKUP(questions!$C$5,Lookup!$K$13:$K1000,Lookup!$M$13:$M1000,"missing",,1))} -> 220400 | AE5: {=IFS(B5<66, XLOOKUP(year(A5),Lookup!$K$13:$K1000,Lookup!$N$13:$N1000,"missing",,1),B5>65,XLOOKUP(questions!$C$5,Lookup!$K$13:$K1000,Lookup!$N$13:$N1000,"missing",,1))} -> 440800 | AG5: Ordinary Account (OA) | AH5: Special Account (SA) | AI5: Medisave Account (MA) | AJ5: Total
A6: =eomonth(EDATE(A5,1),0) -> 46203 | B6: =round(YEARFRAC(EOMONTH(questions!$C$3, 0),A6,1),2) -> 27.58 | C6: =IF(B6<questions!$C$6,if(MONTH(A6)=1,C5*(1+questions!$C$12),C5),0) -> 10000 | D6: =IF(MONTH(A6)=12,C6*questions!$C$11,0) -> 0 | E6: =MIN(C6,IF(YEAR(A6)=2025,7600,8000)) -> 8000 | F6: =MIN(102000-E6*12,D6) -> 0 | G6: {=if(YEAR(A6)=2025,XLOOKUP(B6,Lookup!$A$3:$A$7,Lookup!$D$3:$D$7,,1)*SUM(E6:F6), XLOOKUP(B6,Lookup!$A$14:$A$18,Lookup!$D$14:$D$18,,1)*SUM(E6:F6))} -> 2960 | H6: {=if(YEAR(A6)=2025,XLOOKUP(B6,Lookup!$F$3:$F$10,Lookup!$G$3:$G$10,,1)*G6, XLOOKUP(B6,Lookup!$F$14:$F$21,Lookup!$G$14:$G$21,,1)*G6)} -> 1840.232 | I6: {=if(B6<55, if(YEAR(A6)=2025,XLOOKUP(B6,Lookup!$F$3:$F$10,Lookup!$H$3:$H$10,,1)*G6, XLOOKUP(B6,Lookup!$F$14:$F$21,Lookup!$H$14:$H$21,,1)*G6),0)} -> 479.816 | J6: {=if(YEAR(A6)=2025,XLOOKUP(B6,Lookup!$F$3:$F$10,Lookup!$I$3:$I$10,,1)*G6, XLOOKUP(B6,Lookup!$F$14:$F$21,Lookup!$I$14:$I$21,,1)*G6)} -> 639.952 | K6: {=if(B6>54, if(YEAR(A6)=2025,XLOOKUP(B6,Lookup!$F$3:$F$10,Lookup!$H$3:$H$10,,1)*G6, XLOOKUP(B6,Lookup!$F$14:$F$21,Lookup!$H$14:$H$21,,1)*G6),0)} -> 0 | L6: =IF(and(A6<questions!$C$19,questions!$C$18="yes"),questions!$C$20,0) -> 700 | M6: =(Y5+H6)*Lookup!A$26/12 -> 26.585267 | N6: =if(B6<55, (Z5+I6)*Lookup!B$26/12, (AB5+K6)*Lookup!B$26/12) -> 14.73088 | O6: =(AA5+J6)*Lookup!C$26/12 -> 16.866027 | P6: =IF(year(A6)=year(A5), P5+M6, M6) -> 92.088167 | Q6: =IF(year(A6)=year(A5), Q5+N6, N6) -> 49.3272 | R6: =IF(year(A6)=year(A5), R5+O6, O6) -> 54.665067 | S6: =if(B6<55,min(20000,Y5)*0.01/12,min(20000,Y5)*0.02/12) -> 9.10058 | T6: =if(B6<=55,min(60000-min(20000,Y5),Z5)*0.01/12,min(30000-min(20000,Y5),AB5)*0.02/12+min(30000,AB5)*0.01/12) -> 3.2828733 | U6: =if(B6<55,min(60000-min(60000-min(20000,Y5),Z5)-min(20000,Y5),AA5)*0.01/12,min(30000-min(30000-min(20000,Y5),AB5)-min(20000,Y5),AA5)*0.02/12+min(30000-min(30000-min(20000,Y5),AB5)-min(20000,Y5),AA5)*0.01/12) -> 3.6832133 | V6: =IF(year($A6)=year($A5), V5+S6, S6) -> 30.70116 | W6: =IF(year($A6)=year($A5), W5+T6, T6) -> 10.732413 | X6: =IF(year($A6)=year($A5), X5+U6, U6) -> 11.533093 | Y6: =IFS( B6<55, MAX( Y5 + IF(MONTH(A6)=12, P6+V6, 0) + H6 - L6 + MAX(0, IF(AA5 >= VLOOKUP(YEAR(A6), Lookup!$Q:$R, 2), Z5 + IF(MONTH(A6)=12, Q6+W6, 0) + I6 + AA5 + IF(MONTH(A6)=12, R6+X6, 0) - VLOOKUP(YEAR(A6), Lookup!$Q:$R, 2) + J6, Z5 + IF(MONTH(A6)=12, Q6+W6, 0) + I6 ) - VLOOKUP(YEAR(A6), Lookup!$K:$M, 3) ), 0), B6=55, IF(Z5>=AD6, MAX(Y5 + IF(MONTH(A6)=12, P6+V6, 0) + H6 - L6, 0), MAX(MAX(0, Y5-(AD6-Z5)) + IF(MONTH(A6)=12, P6+V6, 0) + H6 - L6, 0) ), B6>55, IF(AB5>=$AH$7, MAX(Y5 + IF(MONTH(A6)=12, P6+V6, 0) + H6 - L6 + K6 + Z5, 0), MAX(Y5 + IF(MONTH(A6)=12, P6+V6, 0) + H6 - L6, 0) ) ) -> 12060.928 | Z6: =IFS( B6<55, MIN( IF(AA5 >= VLOOKUP(YEAR(A6), Lookup!$Q:$R, 2), Z5 + IF(MONTH(A6)=12, Q6+W6, 0) + I6 + AA5 + IF(MONTH(A6)=12, R6+X6, 0) - VLOOKUP(YEAR(A6), Lookup!$Q:$R, 2) + J6, Z5 + IF(MONTH(A6)=12, Q6+W6, 0) + I6 ), VLOOKUP(YEAR(A6), Lookup!$K:$M, 3) ), B6=55, IF(Z5 >= AD6, Z5 - AD6, 0), B6>55, 0 ) -> 4419.264 | AA6: =IFS( B6<65, IF(AA5+J6 < VLOOKUP(YEAR(A6), Lookup!$Q:$R, 2), AA5 + IF(MONTH(A6)=12, R5+X5, 0) + J6, MIN( AA5 + IF(MONTH(A6)=12, R5+X5, 0) + J6 , VLOOKUP(YEAR(A6), Lookup!$Q:$R, 2) ) ), B6>=65, IF(AA5+J6 < VLOOKUP(questions!$C$5, Lookup!$Q:$R, 2), AA5 + IF(MONTH(A6)=12, R5+X5, 0) + J6 , MIN( AA5 + IF(MONTH(A6)=12, R5+X5, 0) + J6, VLOOKUP(questions!$C$5, Lookup!$Q:$R, 2) ) ) ) -> 5059.808 | AB6: =IFS( B6<55, 0, B6=55, MIN(Y5+Z5, AD6), B6>55, IF(AB5 < $AH$7, MIN(AB5 + IF(MONTH(A6)=12, Q6+W6, 0) + K6, $AH$7), AB5 + IF(MONTH(A6)=12, Q6+W6, 0) + K6 ) ) -> 0 | AC6: {=IFS(B6<66, XLOOKUP(year(A6),Lookup!$K$13:$K1000,Lookup!$L$13:$L1000,"missing",,1),B6>65,XLOOKUP(questions!$C$5,Lookup!$K$13:$K1000,Lookup!$L$13:$L1000,"missing",,1))} -> 110200 | AD6: {=IFS(B6<66, XLOOKUP(year(A6),Lookup!$K$13:$K1000,Lookup!$M$13:$M1000,"missing",,1),B6>65, XLOOKUP(questions!$C$5,Lookup!$K$13:$K1000,Lookup!$M$13:$M1000,"missing",,1))} -> 220400 | AE6: {=IFS(B6<66, XLOOKUP(year(A6),Lookup!$K$13:$K1000,Lookup!$N$13:$N1000,"missing",,1),B6>65,XLOOKUP(questions!$C$5,Lookup!$K$13:$K1000,Lookup!$N$13:$N1000,"missing",,1))} -> 440800
A7: =eomonth(EDATE(A6,1),0) -> 46234 | B7: =round(YEARFRAC(EOMONTH(questions!$C$3, 0),A7,1),2) -> 27.67 | C7: =IF(B7<questions!$C$6,if(MONTH(A7)=1,C6*(1+questions!$C$12),C6),0) -> 10000 | D7: =IF(MONTH(A7)=12,C7*questions!$C$11,0) -> 0 | E7: =MIN(C7,IF(YEAR(A7)=2025,7600,8000)) -> 8000 | F7: =MIN(102000-E7*12,D7) -> 0 | G7: {=if(YEAR(A7)=2025,XLOOKUP(B7,Lookup!$A$3:$A$7,Lookup!$D$3:$D$7,,1)*SUM(E7:F7), XLOOKUP(B7,Lookup!$A$14:$A$18,Lookup!$D$14:$D$18,,1)*SUM(E7:F7))} -> 2960 | H7: {=if(YEAR(A7)=2025,XLOOKUP(B7,Lookup!$F$3:$F$10,Lookup!$G$3:$G$10,,1)*G7, XLOOKUP(B7,Lookup!$F$14:$F$21,Lookup!$G$14:$G$21,,1)*G7)} -> 1840.232 | I7: {=if(B7<55, if(YEAR(A7)=2025,XLOOKUP(B7,Lookup!$F$3:$F$10,Lookup!$H$3:$H$10,,1)*G7, XLOOKUP(B7,Lookup!$F$14:$F$21,Lookup!$H$14:$H$21,,1)*G7),0)} -> 479.816 | J7: {=if(YEAR(A7)=2025,XLOOKUP(B7,Lookup!$F$3:$F$10,Lookup!$I$3:$I$10,,1)*G7, XLOOKUP(B7,Lookup!$F$14:$F$21,Lookup!$I$14:$I$21,,1)*G7)} -> 639.952 | K7: {=if(B7>54, if(YEAR(A7)=2025,XLOOKUP(B7,Lookup!$F$3:$F$10,Lookup!$H$3:$H$10,,1)*G7, XLOOKUP(B7,Lookup!$F$14:$F$21,Lookup!$H$14:$H$21,,1)*G7),0)} -> 0 | L7: =IF(and(A7<questions!$C$19,questions!$C$18="yes"),questions!$C$20,0) -> 700 | M7: =(Y6+H7)*Lookup!A$26/12 -> 28.96075 | N7: =if(B7<55, (Z6+I7)*Lookup!B$26/12, (AB6+K7)*Lookup!B$26/12) -> 16.330267 | O7: =(AA6+J7)*Lookup!C$26/12 -> 18.9992 | P7: =IF(year(A7)=year(A6), P6+M7, M7) -> 121.04892 | Q7: =IF(year(A7)=year(A6), Q6+N7, N7) -> 65.657467 | R7: =IF(year(A7)=year(A6), R6+O7, O7) -> 73.664267 | S7: =if(B7<55,min(20000,Y6)*0.01/12,min(20000,Y6)*0.02/12) -> 10.050773 | T7: =if(B7<=55,min(60000-min(20000,Y6),Z6)*0.01/12,min(30000-min(20000,Y6),AB6)*0.02/12+min(30000,AB6)*0.01/12) -> 3.68272 | U7: =if(B7<55,min(60000-min(60000-min(20000,Y6),Z6)-min(20000,Y6),AA6)*0.01/12,min(30000-min(30000-min(20000,Y6),AB6)-min(20000,Y6),AA6)*0.02/12+min(30000-min(30000-min(20000,Y6),AB6)-min(20000,Y6),AA6)*0.01/12) -> 4.2165067 | V7: =IF(year($A7)=year($A6), V6+S7, S7) -> 40.751933 | W7: =IF(year($A7)=year($A6), W6+T7, T7) -> 14.415133 | X7: =IF(year($A7)=year($A6), X6+U7, U7) -> 15.7496 | Y7: =IFS( B7<55, MAX( Y6 + IF(MONTH(A7)=12, P7+V7, 0) + H7 - L7 + MAX(0, IF(AA6 >= VLOOKUP(YEAR(A7), Lookup!$Q:$R, 2), Z6 + IF(MONTH(A7)=12, Q7+W7, 0) + I7 + AA6 + IF(MONTH(A7)=12, R7+X7, 0) - VLOOKUP(YEAR(A7), Lookup!$Q:$R, 2) + J7, Z6 + IF(MONTH(A7)=12, Q7+W7, 0) + I7 ) - VLOOKUP(YEAR(A7), Lookup!$K:$M, 3) ), 0), B7=55, IF(Z6>=AD7, MAX(Y6 + IF(MONTH(A7)=12, P7+V7, 0) + H7 - L7, 0), MAX(MAX(0, Y6-(AD7-Z6)) + IF(MONTH(A7)=12, P7+V7, 0) + H7 - L7, 0) ), B7>55, IF(AB6>=$AH$7, MAX(Y6 + IF(MONTH(A7)=12, P7+V7, 0) + H7 - L7 + K7 + Z6, 0), MAX(Y6 + IF(MONTH(A7)=12, P7+V7, 0) + H7 - L7, 0) ) ) -> 13201.16 | Z7: =IFS( B7<55, MIN( IF(AA6 >= VLOOKUP(YEAR(A7), Lookup!$Q:$R, 2), Z6 + IF(MONTH(A7)=12, Q7+W7, 0) + I7 + AA6 + IF(MONTH(A7)=12, R7+X7, 0) - VLOOKUP(YEAR(A7), Lookup!$Q:$R, 2) + J7, Z6 + IF(MONTH(A7)=12, Q7+W7, 0) + I7 ), VLOOKUP(YEAR(A7), Lookup!$K:$M, 3) ), B7=55, IF(Z6 >= AD7, Z6 - AD7, 0), B7>55, 0 ) -> 4899.08 | AA7: =IFS( B7<65, IF(AA6+J7 < VLOOKUP(YEAR(A7), Lookup!$Q:$R, 2), AA6 + IF(MONTH(A7)=12, R6+X6, 0) + J7, MIN( AA6 + IF(MONTH(A7)=12, R6+X6, 0) + J7 , VLOOKUP(YEAR(A7), Lookup!$Q:$R, 2) ) ), B7>=65, IF(AA6+J7 < VLOOKUP(questions!$C$5, Lookup!$Q:$R, 2), AA6 + IF(MONTH(A7)=12, R6+X6, 0) + J7 , MIN( AA6 + IF(MONTH(A7)=12, R6+X6, 0) + J7, VLOOKUP(questions!$C$5, Lookup!$Q:$R, 2) ) ) ) -> 5699.76 | AB7: =IFS( B7<55, 0, B7=55, MIN(Y6+Z6, AD7), B7>55, IF(AB6 < $AH$7, MIN(AB6 + IF(MONTH(A7)=12, Q7+W7, 0) + K7, $AH$7), AB6 + IF(MONTH(A7)=12, Q7+W7, 0) + K7 ) ) -> 0 | AC7: {=IFS(B7<66, XLOOKUP(year(A7),Lookup!$K$13:$K1000,Lookup!$L$13:$L1000,"missing",,1),B7>65,XLOOKUP(questions!$C$5,Lookup!$K$13:$K1000,Lookup!$L$13:$L1000,"missing",,1))} -> 110200 | AD7: {=IFS(B7<66, XLOOKUP(year(A7),Lookup!$K$13:$K1000,Lookup!$M$13:$M1000,"missing",,1),B7>65, XLOOKUP(questions!$C$5,Lookup!$K$13:$K1000,Lookup!$M$13:$M1000,"missing",,1))} -> 220400 | AE7: {=IFS(B7<66, XLOOKUP(year(A7),Lookup!$K$13:$K1000,Lookup!$N$13:$N1000,"missing",,1),B7>65,XLOOKUP(questions!$C$5,Lookup!$K$13:$K1000,Lookup!$N$13:$N1000,"missing",,1))} -> 440800 | AG7: {=XLOOKUP(questions!C4,Lookup!$K$3:$K1000,Lookup!$L$3:$L1000,"missing",,1)} -> 279083.87 | AH7: {=XLOOKUP(questions!C4,Lookup!$K$3:$K1000,Lookup!$M$3:$M1000,"missing",,1)} -> 558167.74 | AI7: {=XLOOKUP(questions!C4,Lookup!$K$3:$K1000,Lookup!$N$3:$N1000,"missing",,1)} -> 1116335.5
A8: =eomonth(EDATE(A7,1),0) -> 46265 | B8: =round(YEARFRAC(EOMONTH(questions!$C$3, 0),A8,1),2) -> 27.75 | C8: =IF(B8<questions!$C$6,if(MONTH(A8)=1,C7*(1+questions!$C$12),C7),0) -> 10000 | D8: =IF(MONTH(A8)=12,C8*questions!$C$11,0) -> 0 | E8: =MIN(C8,IF(YEAR(A8)=2025,7600,8000)) -> 8000 | F8: =MIN(102000-E8*12,D8) -> 0 | G8: {=if(YEAR(A8)=2025,XLOOKUP(B8,Lookup!$A$3:$A$7,Lookup!$D$3:$D$7,,1)*SUM(E8:F8), XLOOKUP(B8,Lookup!$A$14:$A$18,Lookup!$D$14:$D$18,,1)*SUM(E8:F8))} -> 2960 | H8: {=if(YEAR(A8)=2025,XLOOKUP(B8,Lookup!$F$3:$F$10,Lookup!$G$3:$G$10,,1)*G8, XLOOKUP(B8,Lookup!$F$14:$F$21,Lookup!$G$14:$G$21,,1)*G8)} -> 1840.232 | I8: {=if(B8<55, if(YEAR(A8)=2025,XLOOKUP(B8,Lookup!$F$3:$F$10,Lookup!$H$3:$H$10,,1)*G8, XLOOKUP(B8,Lookup!$F$14:$F$21,Lookup!$H$14:$H$21,,1)*G8),0)} -> 479.816 | J8: {=if(YEAR(A8)=2025,XLOOKUP(B8,Lookup!$F$3:$F$10,Lookup!$I$3:$I$10,,1)*G8, XLOOKUP(B8,Lookup!$F$14:$F$21,Lookup!$I$14:$I$21,,1)*G8)} -> 639.952 | K8: {=if(B8>54, if(YEAR(A8)=2025,XLOOKUP(B8,Lookup!$F$3:$F$10,Lookup!$H$3:$H$10,,1)*G8, XLOOKUP(B8,Lookup!$F$14:$F$21,Lookup!$H$14:$H$21,,1)*G8),0)} -> 0 | L8: =IF(and(A8<questions!$C$19,questions!$C$18="yes"),questions!$C$20,0) -> 700 | M8: =(Y7+H8)*Lookup!A$26/12 -> 31.336233 | N8: =if(B8<55, (Z7+I8)*Lookup!B$26/12, (AB7+K8)*Lookup!B$26/12) -> 17.929653 | O8: =(AA7+J8)*Lookup!C$26/12 -> 21.132373 | P8: =IF(year(A8)=year(A7), P7+M8, M8) -> 152.38515 | Q8: =IF(year(A8)=year(A7), Q7+N8, N8) -> 83.58712 | R8: =IF(year(A8)=year(A7), R7+O8, O8) -> 94.79664 | S8: =if(B8<55,min(20000,Y7)*0.01/12,min(20000,Y7)*0.02/12) -> 11.000967 | T8: =if(B8<=55,min(60000-min(20000,Y7),Z7)*0.01/12,min(30000-min(20000,Y7),AB7)*0.02/12+min(30000,AB7)*0.01/12) -> 4.0825667 | U8: =if(B8<55,min(60000-min(60000-min(20000,Y7),Z7)-min(20000,Y7),AA7)*0.01/12,min(30000-min(30000-min(20000,Y7),AB7)-min(20000,Y7),AA7)*0.02/12+min(30000-min(30000-min(20000,Y7),AB7)-min(20000,Y7),AA7)*0.01/12) -> 4.7498 | V8: =IF(year($A8)=year($A7), V7+S8, S8) -> 51.7529 | W8: =IF(year($A8)=year($A7), W7+T8, T8) -> 18.4977 | X8: =IF(year($A8)=year($A7), X7+U8, U8) -> 20.4994 | Y8: =IFS( B8<55, MAX( Y7 + IF(MONTH(A8)=12, P8+V8, 0) + H8 - L8 + MAX(0, IF(AA7 >= VLOOKUP(YEAR(A8), Lookup!$Q:$R, 2), Z7 + IF(MONTH(A8)=12, Q8+W8, 0) + I8 + AA7 + IF(MONTH(A8)=12, R8+X8, 0) - VLOOKUP(YEAR(A8), Lookup!$Q:$R, 2) + J8, Z7 + IF(MONTH(A8)=12, Q8+W8, 0) + I8 ) - VLOOKUP(YEAR(A8), Lookup!$K:$M, 3) ), 0), B8=55, IF(Z7>=AD8, MAX(Y7 + IF(MONTH(A8)=12, P8+V8, 0) + H8 - L8, 0), MAX(MAX(0, Y7-(AD8-Z7)) + IF(MONTH(A8)=12, P8+V8, 0) + H8 - L8, 0) ), B8>55, IF(AB7>=$AH$7, MAX(Y7 + IF(MONTH(A8)=12, P8+V8, 0) + H8 - L8 + K8 + Z7, 0), MAX(Y7 + IF(MONTH(A8)=12, P8+V8, 0) + H8 - L8, 0) ) ) -> 14341.392 | Z8: =IFS( B8<55, MIN( IF(AA7 >= VLOOKUP(YEAR(A8), Lookup!$Q:$R, 2), Z7 + IF(MONTH(A8)=12, Q8+W8, 0) + I8 + AA7 + IF(MONTH(A8)=12, R8+X8, 0) - VLOOKUP(YEAR(A8), Lookup!$Q:$R, 2) + J8, Z7 + IF(MONTH(A8)=12, Q8+W8, 0) + I8 ), VLOOKUP(YEAR(A8), Lookup!$K:$M, 3) ), B8=55, IF(Z7 >= AD8, Z7 - AD8, 0), B8>55, 0 ) -> 5378.896 | AA8: =IFS( B8<65, IF(AA7+J8 < VLOOKUP(YEAR(A8), Lookup!$Q:$R, 2), AA7 + IF(MONTH(A8)=12, R7+X7, 0) + J8, MIN( AA7 + IF(MONTH(A8)=12, R7+X7, 0) + J8 , VLOOKUP(YEAR(A8), Lookup!$Q:$R, 2) ) ), B8>=65, IF(AA7+J8 < VLOOKUP(questions!$C$5, Lookup!$Q:$R, 2), AA7 + IF(MONTH(A8)=12, R7+X7, 0) + J8 , MIN( AA7 + IF(MONTH(A8)=12, R7+X7, 0) + J8, VLOOKUP(questions!$C$5, Lookup!$Q:$R, 2) ) ) ) -> 6339.712 | AB8: =IFS( B8<55, 0, B8=55, MIN(Y7+Z7, AD8), B8>55, IF(AB7 < $AH$7, MIN(AB7 + IF(MONTH(A8)=12, Q8+W8, 0) + K8, $AH$7), AB7 + IF(MONTH(A8)=12, Q8+W8, 0) + K8 ) ) -> 0 | AC8: {=IFS(B8<66, XLOOKUP(year(A8),Lookup!$K$13:$K1000,Lookup!$L$13:$L1000,"missing",,1),B8>65,XLOOKUP(questions!$C$5,Lookup!$K$13:$K1000,Lookup!$L$13:$L1000,"missing",,1))} -> 110200 | AD8: {=IFS(B8<66, XLOOKUP(year(A8),Lookup!$K$13:$K1000,Lookup!$M$13:$M1000,"missing",,1),B8>65, XLOOKUP(questions!$C$5,Lookup!$K$13:$K1000,Lookup!$M$13:$M1000,"missing",,1))} -> 220400 | AE8: {=IFS(B8<66, XLOOKUP(year(A8),Lookup!$K$13:$K1000,Lookup!$N$13:$N1000,"missing",,1),B8>65,XLOOKUP(questions!$C$5,Lookup!$K$13:$K1000,Lookup!$N$13:$N1000,"missing",,1))} -> 440800 | AG8: Basic Retirement Sum (BRS) | AH8: Full Retirement Sum (FRS) | AI8: Enhanced Retirement Sum (ERS)
A9: =eomonth(EDATE(A8,1),0) -> 46295 | B9: =round(YEARFRAC(EOMONTH(questions!$C$3, 0),A9,1),2) -> 27.83 | C9: =IF(B9<questions!$C$6,if(MONTH(A9)=1,C8*(1+questions!$C$12),C8),0) -> 10000 | D9: =IF(MONTH(A9)=12,C9*questions!$C$11,0) -> 0 | E9: =MIN(C9,IF(YEAR(A9)=2025,7600,8000)) -> 8000 | F9: =MIN(102000-E9*12,D9) -> 0 | G9: {=if(YEAR(A9)=2025,XLOOKUP(B9,Lookup!$A$3:$A$7,Lookup!$D$3:$D$7,,1)*SUM(E9:F9), XLOOKUP(B9,Lookup!$A$14:$A$18,Lookup!$D$14:$D$18,,1)*SUM(E9:F9))} -> 2960 | H9: {=if(YEAR(A9)=2025,XLOOKUP(B9,Lookup!$F$3:$F$10,Lookup!$G$3:$G$10,,1)*G9, XLOOKUP(B9,Lookup!$F$14:$F$21,Lookup!$G$14:$G$21,,1)*G9)} -> 1840.232 | I9: {=if(B9<55, if(YEAR(A9)=2025,XLOOKUP(B9,Lookup!$F$3:$F$10,Lookup!$H$3:$H$10,,1)*G9, XLOOKUP(B9,Lookup!$F$14:$F$21,Lookup!$H$14:$H$21,,1)*G9),0)} -> 479.816 | J9: {=if(YEAR(A9)=2025,XLOOKUP(B9,Lookup!$F$3:$F$10,Lookup!$I$3:$I$10,,1)*G9, XLOOKUP(B9,Lookup!$F$14:$F$21,Lookup!$I$14:$I$21,,1)*G9)} -> 639.952 | K9: {=if(B9>54, if(YEAR(A9)=2025,XLOOKUP(B9,Lookup!$F$3:$F$10,Lookup!$H$3:$H$10,,1)*G9, XLOOKUP(B9,Lookup!$F$14:$F$21,Lookup!$H$14:$H$21,,1)*G9),0)} -> 0 | L9: =IF(and(A9<questions!$C$19,questions!$C$18="yes"),questions!$C$20,0) -> 700 | M9: =(Y8+H9)*Lookup!A$26/12 -> 33.711717 | N9: =if(B9<55, (Z8+I9)*Lookup!B$26/12, (AB8+K9)*Lookup!B$26/12) -> 19.52904 | O9: =(AA8+J9)*Lookup!C$26/12 -> 23.265547 | P9: =IF(year(A9)=year(A8), P8+M9, M9) -> 186.09687 | Q9: =IF(year(A9)=year(A8), Q8+N9, N9) -> 103.11616 | R9: =IF(year(A9)=year(A8), R8+O9, O9) -> 118.06219 | S9: =if(B9<55,min(20000,Y8)*0.01/12,min(20000,Y8)*0.02/12) -> 11.95116 | T9: =if(B9<=55,min(60000-min(20000,Y8),Z8)*0.01/12,min(30000-min(20000,Y8),AB8)*0.02/12+min(30000,AB8)*0.01/12) -> 4.4824133 | U9: =if(B9<55,min(60000-min(60000-min(20000,Y8),Z8)-min(20000,Y8),AA8)*0.01/12,min(30000-min(30000-min(20000,Y8),AB8)-min(20000,Y8),AA8)*0.02/12+min(30000-min(30000-min(20000,Y8),AB8)-min(20000,Y8),AA8)*0.01/12) -> 5.2830933 | V9: =IF(year($A9)=year($A8), V8+S9, S9) -> 63.70406 | W9: =IF(year($A9)=year($A8), W8+T9, T9) -> 22.980113 | X9: =IF(year($A9)=year($A8), X8+U9, U9) -> 25.782493 | Y9: =IFS( B9<55, MAX( Y8 + IF(MONTH(A9)=12, P9+V9, 0) + H9 - L9 + MAX(0, IF(AA8 >= VLOOKUP(YEAR(A9), Lookup!$Q:$R, 2), Z8 + IF(MONTH(A9)=12, Q9+W9, 0) + I9 + AA8 + IF(MONTH(A9)=12, R9+X9, 0) - VLOOKUP(YEAR(A9), Lookup!$Q:$R, 2) + J9, Z8 + IF(MONTH(A9)=12, Q9+W9, 0) + I9 ) - VLOOKUP(YEAR(A9), Lookup!$K:$M, 3) ), 0), B9=55, IF(Z8>=AD9, MAX(Y8 + IF(MONTH(A9)=12, P9+V9, 0) + H9 - L9, 0), MAX(MAX(0, Y8-(AD9-Z8)) + IF(MONTH(A9)=12, P9+V9, 0) + H9 - L9, 0) ), B9>55, IF(AB8>=$AH$7, MAX(Y8 + IF(MONTH(A9)=12, P9+V9, 0) + H9 - L9 + K9 + Z8, 0), MAX(Y8 + IF(MONTH(A9)=12, P9+V9, 0) + H9 - L9, 0) ) ) -> 15481.624 | Z9: =IFS( B9<55, MIN( IF(AA8 >= VLOOKUP(YEAR(A9), Lookup!$Q:$R, 2), Z8 + IF(MONTH(A9)=12, Q9+W9, 0) + I9 + AA8 + IF(MONTH(A9)=12, R9+X9, 0) - VLOOKUP(YEAR(A9), Lookup!$Q:$R, 2) + J9, Z8 + IF(MONTH(A9)=12, Q9+W9, 0) + I9 ), VLOOKUP(YEAR(A9), Lookup!$K:$M, 3) ), B9=55, IF(Z8 >= AD9, Z8 - AD9, 0), B9>55, 0 ) -> 5858.712 | AA9: =IFS( B9<65, IF(AA8+J9 < VLOOKUP(YEAR(A9), Lookup!$Q:$R, 2), AA8 + IF(MONTH(A9)=12, R8+X8, 0) + J9, MIN( AA8 + IF(MONTH(A9)=12, R8+X8, 0) + J9 , VLOOKUP(YEAR(A9), Lookup!$Q:$R, 2) ) ), B9>=65, IF(AA8+J9 < VLOOKUP(questions!$C$5, Lookup!$Q:$R, 2), AA8 + IF(MONTH(A9)=12, R8+X8, 0) + J9 , MIN( AA8 + IF(MONTH(A9)=12, R8+X8, 0) + J9, VLOOKUP(questions!$C$5, Lookup!$Q:$R, 2) ) ) ) -> 6979.664 | AB9: =IFS( B9<55, 0, B9=55, MIN(Y8+Z8, AD9), B9>55, IF(AB8 < $AH$7, MIN(AB8 + IF(MONTH(A9)=12, Q9+W9, 0) + K9, $AH$7), AB8 + IF(MONTH(A9)=12, Q9+W9, 0) + K9 ) ) -> 0 | AC9: {=IFS(B9<66, XLOOKUP(year(A9),Lookup!$K$13:$K1000,Lookup!$L$13:$L1000,"missing",,1),B9>65,XLOOKUP(questions!$C$5,Lookup!$K$13:$K1000,Lookup!$L$13:$L1000,"missing",,1))} -> 110200 | AD9: {=IFS(B9<66, XLOOKUP(year(A9),Lookup!$K$13:$K1000,Lookup!$M$13:$M1000,"missing",,1),B9>65, XLOOKUP(questions!$C$5,Lookup!$K$13:$K1000,Lookup!$M$13:$M1000,"missing",,1))} -> 220400 | AE9: {=IFS(B9<66, XLOOKUP(year(A9),Lookup!$K$13:$K1000,Lookup!$N$13:$N1000,"missing",,1),B9>65,XLOOKUP(questions!$C$5,Lookup!$K$13:$K1000,Lookup!$N$13:$N1000,"missing",,1))} -> 440800
A10: =eomonth(EDATE(A9,1),0) -> 46326 | B10: =round(YEARFRAC(EOMONTH(questions!$C$3, 0),A10,1),2) -> 27.92 | C10: =IF(B10<questions!$C$6,if(MONTH(A10)=1,C9*(1+questions!$C$12),C9),0) -> 10000 | D10: =IF(MONTH(A10)=12,C10*questions!$C$11,0) -> 0 | E10: =MIN(C10,IF(YEAR(A10)=2025,7600,8000)) -> 8000 | F10: =MIN(102000-E10*12,D10) -> 0 | G10: {=if(YEAR(A10)=2025,XLOOKUP(B10,Lookup!$A$3:$A$7,Lookup!$D$3:$D$7,,1)*SUM(E10:F10), XLOOKUP(B10,Lookup!$A$14:$A$18,Lookup!$D$14:$D$18,,1)*SUM(E10:F10))} -> 2960 | H10: {=if(YEAR(A10)=2025,XLOOKUP(B10,Lookup!$F$3:$F$10,Lookup!$G$3:$G$10,,1)*G10, XLOOKUP(B10,Lookup!$F$14:$F$21,Lookup!$G$14:$G$21,,1)*G10)} -> 1840.232 | I10: {=if(B10<55, if(YEAR(A10)=2025,XLOOKUP(B10,Lookup!$F$3:$F$10,Lookup!$H$3:$H$10,,1)*G10, XLOOKUP(B10,Lookup!$F$14:$F$21,Lookup!$H$14:$H$21,,1)*G10),0)} -> 479.816 | J10: {=if(YEAR(A10)=2025,XLOOKUP(B10,Lookup!$F$3:$F$10,Lookup!$I$3:$I$10,,1)*G10, XLOOKUP(B10,Lookup!$F$14:$F$21,Lookup!$I$14:$I$21,,1)*G10)} -> 639.952 | K10: {=if(B10>54, if(YEAR(A10)=2025,XLOOKUP(B10,Lookup!$F$3:$F$10,Lookup!$H$3:$H$10,,1)*G10, XLOOKUP(B10,Lookup!$F$14:$F$21,Lookup!$H$14:$H$21,,1)*G10),0)} -> 0 | L10: =IF(and(A10<questions!$C$19,questions!$C$18="yes"),questions!$C$20,0) -> 700 | M10: =(Y9+H10)*Lookup!A$26/12 -> 36.0872 | N10: =if(B10<55, (Z9+I10)*Lookup!B$26/12, (AB9+K10)*Lookup!B$26/12) -> 21.128427 | O10: =(AA9+J10)*Lookup!C$26/12 -> 25.39872 | P10: =IF(year(A10)=year(A9), P9+M10, M10) -> 222.18407 | Q10: =IF(year(A10)=year(A9), Q9+N10, N10) -> 124.24459 | R10: =IF(year(A10)=year(A9), R9+O10, O10) -> 143.46091 | S10: =if(B10<55,min(20000,Y9)*0.01/12,min(20000,Y9)*0.02/12) -> 12.901353 | T10: =if(B10<=55,min(60000-min(20000,Y9),Z9)*0.01/12,min(30000-min(20000,Y9),AB9)*0.02/12+min(30000,AB9)*0.01/12) -> 4.88226 | U10: =if(B10<55,min(60000-min(60000-min(20000,Y9),Z9)-min(20000,Y9),AA9)*0.01/12,min(30000-min(30000-min(20000,Y9),AB9)-min(20000,Y9),AA9)*0.02/12+min(30000-min(30000-min(20000,Y9),AB9)-min(20000,Y9),AA9)*0.01/12) -> 5.8163867 | V10: =IF(year($A10)=year($A9), V9+S10, S10) -> 76.605413 | W10: =IF(year($A10)=year($A9), W9+T10, T10) -> 27.862373 | X10: =IF(year($A10)=year($A9), X9+U10, U10) -> 31.59888 | Y10: =IFS( B10<55, MAX( Y9 + IF(MONTH(A10)=12, P10+V10, 0) + H10 - L10 + MAX(0, IF(AA9 >= VLOOKUP(YEAR(A10), Lookup!$Q:$R, 2), Z9 + IF(MONTH(A10)=12, Q10+W10, 0) + I10 + AA9 + IF(MONTH(A10)=12, R10+X10, 0) - VLOOKUP(YEAR(A10), Lookup!$Q:$R, 2) + J10, Z9 + IF(MONTH(A10)=12, Q10+W10, 0) + I10 ) - VLOOKUP(YEAR(A10), Lookup!$K:$M, 3) ), 0), B10=55, IF(Z9>=AD10, MAX(Y9 + IF(MONTH(A10)=12, P10+V10, 0) + H10 - L10, 0), MAX(MAX(0, Y9-(AD10-Z9)) + IF(MONTH(A10)=12, P10+V10, 0) + H10 - L10, 0) ), B10>55, IF(AB9>=$AH$7, MAX(Y9 + IF(MONTH(A10)=12, P10+V10, 0) + H10 - L10 + K10 + Z9, 0), MAX(Y9 + IF(MONTH(A10)=12, P10+V10, 0) + H10 - L10, 0) ) ) -> 16621.856 | Z10: =IFS( B10<55, MIN( IF(AA9 >= VLOOKUP(YEAR(A10), Lookup!$Q:$R, 2), Z9 + IF(MONTH(A10)=12, Q10+W10, 0) + I10 + AA9 + IF(MONTH(A10)=12, R10+X10, 0) - VLOOKUP(YEAR(A10), Lookup!$Q:$R, 2) + J10, Z9 + IF(MONTH(A10)=12, Q10+W10, 0) + I10 ), VLOOKUP(YEAR(A10), Lookup!$K:$M, 3) ), B10=55, IF(Z9 >= AD10, Z9 - AD10, 0), B10>55, 0 ) -> 6338.528 | AA10: =IFS( B10<65, IF(AA9+J10 < VLOOKUP(YEAR(A10), Lookup!$Q:$R, 2), AA9 + IF(MONTH(A10)=12, R9+X9, 0) + J10, MIN( AA9 + IF(MONTH(A10)=12, R9+X9, 0) + J10 , VLOOKUP(YEAR(A10), Lookup!$Q:$R, 2) ) ), B10>=65, IF(AA9+J10 < VLOOKUP(questions!$C$5, Lookup!$Q:$R, 2), AA9 + IF(MONTH(A10)=12, R9+X9, 0) + J10 , MIN( AA9 + IF(MONTH(A10)=12, R9+X9, 0) + J10, VLOOKUP(questions!$C$5, Lookup!$Q:$R, 2) ) ) ) -> 7619.616 | AB10: =IFS( B10<55, 0, B10=55, MIN(Y9+Z9, AD10), B10>55, IF(AB9 < $AH$7, MIN(AB9 + IF(MONTH(A10)=12, Q10+W10, 0) + K10, $AH$7), AB9 + IF(MONTH(A10)=12, Q10+W10, 0) + K10 ) ) -> 0 | AC10: {=IFS(B10<66, XLOOKUP(year(A10),Lookup!$K$13:$K1000,Lookup!$L$13:$L1000,"missing",,1),B10>65,XLOOKUP(questions!$C$5,Lookup!$K$13:$K1000,Lookup!$L$13:$L1000,"missing",,1))} -> 110200 | AD10: {=IFS(B10<66, XLOOKUP(year(A10),Lookup!$K$13:$K1000,Lookup!$M$13:$M1000,"missing",,1),B10>65, XLOOKUP(questions!$C$5,Lookup!$K$13:$K1000,Lookup!$M$13:$M1000,"missing",,1))} -> 220400 | AE10: {=IFS(B10<66, XLOOKUP(year(A10),Lookup!$K$13:$K1000,Lookup!$N$13:$N1000,"missing",,1),B10>65,XLOOKUP(questions!$C$5,Lookup!$K$13:$K1000,Lookup!$N$13:$N1000,"missing",,1))} -> 440800
A11: =eomonth(EDATE(A10,1),0) -> 46356 | B11: =round(YEARFRAC(EOMONTH(questions!$C$3, 0),A11,1),2) -> 28 | C11: =IF(B11<questions!$C$6,if(MONTH(A11)=1,C10*(1+questions!$C$12),C10),0) -> 10000 | D11: =IF(MONTH(A11)=12,C11*questions!$C$11,0) -> 0 | E11: =MIN(C11,IF(YEAR(A11)=2025,7600,8000)) -> 8000 | F11: =MIN(102000-E11*12,D11) -> 0 | G11: {=if(YEAR(A11)=2025,XLOOKUP(B11,Lookup!$A$3:$A$7,Lookup!$D$3:$D$7,,1)*SUM(E11:F11), XLOOKUP(B11,Lookup!$A$14:$A$18,Lookup!$D$14:$D$18,,1)*SUM(E11:F11))} -> 2960 | H11: {=if(YEAR(A11)=2025,XLOOKUP(B11,Lookup!$F$3:$F$10,Lookup!$G$3:$G$10,,1)*G11, XLOOKUP(B11,Lookup!$F$14:$F$21,Lookup!$G$14:$G$21,,1)*G11)} -> 1840.232 | I11: {=if(B11<55, if(YEAR(A11)=2025,XLOOKUP(B11,Lookup!$F$3:$F$10,Lookup!$H$3:$H$10,,1)*G11, XLOOKUP(B11,Lookup!$F$14:$F$21,Lookup!$H$14:$H$21,,1)*G11),0)} -> 479.816 | J11: {=if(YEAR(A11)=2025,XLOOKUP(B11,Lookup!$F$3:$F$10,Lookup!$I$3:$I$10,,1)*G11, XLOOKUP(B11,Lookup!$F$14:$F$21,Lookup!$I$14:$I$21,,1)*G11)} -> 639.952 | K11: {=if(B11>54, if(YEAR(A11)=2025,XLOOKUP(B11,Lookup!$F$3:$F$10,Lookup!$H$3:$H$10,,1)*G11, XLOOKUP(B11,Lookup!$F$14:$F$21,Lookup!$H$14:$H$21,,1)*G11),0)} -> 0 | L11: =IF(and(A11<questions!$C$19,questions!$C$18="yes"),questions!$C$20,0) -> 700 | M11: =(Y10+H11)*Lookup!A$26/12 -> 38.462683 | N11: =if(B11<55, (Z10+I11)*Lookup!B$26/12, (AB10+K11)*Lookup!B$26/12) -> 22.727813 | O11: =(AA10+J11)*Lookup!C$26/12 -> 27.531893 | P11: =IF(year(A11)=year(A10), P10+M11, M11) -> 260.64675 | Q11: =IF(year(A11)=year(A10), Q10+N11, N11) -> 146.9724 | R11: =IF(year(A11)=year(A10), R10+O11, O11) -> 170.9928 | S11: =if(B11<55,min(20000,Y10)*0.01/12,min(20000,Y10)*0.02/12) -> 13.851547 | T11: =if(B11<=55,min(60000-min(20000,Y10),Z10)*0.01/12,min(30000-min(20000,Y10),AB10)*0.02/12+min(30000,AB10)*0.01/12) -> 5.2821067 | U11: =if(B11<55,min(60000-min(60000-min(20000,Y10),Z10)-min(20000,Y10),AA10)*0.01/12,min(30000-min(30000-min(20000,Y10),AB10)-min(20000,Y10),AA10)*0.02/12+min(30000-min(30000-min(20000,Y10),AB10)-min(20000,Y10),AA10)*0.01/12) -> 6.34968 | V11: =IF(year($A11)=year($A10), V10+S11, S11) -> 90.45696 | W11: =IF(year($A11)=year($A10), W10+T11, T11) -> 33.14448 | X11: =IF(year($A11)=year($A10), X10+U11, U11) -> 37.94856 | Y11: =IFS( B11<55, MAX( Y10 + IF(MONTH(A11)=12, P11+V11, 0) + H11 - L11 + MAX(0, IF(AA10 >= VLOOKUP(YEAR(A11), Lookup!$Q:$R, 2), Z10 + IF(MONTH(A11)=12, Q11+W11, 0) + I11 + AA10 + IF(MONTH(A11)=12, R11+X11, 0) - VLOOKUP(YEAR(A11), Lookup!$Q:$R, 2) + J11, Z10 + IF(MONTH(A11)=12, Q11+W11, 0) + I11 ) - VLOOKUP(YEAR(A11), Lookup!$K:$M, 3) ), 0), B11=55, IF(Z10>=AD11, MAX(Y10 + IF(MONTH(A11)=12, P11+V11, 0) + H11 - L11, 0), MAX(MAX(0, Y10-(AD11-Z10)) + IF(MONTH(A11)=12, P11+V11, 0) + H11 - L11, 0) ), B11>55, IF(AB10>=$AH$7, MAX(Y10 + IF(MONTH(A11)=12, P11+V11, 0) + H11 - L11 + K11 + Z10, 0), MAX(Y10 + IF(MONTH(A11)=12, P11+V11, 0) + H11 - L11, 0) ) ) -> 17762.088 | Z11: =IFS( B11<55, MIN( IF(AA10 >= VLOOKUP(YEAR(A11), Lookup!$Q:$R, 2), Z10 + IF(MONTH(A11)=12, Q11+W11, 0) + I11 + AA10 + IF(MONTH(A11)=12, R11+X11, 0) - VLOOKUP(YEAR(A11), Lookup!$Q:$R, 2) + J11, Z10 + IF(MONTH(A11)=12, Q11+W11, 0) + I11 ), VLOOKUP(YEAR(A11), Lookup!$K:$M, 3) ), B11=55, IF(Z10 >= AD11, Z10 - AD11, 0), B11>55, 0 ) -> 6818.344 | AA11: =IFS( B11<65, IF(AA10+J11 < VLOOKUP(YEAR(A11), Lookup!$Q:$R, 2), AA10 + IF(MONTH(A11)=12, R10+X10, 0) + J11, MIN( AA10 + IF(MONTH(A11)=12, R10+X10, 0) + J11 , VLOOKUP(YEAR(A11), Lookup!$Q:$R, 2) ) ), B11>=65, IF(AA10+J11 < VLOOKUP(questions!$C$5, Lookup!$Q:$R, 2), AA10 + IF(MONTH(A11)=12, R10+X10, 0) + J11 , MIN( AA10 + IF(MONTH(A11)=12, R10+X10, 0) + J11, VLOOKUP(questions!$C$5, Lookup!$Q:$R, 2) ) ) ) -> 8259.568 | AB11: =IFS( B11<55, 0, B11=55, MIN(Y10+Z10, AD11), B11>55, IF(AB10 < $AH$7, MIN(AB10 + IF(MONTH(A11)=12, Q11+W11, 0) + K11, $AH$7), AB10 + IF(MONTH(A11)=12, Q11+W11, 0) + K11 ) ) -> 0 | AC11: {=IFS(B11<66, XLOOKUP(year(A11),Lookup!$K$13:$K1000,Lookup!$L$13:$L1000,"missing",,1),B11>65,XLOOKUP(questions!$C$5,Lookup!$K$13:$K1000,Lookup!$L$13:$L1000,"missing",,1))} -> 110200 | AD11: {=IFS(B11<66, XLOOKUP(year(A11),Lookup!$K$13:$K1000,Lookup!$M$13:$M1000,"missing",,1),B11>65, XLOOKUP(questions!$C$5,Lookup!$K$13:$K1000,Lookup!$M$13:$M1000,"missing",,1))} -> 220400 | AE11: {=IFS(B11<66, XLOOKUP(year(A11),Lookup!$K$13:$K1000,Lookup!$N$13:$N1000,"missing",,1),B11>65,XLOOKUP(questions!$C$5,Lookup!$K$13:$K1000,Lookup!$N$13:$N1000,"missing",,1))} -> 440800
A12: =eomonth(EDATE(A11,1),0) -> 46387 | B12: =round(YEARFRAC(EOMONTH(questions!$C$3, 0),A12,1),2) -> 28.08 | C12: =IF(B12<questions!$C$6,if(MONTH(A12)=1,C11*(1+questions!$C$12),C11),0) -> 10000 | D12: =IF(MONTH(A12)=12,C12*questions!$C$11,0) -> 10000 | E12: =MIN(C12,IF(YEAR(A12)=2025,7600,8000)) -> 8000 | F12: =MIN(102000-E12*12,D12) -> 6000 | G12: {=if(YEAR(A12)=2025,XLOOKUP(B12,Lookup!$A$3:$A$7,Lookup!$D$3:$D$7,,1)*SUM(E12:F12), XLOOKUP(B12,Lookup!$A$14:$A$18,Lookup!$D$14:$D$18,,1)*SUM(E12:F12))} -> 5180 | H12: {=if(YEAR(A12)=2025,XLOOKUP(B12,Lookup!$F$3:$F$10,Lookup!$G$3:$G$10,,1)*G12, XLOOKUP(B12,Lookup!$F$14:$F$21,Lookup!$G$14:$G$21,,1)*G12)} -> 3220.406 | I12: {=if(B12<55, if(YEAR(A12)=2025,XLOOKUP(B12,Lookup!$F$3:$F$10,Lookup!$H$3:$H$10,,1)*G12, XLOOKUP(B12,Lookup!$F$14:$F$21,Lookup!$H$14:$H$21,,1)*G12),0)} -> 839.678 | J12: {=if(YEAR(A12)=2025,XLOOKUP(B12,Lookup!$F$3:$F$10,Lookup!$I$3:$I$10,,1)*G12, XLOOKUP(B12,Lookup!$F$14:$F$21,Lookup!$I$14:$I$21,,1)*G12)} -> 1119.916 | K12: {=if(B12>54, if(YEAR(A12)=2025,XLOOKUP(B12,Lookup!$F$3:$F$10,Lookup!$H$3:$H$10,,1)*G12, XLOOKUP(B12,Lookup!$F$14:$F$21,Lookup!$H$14:$H$21,,1)*G12),0)} -> 0 | L12: =IF(and(A12<questions!$C$19,questions!$C$18="yes"),questions!$C$20,0) -> 700 | M12: =(Y11+H12)*Lookup!A$26/12 -> 43.713529 | N12: =if(B12<55, (Z11+I12)*Lookup!B$26/12, (AB11+K12)*Lookup!B$26/12) -> 25.52674 | O12: =(AA11+J12)*Lookup!C$26/12 -> 31.264947 | P12: =IF(year(A12)=year(A11), P11+M12, M12) -> 304.36028 | Q12: =IF(year(A12)=year(A11), Q11+N12, N12) -> 172.49914 | R12: =IF(year(A12)=year(A11), R11+O12, O12) -> 202.25775 | S12: =if(B12<55,min(20000,Y11)*0.01/12,min(20000,Y11)*0.02/12) -> 14.80174 | T12: =if(B12<=55,min(60000-min(20000,Y11),Z11)*0.01/12,min(30000-min(20000,Y11),AB11)*0.02/12+min(30000,AB11)*0.01/12) -> 5.6819533 | U12: =if(B12<55,min(60000-min(60000-min(20000,Y11),Z11)-min(20000,Y11),AA11)*0.01/12,min(30000-min(30000-min(20000,Y11),AB11)-min(20000,Y11),AA11)*0.02/12+min(30000-min(30000-min(20000,Y11),AB11)-min(20000,Y11),AA11)*0.01/12) -> 6.8829733 | V12: =IF(year($A12)=year($A11), V11+S12, S12) -> 105.2587 | W12: =IF(year($A12)=year($A11), W11+T12, T12) -> 38.826433 | X12: =IF(year($A12)=year($A11), X11+U12, U12) -> 44.831533 | Y12: =IFS( B12<55, MAX( Y11 + IF(MONTH(A12)=12, P12+V12, 0) + H12 - L12 + MAX(0, IF(AA11 >= VLOOKUP(YEAR(A12), Lookup!$Q:$R, 2), Z11 + IF(MONTH(A12)=12, Q12+W12, 0) + I12 + AA11 + IF(MONTH(A12)=12, R12+X12, 0) - VLOOKUP(YEAR(A12), Lookup!$Q:$R, 2) + J12, Z11 + IF(MONTH(A12)=12, Q12+W12, 0) + I12 ) - VLOOKUP(YEAR(A12), Lookup!$K:$M, 3) ), 0), B12=55, IF(Z11>=AD12, MAX(Y11 + IF(MONTH(A12)=12, P12+V12, 0) + H12 - L12, 0), MAX(MAX(0, Y11-(AD12-Z11)) + IF(MONTH(A12)=12, P12+V12, 0) + H12 - L12, 0) ), B12>55, IF(AB11>=$AH$7, MAX(Y11 + IF(MONTH(A12)=12, P12+V12, 0) + H12 - L12 + K12 + Z11, 0), MAX(Y11 + IF(MONTH(A12)=12, P12+V12, 0) + H12 - L12, 0) ) ) -> 20692.113 | Z12: =IFS( B12<55, MIN( IF(AA11 >= VLOOKUP(YEAR(A12), Lookup!$Q:$R, 2), Z11 + IF(MONTH(A12)=12, Q12+W12, 0) + I12 + AA11 + IF(MONTH(A12)=12, R12+X12, 0) - VLOOKUP(YEAR(A12), Lookup!$Q:$R, 2) + J12, Z11 + IF(MONTH(A12)=12, Q12+W12, 0) + I12 ), VLOOKUP(YEAR(A12), Lookup!$K:$M, 3) ), B12=55, IF(Z11 >= AD12, Z11 - AD12, 0), B12>55, 0 ) -> 7869.3476 | AA12: =IFS( B12<65, IF(AA11+J12 < VLOOKUP(YEAR(A12), Lookup!$Q:$R, 2), AA11 + IF(MONTH(A12)=12, R11+X11, 0) + J12, MIN( AA11 + IF(MONTH(A12)=12, R11+X11, 0) + J12 , VLOOKUP(YEAR(A12), Lookup!$Q:$R, 2) ) ), B12>=65, IF(AA11+J12 < VLOOKUP(questions!$C$5, Lookup!$Q:$R, 2), AA11 + IF(MONTH(A12)=12, R11+X11, 0) + J12 , MIN( AA11 + IF(MONTH(A12)=12, R11+X11, 0) + J12, VLOOKUP(questions!$C$5, Lookup!$Q:$R, 2) ) ) ) -> 9588.4254 | AB12: =IFS( B12<55, 0, B12=55, MIN(Y11+Z11, AD12), B12>55, IF(AB11 < $AH$7, MIN(AB11 + IF(MONTH(A12)=12, Q12+W12, 0) + K12, $AH$7), AB11 + IF(MONTH(A12)=12, Q12+W12, 0) + K12 ) ) -> 0 | AC12: {=IFS(B12<66, XLOOKUP(year(A12),Lookup!$K$13:$K1000,Lookup!$L$13:$L1000,"missing",,1),B12>65,XLOOKUP(questions!$C$5,Lookup!$K$13:$K1000,Lookup!$L$13:$L1000,"missing",,1))} -> 110200 | AD12: {=IFS(B12<66, XLOOKUP(year(A12),Lookup!$K$13:$K1000,Lookup!$M$13:$M1000,"missing",,1),B12>65, XLOOKUP(questions!$C$5,Lookup!$K$13:$K1000,Lookup!$M$13:$M1000,"missing",,1))} -> 220400 | AE12: {=IFS(B12<66, XLOOKUP(year(A12),Lookup!$K$13:$K1000,Lookup!$N$13:$N1000,"missing",,1),B12>65,XLOOKUP(questions!$C$5,Lookup!$K$13:$K1000,Lookup!$N$13:$N1000,"missing",,1))} -> 440800
A13: =eomonth(EDATE(A12,1),0) -> 46418 | B13: =round(YEARFRAC(EOMONTH(questions!$C$3, 0),A13,1),2) -> 28.17 | C13: =IF(B13<questions!$C$6,if(MONTH(A13)=1,C12*(1+questions!$C$12),C12),0) -> 10300 | D13: =IF(MONTH(A13)=12,C13*questions!$C$11,0) -> 0 | E13: =MIN(C13,IF(YEAR(A13)=2025,7600,8000)) -> 8000 | F13: =MIN(102000-E13*12,D13) -> 0 | G13: {=if(YEAR(A13)=2025,XLOOKUP(B13,Lookup!$A$3:$A$7,Lookup!$D$3:$D$7,,1)*SUM(E13:F13), XLOOKUP(B13,Lookup!$A$14:$A$18,Lookup!$D$14:$D$18,,1)*SUM(E13:F13))} -> 2960 | H13: {=if(YEAR(A13)=2025,XLOOKUP(B13,Lookup!$F$3:$F$10,Lookup!$G$3:$G$10,,1)*G13, XLOOKUP(B13,Lookup!$F$14:$F$21,Lookup!$G$14:$G$21,,1)*G13)} -> 1840.232 | I13: {=if(B13<55, if(YEAR(A13)=2025,XLOOKUP(B13,Lookup!$F$3:$F$10,Lookup!$H$3:$H$10,,1)*G13, XLOOKUP(B13,Lookup!$F$14:$F$21,Lookup!$H$14:$H$21,,1)*G13),0)} -> 479.816 | J13: {=if(YEAR(A13)=2025,XLOOKUP(B13,Lookup!$F$3:$F$10,Lookup!$I$3:$I$10,,1)*G13, XLOOKUP(B13,Lookup!$F$14:$F$21,Lookup!$I$14:$I$21,,1)*G13)} -> 639.952 | K13: {=if(B13>54, if(YEAR(A13)=2025,XLOOKUP(B13,Lookup!$F$3:$F$10,Lookup!$H$3:$H$10,,1)*G13, XLOOKUP(B13,Lookup!$F$14:$F$21,Lookup!$H$14:$H$21,,1)*G13),0)} -> 0 | L13: =IF(and(A13<questions!$C$19,questions!$C$18="yes"),questions!$C$20,0) -> 700 | M13: =(Y12+H13)*Lookup!A$26/12 -> 46.942385 | N13: =if(B13<55, (Z12+I13)*Lookup!B$26/12, (AB12+K13)*Lookup!B$26/12) -> 27.830545 | O13: =(AA12+J13)*Lookup!C$26/12 -> 34.094591 | P13: =IF(year(A13)=year(A12), P12+M13, M13) -> 46.942385 | Q13: =IF(year(A13)=year(A12), Q12+N13, N13) -> 27.830545 | R13: =IF(year(A13)=year(A12), R12+O13, O13) -> 34.094591 | S13: =if(B13<55,min(20000,Y12)*0.01/12,min(20000,Y12)*0.02/12) -> 16.666667 | T13: =if(B13<=55,min(60000-min(20000,Y12),Z12)*0.01/12,min(30000-min(20000,Y12),AB12)*0.02/12+min(30000,AB12)*0.01/12) -> 6.5577896 | U13: =if(B13<55,min(60000-min(60000-min(20000,Y12),Z12)-min(20000,Y12),AA12)*0.01/12,min(30000-min(30000-min(20000,Y12),AB12)-min(20000,Y12),AA12)*0.02/12+min(30000-min(30000-min(20000,Y12),AB12)-min(20000,Y12),AA12)*0.01/12) -> 7.9903545 | V13: =IF(year($A13)=year($A12), V12+S13, S13) -> 16.666667 | W13: =IF(year($A13)=year($A12), W12+T13, T13) -> 6.5577896 | X13: =IF(year($A13)=year($A12), X12+U13, U13) -> 7.9903545 | Y13: =IFS( B13<55, MAX( Y12 + IF(MONTH(A13)=12, P13+V13, 0) + H13 - L13 + MAX(0, IF(AA12 >= VLOOKUP(YEAR(A13), Lookup!$Q:$R, 2), Z12 + IF(MONTH(A13)=12, Q13+W13, 0) + I13 + AA12 + IF(MONTH(A13)=12, R13+X13, 0) - VLOOKUP(YEAR(A13), Lookup!$Q:$R, 2) + J13, Z12 + IF(MONTH(A13)=12, Q13+W13, 0) + I13 ) - VLOOKUP(YEAR(A13), Lookup!$K:$M, 3) ), 0), B13=55, IF(Z12>=AD13, MAX(Y12 + IF(MONTH(A13)=12, P13+V13, 0) + H13 - L13, 0), MAX(MAX(0, Y12-(AD13-Z12)) + IF(MONTH(A13)=12, P13+V13, 0) + H13 - L13, 0) ), B13>55, IF(AB12>=$AH$7, MAX(Y12 + IF(MONTH(A13)=12, P13+V13, 0) + H13 - L13 + K13 + Z12, 0), MAX(Y12 + IF(MONTH(A13)=12, P13+V13, 0) + H13 - L13, 0) ) ) -> 21832.345 | Z13: =IFS( B13<55, MIN( IF(AA12 >= VLOOKUP(YEAR(A13), Lookup!$Q:$R, 2), Z12 + IF(MONTH(A13)=12, Q13+W13, 0) + I13 + AA12 + IF(MONTH(A13)=12, R13+X13, 0) - VLOOKUP(YEAR(A13), Lookup!$Q:$R, 2) + J13, Z12 + IF(MONTH(A13)=12, Q13+W13, 0) + I13 ), VLOOKUP(YEAR(A13), Lookup!$K:$M, 3) ), B13=55, IF(Z12 >= AD13, Z12 - AD13, 0), B13>55, 0 ) -> 8349.1636 | AA13: =IFS( B13<65, IF(AA12+J13 < VLOOKUP(YEAR(A13), Lookup!$Q:$R, 2), AA12 + IF(MONTH(A13)=12, R12+X12, 0) + J13, MIN( AA12 + IF(MONTH(A13)=12, R12+X12, 0) + J13 , VLOOKUP(YEAR(A13), Lookup!$Q:$R, 2) ) ), B13>=65, IF(AA12+J13 < VLOOKUP(questions!$C$5, Lookup!$Q:$R, 2), AA12 + IF(MONTH(A13)=12, R12+X12, 0) + J13 , MIN( AA12 + IF(MONTH(A13)=12, R12+X12, 0) + J13, VLOOKUP(questions!$C$5, Lookup!$Q:$R, 2) ) ) ) -> 10228.377 | AB13: =IFS( B13<55, 0, B13=55, MIN(Y12+Z12, AD13), B13>55, IF(AB12 < $AH$7, MIN(AB12 + IF(MONTH(A13)=12, Q13+W13, 0) + K13, $AH$7), AB12 + IF(MONTH(A13)=12, Q13+W13, 0) + K13 ) ) -> 0 | AC13: {=IFS(B13<66, XLOOKUP(year(A13),Lookup!$K$13:$K1000,Lookup!$L$13:$L1000,"missing",,1),B13>65,XLOOKUP(questions!$C$5,Lookup!$K$13:$K1000,Lookup!$L$13:$L1000,"missing",,1))} -> 114100 | AD13: {=IFS(B13<66, XLOOKUP(year(A13),Lookup!$K$13:$K1000,Lookup!$M$13:$M1000,"missing",,1),B13>65, XLOOKUP(questions!$C$5,Lookup!$K$13:$K1000,Lookup!$M$13:$M1000,"missing",,1))} -> 228200 | AE13: {=IFS(B13<66, XLOOKUP(year(A13),Lookup!$K$13:$K1000,Lookup!$N$13:$N1000,"missing",,1),B13>65,XLOOKUP(questions!$C$5,Lookup!$K$13:$K1000,Lookup!$N$13:$N1000,"missing",,1))} -> 456400
A14: =eomonth(EDATE(A13,1),0) -> 46446 | B14: =round(YEARFRAC(EOMONTH(questions!$C$3, 0),A14,1),2) -> 28.25 | C14: =IF(B14<questions!$C$6,if(MONTH(A14)=1,C13*(1+questions!$C$12),C13),0) -> 10300 | D14: =IF(MONTH(A14)=12,C14*questions!$C$11,0) -> 0 | E14: =MIN(C14,IF(YEAR(A14)=2025,7600,8000)) -> 8000 | F14: =MIN(102000-E14*12,D14) -> 0 | G14: {=if(YEAR(A14)=2025,XLOOKUP(B14,Lookup!$A$3:$A$7,Lookup!$D$3:$D$7,,1)*SUM(E14:F14), XLOOKUP(B14,Lookup!$A$14:$A$18,Lookup!$D$14:$D$18,,1)*SUM(E14:F14))} -> 2960 | H14: {=if(YEAR(A14)=2025,XLOOKUP(B14,Lookup!$F$3:$F$10,Lookup!$G$3:$G$10,,1)*G14, XLOOKUP(B14,Lookup!$F$14:$F$21,Lookup!$G$14:$G$21,,1)*G14)} -> 1840.232 | I14: {=if(B14<55, if(YEAR(A14)=2025,XLOOKUP(B14,Lookup!$F$3:$F$10,Lookup!$H$3:$H$10,,1)*G14, XLOOKUP(B14,Lookup!$F$14:$F$21,Lookup!$H$14:$H$21,,1)*G14),0)} -> 479.816 | J14: {=if(YEAR(A14)=2025,XLOOKUP(B14,Lookup!$F$3:$F$10,Lookup!$I$3:$I$10,,1)*G14, XLOOKUP(B14,Lookup!$F$14:$F$21,Lookup!$I$14:$I$21,,1)*G14)} -> 639.952 | K14: {=if(B14>54, if(YEAR(A14)=2025,XLOOKUP(B14,Lookup!$F$3:$F$10,Lookup!$H$3:$H$10,,1)*G14, XLOOKUP(B14,Lookup!$F$14:$F$21,Lookup!$H$14:$H$21,,1)*G14),0)} -> 0 | L14: =IF(and(A14<questions!$C$19,questions!$C$18="yes"),questions!$C$20,0) -> 700 | M14: =(Y13+H14)*Lookup!A$26/12 -> 49.317869 | N14: =if(B14<55, (Z13+I14)*Lookup!B$26/12, (AB13+K14)*Lookup!B$26/12) -> 29.429932 | O14: =(AA13+J14)*Lookup!C$26/12 -> 36.227765 | P14: =IF(year(A14)=year(A13), P13+M14, M14) -> 96.260254 | Q14: =IF(year(A14)=year(A13), Q13+N14, N14) -> 57.260477 | R14: =IF(year(A14)=year(A13), R13+O14, O14) -> 70.322356 | S14: =if(B14<55,min(20000,Y13)*0.01/12,min(20000,Y13)*0.02/12) -> 16.666667 | T14: =if(B14<=55,min(60000-min(20000,Y13),Z13)*0.01/12,min(30000-min(20000,Y13),AB13)*0.02/12+min(30000,AB13)*0.01/12) -> 6.9576363 | U14: =if(B14<55,min(60000-min(60000-min(20000,Y13),Z13)-min(20000,Y13),AA13)*0.01/12,min(30000-min(30000-min(20000,Y13),AB13)-min(20000,Y13),AA13)*0.02/12+min(30000-min(30000-min(20000,Y13),AB13)-min(20000,Y13),AA13)*0.01/12) -> 8.5236478 | V14: =IF(year($A14)=year($A13), V13+S14, S14) -> 33.333333 | W14: =IF(year($A14)=year($A13), W13+T14, T14) -> 13.515426 | X14: =IF(year($A14)=year($A13), X13+U14, U14) -> 16.514002 | Y14: =IFS( B14<55, MAX( Y13 + IF(MONTH(A14)=12, P14+V14, 0) + H14 - L14 + MAX(0, IF(AA13 >= VLOOKUP(YEAR(A14), Lookup!$Q:$R, 2), Z13 + IF(MONTH(A14)=12, Q14+W14, 0) + I14 + AA13 + IF(MONTH(A14)=12, R14+X14, 0) - VLOOKUP(YEAR(A14), Lookup!$Q:$R, 2) + J14, Z13 + IF(MONTH(A14)=12, Q14+W14, 0) + I14 ) - VLOOKUP(YEAR(A14), Lookup!$K:$M, 3) ), 0), B14=55, IF(Z13>=AD14, MAX(Y13 + IF(MONTH(A14)=12, P14+V14, 0) + H14 - L14, 0), MAX(MAX(0, Y13-(AD14-Z13)) + IF(MONTH(A14)=12, P14+V14, 0) + H14 - L14, 0) ), B14>55, IF(AB13>=$AH$7, MAX(Y13 + IF(MONTH(A14)=12, P14+V14, 0) + H14 - L14 + K14 + Z13, 0), MAX(Y13 + IF(MONTH(A14)=12, P14+V14, 0) + H14 - L14, 0) ) ) -> 22972.577 | Z14: =IFS( B14<55, MIN( IF(AA13 >= VLOOKUP(YEAR(A14), Lookup!$Q:$R, 2), Z13 + IF(MONTH(A14)=12, Q14+W14, 0) + I14 + AA13 + IF(MONTH(A14)=12, R14+X14, 0) - VLOOKUP(YEAR(A14), Lookup!$Q:$R, 2) + J14, Z13 + IF(MONTH(A14)=12, Q14+W14, 0) + I14 ), VLOOKUP(YEAR(A14), Lookup!$K:$M, 3) ), B14=55, IF(Z13 >= AD14, Z13 - AD14, 0), B14>55, 0 ) -> 8828.9796 | AA14: =IFS( B14<65, IF(AA13+J14 < VLOOKUP(YEAR(A14), Lookup!$Q:$R, 2), AA13 + IF(MONTH(A14)=12, R13+X13, 0) + J14, MIN( AA13 + IF(MONTH(A14)=12, R13+X13, 0) + J14 , VLOOKUP(YEAR(A14), Lookup!$Q:$R, 2) ) ), B14>=65, IF(AA13+J14 < VLOOKUP(questions!$C$5, Lookup!$Q:$R, 2), AA13 + IF(MONTH(A14)=12, R13+X13, 0) + J14 , MIN( AA13 + IF(MONTH(A14)=12, R13+X13, 0) + J14, VLOOKUP(questions!$C$5, Lookup!$Q:$R, 2) ) ) ) -> 10868.329 | AB14: =IFS( B14<55, 0, B14=55, MIN(Y13+Z13, AD14), B14>55, IF(AB13 < $AH$7, MIN(AB13 + IF(MONTH(A14)=12, Q14+W14, 0) + K14, $AH$7), AB13 + IF(MONTH(A14)=12, Q14+W14, 0) + K14 ) ) -> 0 | AC14: {=IFS(B14<66, XLOOKUP(year(A14),Lookup!$K$13:$K1000,Lookup!$L$13:$L1000,"missing",,1),B14>65,XLOOKUP(questions!$C$5,Lookup!$K$13:$K1000,Lookup!$L$13:$L1000,"missing",,1))} -> 114100 | AD14: {=IFS(B14<66, XLOOKUP(year(A14),Lookup!$K$13:$K1000,Lookup!$M$13:$M1000,"missing",,1),B14>65, XLOOKUP(questions!$C$5,Lookup!$K$13:$K1000,Lookup!$M$13:$M1000,"missing",,1))} -> 228200 | AE14: {=IFS(B14<66, XLOOKUP(year(A14),Lookup!$K$13:$K1000,Lookup!$N$13:$N1000,"missing",,1),B14>65,XLOOKUP(questions!$C$5,Lookup!$K$13:$K1000,Lookup!$N$13:$N1000,"missing",,1))} -> 456400
A15: =eomonth(EDATE(A14,1),0) -> 46477 | B15: =round(YEARFRAC(EOMONTH(questions!$C$3, 0),A15,1),2) -> 28.33 | C15: =IF(B15<questions!$C$6,if(MONTH(A15)=1,C14*(1+questions!$C$12),C14),0) -> 10300 | D15: =IF(MONTH(A15)=12,C15*questions!$C$11,0) -> 0 | E15: =MIN(C15,IF(YEAR(A15)=2025,7600,8000)) -> 8000 | F15: =MIN(102000-E15*12,D15) -> 0 | G15: {=if(YEAR(A15)=2025,XLOOKUP(B15,Lookup!$A$3:$A$7,Lookup!$D$3:$D$7,,1)*SUM(E15:F15), XLOOKUP(B15,Lookup!$A$14:$A$18,Lookup!$D$14:$D$18,,1)*SUM(E15:F15))} -> 2960 | H15: {=if(YEAR(A15)=2025,XLOOKUP(B15,Lookup!$F$3:$F$10,Lookup!$G$3:$G$10,,1)*G15, XLOOKUP(B15,Lookup!$F$14:$F$21,Lookup!$G$14:$G$21,,1)*G15)} -> 1840.232 | I15: {=if(B15<55, if(YEAR(A15)=2025,XLOOKUP(B15,Lookup!$F$3:$F$10,Lookup!$H$3:$H$10,,1)*G15, XLOOKUP(B15,Lookup!$F$14:$F$21,Lookup!$H$14:$H$21,,1)*G15),0)} -> 479.816 | J15: {=if(YEAR(A15)=2025,XLOOKUP(B15,Lookup!$F$3:$F$10,Lookup!$I$3:$I$10,,1)*G15, XLOOKUP(B15,Lookup!$F$14:$F$21,Lookup!$I$14:$I$21,,1)*G15)} -> 639.952 | K15: {=if(B15>54, if(YEAR(A15)=2025,XLOOKUP(B15,Lookup!$F$3:$F$10,Lookup!$H$3:$H$10,,1)*G15, XLOOKUP(B15,Lookup!$F$14:$F$21,Lookup!$H$14:$H$21,,1)*G15),0)} -> 0 | L15: =IF(and(A15<questions!$C$19,questions!$C$18="yes"),questions!$C$20,0) -> 700 | M15: =(Y14+H15)*Lookup!A$26/12 -> 51.693352 | N15: =if(B15<55, (Z14+I15)*Lookup!B$26/12, (AB14+K15)*Lookup!B$26/12) -> 31.029319 | O15: =(AA14+J15)*Lookup!C$26/12 -> 38.360938 | P15: =IF(year(A15)=year(A14), P14+M15, M15) -> 147.95361 | Q15: =IF(year(A15)=year(A14), Q14+N15, N15) -> 88.289796 | R15: =IF(year(A15)=year(A14), R14+O15, O15) -> 108.68329 | S15: =if(B15<55,min(20000,Y14)*0.01/12,min(20000,Y14)*0.02/12) -> 16.666667 | T15: =if(B15<=55,min(60000-min(20000,Y14),Z14)*0.01/12,min(30000-min(20000,Y14),AB14)*0.02/12+min(30000,AB14)*0.01/12) -> 7.357483 | U15: =if(B15<55,min(60000-min(60000-min(20000,Y14),Z14)-min(20000,Y14),AA14)*0.01/12,min(30000-min(30000-min(20000,Y14),AB14)-min(20000,Y14),AA14)*0.02/12+min(30000-min(30000-min(20000,Y14),AB14)-min(20000,Y14),AA14)*0.01/12) -> 9.0569411 | V15: =IF(year($A15)=year($A14), V14+S15, S15) -> 50 | W15: =IF(year($A15)=year($A14), W14+T15, T15) -> 20.872909 | X15: =IF(year($A15)=year($A14), X14+U15, U15) -> 25.570943 | Y15: =IFS( B15<55, MAX( Y14 + IF(MONTH(A15)=12, P15+V15, 0) + H15 - L15 + MAX(0, IF(AA14 >= VLOOKUP(YEAR(A15), Lookup!$Q:$R, 2), Z14 + IF(MONTH(A15)=12, Q15+W15, 0) + I15 + AA14 + IF(MONTH(A15)=12, R15+X15, 0) - VLOOKUP(YEAR(A15), Lookup!$Q:$R, 2) + J15, Z14 + IF(MONTH(A15)=12, Q15+W15, 0) + I15 ) - VLOOKUP(YEAR(A15), Lookup!$K:$M, 3) ), 0), B15=55, IF(Z14>=AD15, MAX(Y14 + IF(MONTH(A15)=12, P15+V15, 0) + H15 - L15, 0), MAX(MAX(0, Y14-(AD15-Z14)) + IF(MONTH(A15)=12, P15+V15, 0) + H15 - L15, 0) ), B15>55, IF(AB14>=$AH$7, MAX(Y14 + IF(MONTH(A15)=12, P15+V15, 0) + H15 - L15 + K15 + Z14, 0), MAX(Y14 + IF(MONTH(A15)=12, P15+V15, 0) + H15 - L15, 0) ) ) -> 24112.809 | Z15: =IFS( B15<55, MIN( IF(AA14 >= VLOOKUP(YEAR(A15), Lookup!$Q:$R, 2), Z14 + IF(MONTH(A15)=12, Q15+W15, 0) + I15 + AA14 + IF(MONTH(A15)=12, R15+X15, 0) - VLOOKUP(YEAR(A15), Lookup!$Q:$R, 2) + J15, Z14 + IF(MONTH(A15)=12, Q15+W15, 0) + I15 ), VLOOKUP(YEAR(A15), Lookup!$K:$M, 3) ), B15=55, IF(Z14 >= AD15, Z14 - AD15, 0), B15>55, 0 ) -> 9308.7956 | AA15: =IFS( B15<65, IF(AA14+J15 < VLOOKUP(YEAR(A15), Lookup!$Q:$R, 2), AA14 + IF(MONTH(A15)=12, R14+X14, 0) + J15, MIN( AA14 + IF(MONTH(A15)=12, R14+X14, 0) + J15 , VLOOKUP(YEAR(A15), Lookup!$Q:$R, 2) ) ), B15>=65, IF(AA14+J15 < VLOOKUP(questions!$C$5, Lookup!$Q:$R, 2), AA14 + IF(MONTH(A15)=12, R14+X14, 0) + J15 , MIN( AA14 + IF(MONTH(A15)=12, R14+X14, 0) + J15, VLOOKUP(questions!$C$5, Lookup!$Q:$R, 2) ) ) ) -> 11508.281 | AB15: =IFS( B15<55, 0, B15=55, MIN(Y14+Z14, AD15), B15>55, IF(AB14 < $AH$7, MIN(AB14 + IF(MONTH(A15)=12, Q15+W15, 0) + K15, $AH$7), AB14 + IF(MONTH(A15)=12, Q15+W15, 0) + K15 ) ) -> 0 | AC15: {=IFS(B15<66, XLOOKUP(year(A15),Lookup!$K$13:$K1000,Lookup!$L$13:$L1000,"missing",,1),B15>65,XLOOKUP(questions!$C$5,Lookup!$K$13:$K1000,Lookup!$L$13:$L1000,"missing",,1))} -> 114100 | AD15: {=IFS(B15<66, XLOOKUP(year(A15),Lookup!$K$13:$K1000,Lookup!$M$13:$M1000,"missing",,1),B15>65, XLOOKUP(questions!$C$5,Lookup!$K$13:$K1000,Lookup!$M$13:$M1000,"missing",,1))} -> 228200 | AE15: {=IFS(B15<66, XLOOKUP(year(A15),Lookup!$K$13:$K1000,Lookup!$N$13:$N1000,"missing",,1),B15>65,XLOOKUP(questions!$C$5,Lookup!$K$13:$K1000,Lookup!$N$13:$N1000,"missing",,1))} -> 456400
A16: =eomonth(EDATE(A15,1),0) -> 46507 | B16: =round(YEARFRAC(EOMONTH(questions!$C$3, 0),A16,1),2) -> 28.41 | C16: =IF(B16<questions!$C$6,if(MONTH(A16)=1,C15*(1+questions!$C$12),C15),0) -> 10300 | D16: =IF(MONTH(A16)=12,C16*questions!$C$11,0) -> 0 | E16: =MIN(C16,IF(YEAR(A16)=2025,7600,8000)) -> 8000 | F16: =MIN(102000-E16*12,D16) -> 0 | G16: {=if(YEAR(A16)=2025,XLOOKUP(B16,Lookup!$A$3:$A$7,Lookup!$D$3:$D$7,,1)*SUM(E16:F16), XLOOKUP(B16,Lookup!$A$14:$A$18,Lookup!$D$14:$D$18,,1)*SUM(E16:F16))} -> 2960 | H16: {=if(YEAR(A16)=2025,XLOOKUP(B16,Lookup!$F$3:$F$10,Lookup!$G$3:$G$10,,1)*G16, XLOOKUP(B16,Lookup!$F$14:$F$21,Lookup!$G$14:$G$21,,1)*G16)} -> 1840.232 | I16: {=if(B16<55, if(YEAR(A16)=2025,XLOOKUP(B16,Lookup!$F$3:$F$10,Lookup!$H$3:$H$10,,1)*G16, XLOOKUP(B16,Lookup!$F$14:$F$21,Lookup!$H$14:$H$21,,1)*G16),0)} -> 479.816 | J16: {=if(YEAR(A16)=2025,XLOOKUP(B16,Lookup!$F$3:$F$10,Lookup!$I$3:$I$10,,1)*G16, XLOOKUP(B16,Lookup!$F$14:$F$21,Lookup!$I$14:$I$21,,1)*G16)} -> 639.952 | K16: {=if(B16>54, if(YEAR(A16)=2025,XLOOKUP(B16,Lookup!$F$3:$F$10,Lookup!$H$3:$H$10,,1)*G16, XLOOKUP(B16,Lookup!$F$14:$F$21,Lookup!$H$14:$H$21,,1)*G16),0)} -> 0 | L16: =IF(and(A16<questions!$C$19,questions!$C$18="yes"),questions!$C$20,0) -> 700 | M16: =(Y15+H16)*Lookup!A$26/12 -> 54.068835 | N16: =if(B16<55, (Z15+I16)*Lookup!B$26/12, (AB15+K16)*Lookup!B$26/12) -> 32.628705 | O16: =(AA15+J16)*Lookup!C$26/12 -> 40.494111 | P16: =IF(year(A16)=year(A15), P15+M16, M16) -> 202.02244 | Q16: =IF(year(A16)=year(A15), Q15+N16, N16) -> 120.9185 | R16: =IF(year(A16)=year(A15), R15+O16, O16) -> 149.1774 | S16: =if(B16<55,min(20000,Y15)*0.01/12,min(20000,Y15)*0.02/12) -> 16.666667 | T16: =if(B16<=55,min(60000-min(20000,Y15),Z15)*0.01/12,min(30000-min(20000,Y15),AB15)*0.02/12+min(30000,AB15)*0.01/12) -> 7.7573296 | U16: =if(B16<55,min(60000-min(60000-min(20000,Y15),Z15)-min(20000,Y15),AA15)*0.01/12,min(30000-min(30000-min(20000,Y15),AB15)-min(20000,Y15),AA15)*0.02/12+min(30000-min(30000-min(20000,Y15),AB15)-min(20000,Y15),AA15)*0.01/12) -> 9.5902345 | V16: =IF(year($A16)=year($A15), V15+S16, S16) -> 66.666667 | W16: =IF(year($A16)=year($A15), W15+T16, T16) -> 28.630239 | X16: =IF(year($A16)=year($A15), X15+U16, U16) -> 35.161178 | Y16: =IFS( B16<55, MAX( Y15 + IF(MONTH(A16)=12, P16+V16, 0) + H16 - L16 + MAX(0, IF(AA15 >= VLOOKUP(YEAR(A16), Lookup!$Q:$R, 2), Z15 + IF(MONTH(A16)=12, Q16+W16, 0) + I16 + AA15 + IF(MONTH(A16)=12, R16+X16, 0) - VLOOKUP(YEAR(A16), Lookup!$Q:$R, 2) + J16, Z15 + IF(MONTH(A16)=12, Q16+W16, 0) + I16 ) - VLOOKUP(YEAR(A16), Lookup!$K:$M, 3) ), 0), B16=55, IF(Z15>=AD16, MAX(Y15 + IF(MONTH(A16)=12, P16+V16, 0) + H16 - L16, 0), MAX(MAX(0, Y15-(AD16-Z15)) + IF(MONTH(A16)=12, P16+V16, 0) + H16 - L16, 0) ), B16>55, IF(AB15>=$AH$7, MAX(Y15 + IF(MONTH(A16)=12, P16+V16, 0) + H16 - L16 + K16 + Z15, 0), MAX(Y15 + IF(MONTH(A16)=12, P16+V16, 0) + H16 - L16, 0) ) ) -> 25253.041 | Z16: =IFS( B16<55, MIN( IF(AA15 >= VLOOKUP(YEAR(A16), Lookup!$Q:$R, 2), Z15 + IF(MONTH(A16)=12, Q16+W16, 0) + I16 + AA15 + IF(MONTH(A16)=12, R16+X16, 0) - VLOOKUP(YEAR(A16), Lookup!$Q:$R, 2) + J16, Z15 + IF(MONTH(A16)=12, Q16+W16, 0) + I16 ), VLOOKUP(YEAR(A16), Lookup!$K:$M, 3) ), B16=55, IF(Z15 >= AD16, Z15 - AD16, 0), B16>55, 0 ) -> 9788.6116 | AA16: =IFS( B16<65, IF(AA15+J16 < VLOOKUP(YEAR(A16), Lookup!$Q:$R, 2), AA15 + IF(MONTH(A16)=12, R15+X15, 0) + J16, MIN( AA15 + IF(MONTH(A16)=12, R15+X15, 0) + J16 , VLOOKUP(YEAR(A16), Lookup!$Q:$R, 2) ) ), B16>=65, IF(AA15+J16 < VLOOKUP(questions!$C$5, Lookup!$Q:$R, 2), AA15 + IF(MONTH(A16)=12, R15+X15, 0) + J16 , MIN( AA15 + IF(MONTH(A16)=12, R15+X15, 0) + J16, VLOOKUP(questions!$C$5, Lookup!$Q:$R, 2) ) ) ) -> 12148.233 | AB16: =IFS( B16<55, 0, B16=55, MIN(Y15+Z15, AD16), B16>55, IF(AB15 < $AH$7, MIN(AB15 + IF(MONTH(A16)=12, Q16+W16, 0) + K16, $AH$7), AB15 + IF(MONTH(A16)=12, Q16+W16, 0) + K16 ) ) -> 0 | AC16: {=IFS(B16<66, XLOOKUP(year(A16),Lookup!$K$13:$K1000,Lookup!$L$13:$L1000,"missing",,1),B16>65,XLOOKUP(questions!$C$5,Lookup!$K$13:$K1000,Lookup!$L$13:$L1000,"missing",,1))} -> 114100 | AD16: {=IFS(B16<66, XLOOKUP(year(A16),Lookup!$K$13:$K1000,Lookup!$M$13:$M1000,"missing",,1),B16>65, XLOOKUP(questions!$C$5,Lookup!$K$13:$K1000,Lookup!$M$13:$M1000,"missing",,1))} -> 228200 | AE16: {=IFS(B16<66, XLOOKUP(year(A16),Lookup!$K$13:$K1000,Lookup!$N$13:$N1000,"missing",,1),B16>65,XLOOKUP(questions!$C$5,Lookup!$K$13:$K1000,Lookup!$N$13:$N1000,"missing",,1))} -> 456400
A17: =eomonth(EDATE(A16,1),0) -> 46538 | B17: =round(YEARFRAC(EOMONTH(questions!$C$3, 0),A17,1),2) -> 28.5 | C17: =IF(B17<questions!$C$6,if(MONTH(A17)=1,C16*(1+questions!$C$12),C16),0) -> 10300 | D17: =IF(MONTH(A17)=12,C17*questions!$C$11,0) -> 0 | E17: =MIN(C17,IF(YEAR(A17)=2025,7600,8000)) -> 8000 | F17: =MIN(102000-E17*12,D17) -> 0 | G17: {=if(YEAR(A17)=2025,XLOOKUP(B17,Lookup!$A$3:$A$7,Lookup!$D$3:$D$7,,1)*SUM(E17:F17), XLOOKUP(B17,Lookup!$A$14:$A$18,Lookup!$D$14:$D$18,,1)*SUM(E17:F17))} -> 2960 | H17: {=if(YEAR(A17)=2025,XLOOKUP(B17,Lookup!$F$3:$F$10,Lookup!$G$3:$G$10,,1)*G17, XLOOKUP(B17,Lookup!$F$14:$F$21,Lookup!$G$14:$G$21,,1)*G17)} -> 1840.232 | I17: {=if(B17<55, if(YEAR(A17)=2025,XLOOKUP(B17,Lookup!$F$3:$F$10,Lookup!$H$3:$H$10,,1)*G17, XLOOKUP(B17,Lookup!$F$14:$F$21,Lookup!$H$14:$H$21,,1)*G17),0)} -> 479.816 | J17: {=if(YEAR(A17)=2025,XLOOKUP(B17,Lookup!$F$3:$F$10,Lookup!$I$3:$I$10,,1)*G17, XLOOKUP(B17,Lookup!$F$14:$F$21,Lookup!$I$14:$I$21,,1)*G17)} -> 639.952 | K17: {=if(B17>54, if(YEAR(A17)=2025,XLOOKUP(B17,Lookup!$F$3:$F$10,Lookup!$H$3:$H$10,,1)*G17, XLOOKUP(B17,Lookup!$F$14:$F$21,Lookup!$H$14:$H$21,,1)*G17),0)} -> 0 | L17: =IF(and(A17<questions!$C$19,questions!$C$18="yes"),questions!$C$20,0) -> 700 | M17: =(Y16+H17)*Lookup!A$26/12 -> 56.444319 | N17: =if(B17<55, (Z16+I17)*Lookup!B$26/12, (AB16+K17)*Lookup!B$26/12) -> 34.228092 | O17: =(AA16+J17)*Lookup!C$26/12 -> 42.627285 | P17: =IF(year(A17)=year(A16), P16+M17, M17) -> 258.46676 | Q17: =IF(year(A17)=year(A16), Q16+N17, N17) -> 155.14659 | R17: =IF(year(A17)=year(A16), R16+O17, O17) -> 191.80469 | S17: =if(B17<55,min(20000,Y16)*0.01/12,min(20000,Y16)*0.02/12) -> 16.666667 | T17: =if(B17<=55,min(60000-min(20000,Y16),Z16)*0.01/12,min(30000-min(20000,Y16),AB16)*0.02/12+min(30000,AB16)*0.01/12) -> 8.1571763 | U17: =if(B17<55,min(60000-min(60000-min(20000,Y16),Z16)-min(20000,Y16),AA16)*0.01/12,min(30000-min(30000-min(20000,Y16),AB16)-min(20000,Y16),AA16)*0.02/12+min(30000-min(30000-min(20000,Y16),AB16)-min(20000,Y16),AA16)*0.01/12) -> 10.123528 | V17: =IF(year($A17)=year($A16), V16+S17, S17) -> 83.333333 | W17: =IF(year($A17)=year($A16), W16+T17, T17) -> 36.787415 | X17: =IF(year($A17)=year($A16), X16+U17, U17) -> 45.284706 | Y17: =IFS( B17<55, MAX( Y16 + IF(MONTH(A17)=12, P17+V17, 0) + H17 - L17 + MAX(0, IF(AA16 >= VLOOKUP(YEAR(A17), Lookup!$Q:$R, 2), Z16 + IF(MONTH(A17)=12, Q17+W17, 0) + I17 + AA16 + IF(MONTH(A17)=12, R17+X17, 0) - VLOOKUP(YEAR(A17), Lookup!$Q:$R, 2) + J17, Z16 + IF(MONTH(A17)=12, Q17+W17, 0) + I17 ) - VLOOKUP(YEAR(A17), Lookup!$K:$M, 3) ), 0), B17=55, IF(Z16>=AD17, MAX(Y16 + IF(MONTH(A17)=12, P17+V17, 0) + H17 - L17, 0), MAX(MAX(0, Y16-(AD17-Z16)) + IF(MONTH(A17)=12, P17+V17, 0) + H17 - L17, 0) ), B17>55, IF(AB16>=$AH$7, MAX(Y16 + IF(MONTH(A17)=12, P17+V17, 0) + H17 - L17 + K17 + Z16, 0), MAX(Y16 + IF(MONTH(A17)=12, P17+V17, 0) + H17 - L17, 0) ) ) -> 26393.273 | Z17: =IFS( B17<55, MIN( IF(AA16 >= VLOOKUP(YEAR(A17), Lookup!$Q:$R, 2), Z16 + IF(MONTH(A17)=12, Q17+W17, 0) + I17 + AA16 + IF(MONTH(A17)=12, R17+X17, 0) - VLOOKUP(YEAR(A17), Lookup!$Q:$R, 2) + J17, Z16 + IF(MONTH(A17)=12, Q17+W17, 0) + I17 ), VLOOKUP(YEAR(A17), Lookup!$K:$M, 3) ), B17=55, IF(Z16 >= AD17, Z16 - AD17, 0), B17>55, 0 ) -> 10268.428 | AA17: =IFS( B17<65, IF(AA16+J17 < VLOOKUP(YEAR(A17), Lookup!$Q:$R, 2), AA16 + IF(MONTH(A17)=12, R16+X16, 0) + J17, MIN( AA16 + IF(MONTH(A17)=12, R16+X16, 0) + J17 , VLOOKUP(YEAR(A17), Lookup!$Q:$R, 2) ) ), B17>=65, IF(AA16+J17 < VLOOKUP(questions!$C$5, Lookup!$Q:$R, 2), AA16 + IF(MONTH(A17)=12, R16+X16, 0) + J17 , MIN( AA16 + IF(MONTH(A17)=12, R16+X16, 0) + J17, VLOOKUP(questions!$C$5, Lookup!$Q:$R, 2) ) ) ) -> 12788.185 | AB17: =IFS( B17<55, 0, B17=55, MIN(Y16+Z16, AD17), B17>55, IF(AB16 < $AH$7, MIN(AB16 + IF(MONTH(A17)=12, Q17+W17, 0) + K17, $AH$7), AB16 + IF(MONTH(A17)=12, Q17+W17, 0) + K17 ) ) -> 0 | AC17: {=IFS(B17<66, XLOOKUP(year(A17),Lookup!$K$13:$K1000,Lookup!$L$13:$L1000,"missing",,1),B17>65,XLOOKUP(questions!$C$5,Lookup!$K$13:$K1000,Lookup!$L$13:$L1000,"missing",,1))} -> 114100 | AD17: {=IFS(B17<66, XLOOKUP(year(A17),Lookup!$K$13:$K1000,Lookup!$M$13:$M1000,"missing",,1),B17>65, XLOOKUP(questions!$C$5,Lookup!$K$13:$K1000,Lookup!$M$13:$M1000,"missing",,1))} -> 228200 | AE17: {=IFS(B17<66, XLOOKUP(year(A17),Lookup!$K$13:$K1000,Lookup!$N$13:$N1000,"missing",,1),B17>65,XLOOKUP(questions!$C$5,Lookup!$K$13:$K1000,Lookup!$N$13:$N1000,"missing",,1))} -> 456400
A18: =eomonth(EDATE(A17,1),0) -> 46568 | B18: =round(YEARFRAC(EOMONTH(questions!$C$3, 0),A18,1),2) -> 28.58 | C18: =IF(B18<questions!$C$6,if(MONTH(A18)=1,C17*(1+questions!$C$12),C17),0) -> 10300 | D18: =IF(MONTH(A18)=12,C18*questions!$C$11,0) -> 0 | E18: =MIN(C18,IF(YEAR(A18)=2025,7600,8000)) -> 8000 | F18: =MIN(102000-E18*12,D18) -> 0 | G18: {=if(YEAR(A18)=2025,XLOOKUP(B18,Lookup!$A$3:$A$7,Lookup!$D$3:$D$7,,1)*SUM(E18:F18), XLOOKUP(B18,Lookup!$A$14:$A$18,Lookup!$D$14:$D$18,,1)*SUM(E18:F18))} -> 2960 | H18: {=if(YEAR(A18)=2025,XLOOKUP(B18,Lookup!$F$3:$F$10,Lookup!$G$3:$G$10,,1)*G18, XLOOKUP(B18,Lookup!$F$14:$F$21,Lookup!$G$14:$G$21,,1)*G18)} -> 1840.232 | I18: {=if(B18<55, if(YEAR(A18)=2025,XLOOKUP(B18,Lookup!$F$3:$F$10,Lookup!$H$3:$H$10,,1)*G18, XLOOKUP(B18,Lookup!$F$14:$F$21,Lookup!$H$14:$H$21,,1)*G18),0)} -> 479.816 | J18: {=if(YEAR(A18)=2025,XLOOKUP(B18,Lookup!$F$3:$F$10,Lookup!$I$3:$I$10,,1)*G18, XLOOKUP(B18,Lookup!$F$14:$F$21,Lookup!$I$14:$I$21,,1)*G18)} -> 639.952 | K18: {=if(B18>54, if(YEAR(A18)=2025,XLOOKUP(B18,Lookup!$F$3:$F$10,Lookup!$H$3:$H$10,,1)*G18, XLOOKUP(B18,Lookup!$F$14:$F$21,Lookup!$H$14:$H$21,,1)*G18),0)} -> 0 | L18: =IF(and(A18<questions!$C$19,questions!$C$18="yes"),questions!$C$20,0) -> 700 | M18: =(Y17+H18)*Lookup!A$26/12 -> 58.819802 | N18: =if(B18<55, (Z17+I18)*Lookup!B$26/12, (AB17+K18)*Lookup!B$26/12) -> 35.827479 | O18: =(AA17+J18)*Lookup!C$26/12 -> 44.760458 | P18: =IF(year(A18)=year(A17), P17+M18, M18) -> 317.28656 | Q18: =IF(year(A18)=year(A17), Q17+N18, N18) -> 190.97407 | R18: =IF(year(A18)=year(A17), R17+O18, O18) -> 236.56515 | S18: =if(B18<55,min(20000,Y17)*0.01/12,min(20000,Y17)*0.02/12) -> 16.666667 | T18: =if(B18<=55,min(60000-min(20000,Y17),Z17)*0.01/12,min(30000-min(20000,Y17),AB17)*0.02/12+min(30000,AB17)*0.01/12) -> 8.557023 | U18: =if(B18<55,min(60000-min(60000-min(20000,Y17),Z17)-min(20000,Y17),AA17)*0.01/12,min(30000-min(30000-min(20000,Y17),AB17)-min(20000,Y17),AA17)*0.02/12+min(30000-min(30000-min(20000,Y17),AB17)-min(20000,Y17),AA17)*0.01/12) -> 10.656821 | V18: =IF(year($A18)=year($A17), V17+S18, S18) -> 100 | W18: =IF(year($A18)=year($A17), W17+T18, T18) -> 45.344438 | X18: =IF(year($A18)=year($A17), X17+U18, U18) -> 55.941527 | Y18: =IFS( B18<55, MAX( Y17 + IF(MONTH(A18)=12, P18+V18, 0) + H18 - L18 + MAX(0, IF(AA17 >= VLOOKUP(YEAR(A18), Lookup!$Q:$R, 2), Z17 + IF(MONTH(A18)=12, Q18+W18, 0) + I18 + AA17 + IF(MONTH(A18)=12, R18+X18, 0) - VLOOKUP(YEAR(A18), Lookup!$Q:$R, 2) + J18, Z17 + IF(MONTH(A18)=12, Q18+W18, 0) + I18 ) - VLOOKUP(YEAR(A18), Lookup!$K:$M, 3) ), 0), B18=55, IF(Z17>=AD18, MAX(Y17 + IF(MONTH(A18)=12, P18+V18, 0) + H18 - L18, 0), MAX(MAX(0, Y17-(AD18-Z17)) + IF(MONTH(A18)=12, P18+V18, 0) + H18 - L18, 0) ), B18>55, IF(AB17>=$AH$7, MAX(Y17 + IF(MONTH(A18)=12, P18+V18, 0) + H18 - L18 + K18 + Z17, 0), MAX(Y17 + IF(MONTH(A18)=12, P18+V18, 0) + H18 - L18, 0) ) ) -> 27533.505 | Z18: =IFS( B18<55, MIN( IF(AA17 >= VLOOKUP(YEAR(A18), Lookup!$Q:$R, 2), Z17 + IF(MONTH(A18)=12, Q18+W18, 0) + I18 + AA17 + IF(MONTH(A18)=12, R18+X18, 0) - VLOOKUP(YEAR(A18), Lookup!$Q:$R, 2) + J18, Z17 + IF(MONTH(A18)=12, Q18+W18, 0) + I18 ), VLOOKUP(YEAR(A18), Lookup!$K:$M, 3) ), B18=55, IF(Z17 >= AD18, Z17 - AD18, 0), B18>55, 0 ) -> 10748.244 | AA18: =IFS( B18<65, IF(AA17+J18 < VLOOKUP(YEAR(A18), Lookup!$Q:$R, 2), AA17 + IF(MONTH(A18)=12, R17+X17, 0) + J18, MIN( AA17 + IF(MONTH(A18)=12, R17+X17, 0) + J18 , VLOOKUP(YEAR(A18), Lookup!$Q:$R, 2) ) ), B18>=65, IF(AA17+J18 < VLOOKUP(questions!$C$5, Lookup!$Q:$R, 2), AA17 + IF(MONTH(A18)=12, R17+X17, 0) + J18 , MIN( AA17 + IF(MONTH(A18)=12, R17+X17, 0) + J18, VLOOKUP(questions!$C$5, Lookup!$Q:$R, 2) ) ) ) -> 13428.137 | AB18: =IFS( B18<55, 0, B18=55, MIN(Y17+Z17, AD18), B18>55, IF(AB17 < $AH$7, MIN(AB17 + IF(MONTH(A18)=12, Q18+W18, 0) + K18, $AH$7), AB17 + IF(MONTH(A18)=12, Q18+W18, 0) + K18 ) ) -> 0 | AC18: {=IFS(B18<66, XLOOKUP(year(A18),Lookup!$K$13:$K1000,Lookup!$L$13:$L1000,"missing",,1),B18>65,XLOOKUP(questions!$C$5,Lookup!$K$13:$K1000,Lookup!$L$13:$L1000,"missing",,1))} -> 114100 | AD18: {=IFS(B18<66, XLOOKUP(year(A18),Lookup!$K$13:$K1000,Lookup!$M$13:$M1000,"missing",,1),B18>65, XLOOKUP(questions!$C$5,Lookup!$K$13:$K1000,Lookup!$M$13:$M1000,"missing",,1))} -> 228200 | AE18: {=IFS(B18<66, XLOOKUP(year(A18),Lookup!$K$13:$K1000,Lookup!$N$13:$N1000,"missing",,1),B18>65,XLOOKUP(questions!$C$5,Lookup!$K$13:$K1000,Lookup!$N$13:$N1000,"missing",,1))} -> 456400
A19: =eomonth(EDATE(A18,1),0) -> 46599 | B19: =round(YEARFRAC(EOMONTH(questions!$C$3, 0),A19,1),2) -> 28.67 | C19: =IF(B19<questions!$C$6,if(MONTH(A19)=1,C18*(1+questions!$C$12),C18),0) -> 10300 | D19: =IF(MONTH(A19)=12,C19*questions!$C$11,0) -> 0 | E19: =MIN(C19,IF(YEAR(A19)=2025,7600,8000)) -> 8000 | F19: =MIN(102000-E19*12,D19) -> 0 | G19: {=if(YEAR(A19)=2025,XLOOKUP(B19,Lookup!$A$3:$A$7,Lookup!$D$3:$D$7,,1)*SUM(E19:F19), XLOOKUP(B19,Lookup!$A$14:$A$18,Lookup!$D$14:$D$18,,1)*SUM(E19:F19))} -> 2960 | H19: {=if(YEAR(A19)=2025,XLOOKUP(B19,Lookup!$F$3:$F$10,Lookup!$G$3:$G$10,,1)*G19, XLOOKUP(B19,Lookup!$F$14:$F$21,Lookup!$G$14:$G$21,,1)*G19)} -> 1840.232 | I19: {=if(B19<55, if(YEAR(A19)=2025,XLOOKUP(B19,Lookup!$F$3:$F$10,Lookup!$H$3:$H$10,,1)*G19, XLOOKUP(B19,Lookup!$F$14:$F$21,Lookup!$H$14:$H$21,,1)*G19),0)} -> 479.816 | J19: {=if(YEAR(A19)=2025,XLOOKUP(B19,Lookup!$F$3:$F$10,Lookup!$I$3:$I$10,,1)*G19, XLOOKUP(B19,Lookup!$F$14:$F$21,Lookup!$I$14:$I$21,,1)*G19)} -> 639.952 | K19: {=if(B19>54, if(YEAR(A19)=2025,XLOOKUP(B19,Lookup!$F$3:$F$10,Lookup!$H$3:$H$10,,1)*G19, XLOOKUP(B19,Lookup!$F$14:$F$21,Lookup!$H$14:$H$21,,1)*G19),0)} -> 0 | L19: =IF(and(A19<questions!$C$19,questions!$C$18="yes"),questions!$C$20,0) -> 700 | M19: =(Y18+H19)*Lookup!A$26/12 -> 61.195285 | N19: =if(B19<55, (Z18+I19)*Lookup!B$26/12, (AB18+K19)*Lookup!B$26/12) -> 37.426865 | O19: =(AA18+J19)*Lookup!C$26/12 -> 46.893631 | P19: =IF(year(A19)=year(A18), P18+M19, M19) -> 378.48185 | Q19: =IF(year(A19)=year(A18), Q18+N19, N19) -> 228.40094 | R19: =IF(year(A19)=year(A18), R18+O19, O19) -> 283.45878 | S19: =if(B19<55,min(20000,Y18)*0.01/12,min(20000,Y18)*0.02/12) -> 16.666667 | T19: =if(B19<=55,min(60000-min(20000,Y18),Z18)*0.01/12,min(30000-min(20000,Y18),AB18)*0.02/12+min(30000,AB18)*0.01/12) -> 8.9568696 | U19: =if(B19<55,min(60000-min(60000-min(20000,Y18),Z18)-min(20000,Y18),AA18)*0.01/12,min(30000-min(30000-min(20000,Y18),AB18)-min(20000,Y18),AA18)*0.02/12+min(30000-min(30000-min(20000,Y18),AB18)-min(20000,Y18),AA18)*0.01/12) -> 11.190114 | V19: =IF(year($A19)=year($A18), V18+S19, S19) -> 116.66667 | W19: =IF(year($A19)=year($A18), W18+T19, T19) -> 54.301308 | X19: =IF(year($A19)=year($A18), X18+U19, U19) -> 67.131641 | Y19: =IFS( B19<55, MAX( Y18 + IF(MONTH(A19)=12, P19+V19, 0) + H19 - L19 + MAX(0, IF(AA18 >= VLOOKUP(YEAR(A19), Lookup!$Q:$R, 2), Z18 + IF(MONTH(A19)=12, Q19+W19, 0) + I19 + AA18 + IF(MONTH(A19)=12, R19+X19, 0) - VLOOKUP(YEAR(A19), Lookup!$Q:$R, 2) + J19, Z18 + IF(MONTH(A19)=12, Q19+W19, 0) + I19 ) - VLOOKUP(YEAR(A19), Lookup!$K:$M, 3) ), 0), B19=55, IF(Z18>=AD19, MAX(Y18 + IF(MONTH(A19)=12, P19+V19, 0) + H19 - L19, 0), MAX(MAX(0, Y18-(AD19-Z18)) + IF(MONTH(A19)=12, P19+V19, 0) + H19 - L19, 0) ), B19>55, IF(AB18>=$AH$7, MAX(Y18 + IF(MONTH(A19)=12, P19+V19, 0) + H19 - L19 + K19 + Z18, 0), MAX(Y18 + IF(MONTH(A19)=12, P19+V19, 0) + H19 - L19, 0) ) ) -> 28673.737 | Z19: =IFS( B19<55, MIN( IF(AA18 >= VLOOKUP(YEAR(A19), Lookup!$Q:$R, 2), Z18 + IF(MONTH(A19)=12, Q19+W19, 0) + I19 + AA18 + IF(MONTH(A19)=12, R19+X19, 0) - VLOOKUP(YEAR(A19), Lookup!$Q:$R, 2) + J19, Z18 + IF(MONTH(A19)=12, Q19+W19, 0) + I19 ), VLOOKUP(YEAR(A19), Lookup!$K:$M, 3) ), B19=55, IF(Z18 >= AD19, Z18 - AD19, 0), B19>55, 0 ) -> 11228.06 | AA19: =IFS( B19<65, IF(AA18+J19 < VLOOKUP(YEAR(A19), Lookup!$Q:$R, 2), AA18 + IF(MONTH(A19)=12, R18+X18, 0) + J19, MIN( AA18 + IF(MONTH(A19)=12, R18+X18, 0) + J19 , VLOOKUP(YEAR(A19), Lookup!$Q:$R, 2) ) ), B19>=65, IF(AA18+J19 < VLOOKUP(questions!$C$5, Lookup!$Q:$R, 2), AA18 + IF(MONTH(A19)=12, R18+X18, 0) + J19 , MIN( AA18 + IF(MONTH(A19)=12, R18+X18, 0) + J19, VLOOKUP(questions!$C$5, Lookup!$Q:$R, 2) ) ) ) -> 14068.089 | AB19: =IFS( B19<55, 0, B19=55, MIN(Y18+Z18, AD19), B19>55, IF(AB18 < $AH$7, MIN(AB18 + IF(MONTH(A19)=12, Q19+W19, 0) + K19, $AH$7), AB18 + IF(MONTH(A19)=12, Q19+W19, 0) + K19 ) ) -> 0 | AC19: {=IFS(B19<66, XLOOKUP(year(A19),Lookup!$K$13:$K1000,Lookup!$L$13:$L1000,"missing",,1),B19>65,XLOOKUP(questions!$C$5,Lookup!$K$13:$K1000,Lookup!$L$13:$L1000,"missing",,1))} -> 114100 | AD19: {=IFS(B19<66, XLOOKUP(year(A19),Lookup!$K$13:$K1000,Lookup!$M$13:$M1000,"missing",,1),B19>65, XLOOKUP(questions!$C$5,Lookup!$K$13:$K1000,Lookup!$M$13:$M1000,"missing",,1))} -> 228200 | AE19: {=IFS(B19<66, XLOOKUP(year(A19),Lookup!$K$13:$K1000,Lookup!$N$13:$N1000,"missing",,1),B19>65,XLOOKUP(questions!$C$5,Lookup!$K$13:$K1000,Lookup!$N$13:$N1000,"missing",,1))} -> 456400
A20: =eomonth(EDATE(A19,1),0) -> 46630 | B20: =round(YEARFRAC(EOMONTH(questions!$C$3, 0),A20,1),2) -> 28.75 | C20: =IF(B20<questions!$C$6,if(MONTH(A20)=1,C19*(1+questions!$C$12),C19),0) -> 10300 | D20: =IF(MONTH(A20)=12,C20*questions!$C$11,0) -> 0 | E20: =MIN(C20,IF(YEAR(A20)=2025,7600,8000)) -> 8000 | F20: =MIN(102000-E20*12,D20) -> 0 | G20: {=if(YEAR(A20)=2025,XLOOKUP(B20,Lookup!$A$3:$A$7,Lookup!$D$3:$D$7,,1)*SUM(E20:F20), XLOOKUP(B20,Lookup!$A$14:$A$18,Lookup!$D$14:$D$18,,1)*SUM(E20:F20))} -> 2960 | H20: {=if(YEAR(A20)=2025,XLOOKUP(B20,Lookup!$F$3:$F$10,Lookup!$G$3:$G$10,,1)*G20, XLOOKUP(B20,Lookup!$F$14:$F$21,Lookup!$G$14:$G$21,,1)*G20)} -> 1840.232 | I20: {=if(B20<55, if(YEAR(A20)=2025,XLOOKUP(B20,Lookup!$F$3:$F$10,Lookup!$H$3:$H$10,,1)*G20, XLOOKUP(B20,Lookup!$F$14:$F$21,Lookup!$H$14:$H$21,,1)*G20),0)} -> 479.816 | J20: {=if(YEAR(A20)=2025,XLOOKUP(B20,Lookup!$F$3:$F$10,Lookup!$I$3:$I$10,,1)*G20, XLOOKUP(B20,Lookup!$F$14:$F$21,Lookup!$I$14:$I$21,,1)*G20)} -> 639.952 | K20: {=if(B20>54, if(YEAR(A20)=2025,XLOOKUP(B20,Lookup!$F$3:$F$10,Lookup!$H$3:$H$10,,1)*G20, XLOOKUP(B20,Lookup!$F$14:$F$21,Lookup!$H$14:$H$21,,1)*G20),0)} -> 0 | L20: =IF(and(A20<questions!$C$19,questions!$C$18="yes"),questions!$C$20,0) -> 700 | M20: =(Y19+H20)*Lookup!A$26/12 -> 63.570769 | N20: =if(B20<55, (Z19+I20)*Lookup!B$26/12, (AB19+K20)*Lookup!B$26/12) -> 39.026252 | O20: =(AA19+J20)*Lookup!C$26/12 -> 49.026805 | P20: =IF(year(A20)=year(A19), P19+M20, M20) -> 442.05262 | Q20: =IF(year(A20)=year(A19), Q19+N20, N20) -> 267.42719 | R20: =IF(year(A20)=year(A19), R19+O20, O20) -> 332.48558 | S20: =if(B20<55,min(20000,Y19)*0.01/12,min(20000,Y19)*0.02/12) -> 16.666667 | T20: =if(B20<=55,min(60000-min(20000,Y19),Z19)*0.01/12,min(30000-min(20000,Y19),AB19)*0.02/12+min(30000,AB19)*0.01/12) -> 9.3567163 | U20: =if(B20<55,min(60000-min(60000-min(20000,Y19),Z19)-min(20000,Y19),AA19)*0.01/12,min(30000-min(30000-min(20000,Y19),AB19)-min(20000,Y19),AA19)*0.02/12+min(30000-min(30000-min(20000,Y19),AB19)-min(20000,Y19),AA19)*0.01/12) -> 11.723408 | V20: =IF(year($A20)=year($A19), V19+S20, S20) -> 133.33333 | W20: =IF(year($A20)=year($A19), W19+T20, T20) -> 63.658024 | X20: =IF(year($A20)=year($A19), X19+U20, U20) -> 78.855049 | Y20: =IFS( B20<55, MAX( Y19 + IF(MONTH(A20)=12, P20+V20, 0) + H20 - L20 + MAX(0, IF(AA19 >= VLOOKUP(YEAR(A20), Lookup!$Q:$R, 2), Z19 + IF(MONTH(A20)=12, Q20+W20, 0) + I20 + AA19 + IF(MONTH(A20)=12, R20+X20, 0) - VLOOKUP(YEAR(A20), Lookup!$Q:$R, 2) + J20, Z19 + IF(MONTH(A20)=12, Q20+W20, 0) + I20 ) - VLOOKUP(YEAR(A20), Lookup!$K:$M, 3) ), 0), B20=55, IF(Z19>=AD20, MAX(Y19 + IF(MONTH(A20)=12, P20+V20, 0) + H20 - L20, 0), MAX(MAX(0, Y19-(AD20-Z19)) + IF(MONTH(A20)=12, P20+V20, 0) + H20 - L20, 0) ), B20>55, IF(AB19>=$AH$7, MAX(Y19 + IF(MONTH(A20)=12, P20+V20, 0) + H20 - L20 + K20 + Z19, 0), MAX(Y19 + IF(MONTH(A20)=12, P20+V20, 0) + H20 - L20, 0) ) ) -> 29813.969 | Z20: =IFS( B20<55, MIN( IF(AA19 >= VLOOKUP(YEAR(A20), Lookup!$Q:$R, 2), Z19 + IF(MONTH(A20)=12, Q20+W20, 0) + I20 + AA19 + IF(MONTH(A20)=12, R20+X20, 0) - VLOOKUP(YEAR(A20), Lookup!$Q:$R, 2) + J20, Z19 + IF(MONTH(A20)=12, Q20+W20, 0) + I20 ), VLOOKUP(YEAR(A20), Lookup!$K:$M, 3) ), B20=55, IF(Z19 >= AD20, Z19 - AD20, 0), B20>55, 0 ) -> 11707.876 | AA20: =IFS( B20<65, IF(AA19+J20 < VLOOKUP(YEAR(A20), Lookup!$Q:$R, 2), AA19 + IF(MONTH(A20)=12, R19+X19, 0) + J20, MIN( AA19 + IF(MONTH(A20)=12, R19+X19, 0) + J20 , VLOOKUP(YEAR(A20), Lookup!$Q:$R, 2) ) ), B20>=65, IF(AA19+J20 < VLOOKUP(questions!$C$5, Lookup!$Q:$R, 2), AA19 + IF(MONTH(A20)=12, R19+X19, 0) + J20 , MIN( AA19 + IF(MONTH(A20)=12, R19+X19, 0) + J20, VLOOKUP(questions!$C$5, Lookup!$Q:$R, 2) ) ) ) -> 14708.041 | AB20: =IFS( B20<55, 0, B20=55, MIN(Y19+Z19, AD20), B20>55, IF(AB19 < $AH$7, MIN(AB19 + IF(MONTH(A20)=12, Q20+W20, 0) + K20, $AH$7), AB19 + IF(MONTH(A20)=12, Q20+W20, 0) + K20 ) ) -> 0 | AC20: {=IFS(B20<66, XLOOKUP(year(A20),Lookup!$K$13:$K1000,Lookup!$L$13:$L1000,"missing",,1),B20>65,XLOOKUP(questions!$C$5,Lookup!$K$13:$K1000,Lookup!$L$13:$L1000,"missing",,1))} -> 114100 | AD20: {=IFS(B20<66, XLOOKUP(year(A20),Lookup!$K$13:$K1000,Lookup!$M$13:$M1000,"missing",,1),B20>65, XLOOKUP(questions!$C$5,Lookup!$K$13:$K1000,Lookup!$M$13:$M1000,"missing",,1))} -> 228200 | AE20: {=IFS(B20<66, XLOOKUP(year(A20),Lookup!$K$13:$K1000,Lookup!$N$13:$N1000,"missing",,1),B20>65,XLOOKUP(questions!$C$5,Lookup!$K$13:$K1000,Lookup!$N$13:$N1000,"missing",,1))} -> 456400
A21: =eomonth(EDATE(A20,1),0) -> 46660 | B21: =round(YEARFRAC(EOMONTH(questions!$C$3, 0),A21,1),2) -> 28.83 | C21: =IF(B21<questions!$C$6,if(MONTH(A21)=1,C20*(1+questions!$C$12),C20),0) -> 10300 | D21: =IF(MONTH(A21)=12,C21*questions!$C$11,0) -> 0 | E21: =MIN(C21,IF(YEAR(A21)=2025,7600,8000)) -> 8000 | F21: =MIN(102000-E21*12,D21) -> 0 | G21: {=if(YEAR(A21)=2025,XLOOKUP(B21,Lookup!$A$3:$A$7,Lookup!$D$3:$D$7,,1)*SUM(E21:F21), XLOOKUP(B21,Lookup!$A$14:$A$18,Lookup!$D$14:$D$18,,1)*SUM(E21:F21))} -> 2960 | H21: {=if(YEAR(A21)=2025,XLOOKUP(B21,Lookup!$F$3:$F$10,Lookup!$G$3:$G$10,,1)*G21, XLOOKUP(B21,Lookup!$F$14:$F$21,Lookup!$G$14:$G$21,,1)*G21)} -> 1840.232 | I21: {=if(B21<55, if(YEAR(A21)=2025,XLOOKUP(B21,Lookup!$F$3:$F$10,Lookup!$H$3:$H$10,,1)*G21, XLOOKUP(B21,Lookup!$F$14:$F$21,Lookup!$H$14:$H$21,,1)*G21),0)} -> 479.816 | J21: {=if(YEAR(A21)=2025,XLOOKUP(B21,Lookup!$F$3:$F$10,Lookup!$I$3:$I$10,,1)*G21, XLOOKUP(B21,Lookup!$F$14:$F$21,Lookup!$I$14:$I$21,,1)*G21)} -> 639.952 | K21: {=if(B21>54, if(YEAR(A21)=2025,XLOOKUP(B21,Lookup!$F$3:$F$10,Lookup!$H$3:$H$10,,1)*G21, XLOOKUP(B21,Lookup!$F$14:$F$21,Lookup!$H$14:$H$21,,1)*G21),0)} -> 0 | L21: =IF(and(A21<questions!$C$19,questions!$C$18="yes"),questions!$C$20,0) -> 700 | M21: =(Y20+H21)*Lookup!A$26/12 -> 65.946252 | N21: =if(B21<55, (Z20+I21)*Lookup!B$26/12, (AB20+K21)*Lookup!B$26/12) -> 40.625639 | O21: =(AA20+J21)*Lookup!C$26/12 -> 51.159978 | P21: =IF(year(A21)=year(A20), P20+M21, M21) -> 507.99887 | Q21: =IF(year(A21)=year(A20), Q20+N21, N21) -> 308.05283 | R21: =IF(year(A21)=year(A20), R20+O21, O21) -> 383.64556 | S21: =if(B21<55,min(20000,Y20)*0.01/12,min(20000,Y20)*0.02/12) -> 16.666667 | T21: =if(B21<=55,min(60000-min(20000,Y20),Z20)*0.01/12,min(30000-min(20000,Y20),AB20)*0.02/12+min(30000,AB20)*0.01/12) -> 9.756563 | U21: =if(B21<55,min(60000-min(60000-min(20000,Y20),Z20)-min(20000,Y20),AA20)*0.01/12,min(30000-min(30000-min(20000,Y20),AB20)-min(20000,Y20),AA20)*0.02/12+min(30000-min(30000-min(20000,Y20),AB20)-min(20000,Y20),AA20)*0.01/12) -> 12.256701 | V21: =IF(year($A21)=year($A20), V20+S21, S21) -> 150 | W21: =IF(year($A21)=year($A20), W20+T21, T21) -> 73.414587 | X21: =IF(year($A21)=year($A20), X20+U21, U21) -> 91.11175 | Y21: =IFS( B21<55, MAX( Y20 + IF(MONTH(A21)=12, P21+V21, 0) + H21 - L21 + MAX(0, IF(AA20 >= VLOOKUP(YEAR(A21), Lookup!$Q:$R, 2), Z20 + IF(MONTH(A21)=12, Q21+W21, 0) + I21 + AA20 + IF(MONTH(A21)=12, R21+X21, 0) - VLOOKUP(YEAR(A21), Lookup!$Q:$R, 2) + J21, Z20 + IF(MONTH(A21)=12, Q21+W21, 0) + I21 ) - VLOOKUP(YEAR(A21), Lookup!$K:$M, 3) ), 0), B21=55, IF(Z20>=AD21, MAX(Y20 + IF(MONTH(A21)=12, P21+V21, 0) + H21 - L21, 0), MAX(MAX(0, Y20-(AD21-Z20)) + IF(MONTH(A21)=12, P21+V21, 0) + H21 - L21, 0) ), B21>55, IF(AB20>=$AH$7, MAX(Y20 + IF(MONTH(A21)=12, P21+V21, 0) + H21 - L21 + K21 + Z20, 0), MAX(Y20 + IF(MONTH(A21)=12, P21+V21, 0) + H21 - L21, 0) ) ) -> 30954.201 | Z21: =IFS( B21<55, MIN( IF(AA20 >= VLOOKUP(YEAR(A21), Lookup!$Q:$R, 2), Z20 + IF(MONTH(A21)=12, Q21+W21, 0) + I21 + AA20 + IF(MONTH(A21)=12, R21+X21, 0) - VLOOKUP(YEAR(A21), Lookup!$Q:$R, 2) + J21, Z20 + IF(MONTH(A21)=12, Q21+W21, 0) + I21 ), VLOOKUP(YEAR(A21), Lookup!$K:$M, 3) ), B21=55, IF(Z20 >= AD21, Z20 - AD21, 0), B21>55, 0 ) -> 12187.692 | AA21: =IFS( B21<65, IF(AA20+J21 < VLOOKUP(YEAR(A21), Lookup!$Q:$R, 2), AA20 + IF(MONTH(A21)=12, R20+X20, 0) + J21, MIN( AA20 + IF(MONTH(A21)=12, R20+X20, 0) + J21 , VLOOKUP(YEAR(A21), Lookup!$Q:$R, 2) ) ), B21>=65, IF(AA20+J21 < VLOOKUP(questions!$C$5, Lookup!$Q:$R, 2), AA20 + IF(MONTH(A21)=12, R20+X20, 0) + J21 , MIN( AA20 + IF(MONTH(A21)=12, R20+X20, 0) + J21, VLOOKUP(questions!$C$5, Lookup!$Q:$R, 2) ) ) ) -> 15347.993 | AB21: =IFS( B21<55, 0, B21=55, MIN(Y20+Z20, AD21), B21>55, IF(AB20 < $AH$7, MIN(AB20 + IF(MONTH(A21)=12, Q21+W21, 0) + K21, $AH$7), AB20 + IF(MONTH(A21)=12, Q21+W21, 0) + K21 ) ) -> 0 | AC21: {=IFS(B21<66, XLOOKUP(year(A21),Lookup!$K$13:$K1000,Lookup!$L$13:$L1000,"missing",,1),B21>65,XLOOKUP(questions!$C$5,Lookup!$K$13:$K1000,Lookup!$L$13:$L1000,"missing",,1))} -> 114100 | AD21: {=IFS(B21<66, XLOOKUP(year(A21),Lookup!$K$13:$K1000,Lookup!$M$13:$M1000,"missing",,1),B21>65, XLOOKUP(questions!$C$5,Lookup!$K$13:$K1000,Lookup!$M$13:$M1000,"missing",,1))} -> 228200 | AE21: {=IFS(B21<66, XLOOKUP(year(A21),Lookup!$K$13:$K1000,Lookup!$N$13:$N1000,"missing",,1),B21>65,XLOOKUP(questions!$C$5,Lookup!$K$13:$K1000,Lookup!$N$13:$N1000,"missing",,1))} -> 456400
A22: =eomonth(EDATE(A21,1),0) -> 46691 | B22: =round(YEARFRAC(EOMONTH(questions!$C$3, 0),A22,1),2) -> 28.92 | C22: =IF(B22<questions!$C$6,if(MONTH(A22)=1,C21*(1+questions!$C$12),C21),0) -> 10300 | D22: =IF(MONTH(A22)=12,C22*questions!$C$11,0) -> 0 | E22: =MIN(C22,IF(YEAR(A22)=2025,7600,8000)) -> 8000 | F22: =MIN(102000-E22*12,D22) -> 0 | G22: {=if(YEAR(A22)=2025,XLOOKUP(B22,Lookup!$A$3:$A$7,Lookup!$D$3:$D$7,,1)*SUM(E22:F22), XLOOKUP(B22,Lookup!$A$14:$A$18,Lookup!$D$14:$D$18,,1)*SUM(E22:F22))} -> 2960 | H22: {=if(YEAR(A22)=2025,XLOOKUP(B22,Lookup!$F$3:$F$10,Lookup!$G$3:$G$10,,1)*G22, XLOOKUP(B22,Lookup!$F$14:$F$21,Lookup!$G$14:$G$21,,1)*G22)} -> 1840.232 | I22: {=if(B22<55, if(YEAR(A22)=2025,XLOOKUP(B22,Lookup!$F$3:$F$10,Lookup!$H$3:$H$10,,1)*G22, XLOOKUP(B22,Lookup!$F$14:$F$21,Lookup!$H$14:$H$21,,1)*G22),0)} -> 479.816 | J22: {=if(YEAR(A22)=2025,XLOOKUP(B22,Lookup!$F$3:$F$10,Lookup!$I$3:$I$10,,1)*G22, XLOOKUP(B22,Lookup!$F$14:$F$21,Lookup!$I$14:$I$21,,1)*G22)} -> 639.952 | K22: {=if(B22>54, if(YEAR(A22)=2025,XLOOKUP(B22,Lookup!$F$3:$F$10,Lookup!$H$3:$H$10,,1)*G22, XLOOKUP(B22,Lookup!$F$14:$F$21,Lookup!$H$14:$H$21,,1)*G22),0)} -> 0 | L22: =IF(and(A22<questions!$C$19,questions!$C$18="yes"),questions!$C$20,0) -> 700 | M22: =(Y21+H22)*Lookup!A$26/12 -> 68.321735 | N22: =if(B22<55, (Z21+I22)*Lookup!B$26/12, (AB21+K22)*Lookup!B$26/12) -> 42.225025 | O22: =(AA21+J22)*Lookup!C$26/12 -> 53.293151 | P22: =IF(year(A22)=year(A21), P21+M22, M22) -> 576.3206 | Q22: =IF(year(A22)=year(A21), Q21+N22, N22) -> 350.27785 | R22: =IF(year(A22)=year(A21), R21+O22, O22) -> 436.93871 | S22: =if(B22<55,min(20000,Y21)*0.01/12,min(20000,Y21)*0.02/12) -> 16.666667 | T22: =if(B22<=55,min(60000-min(20000,Y21),Z21)*0.01/12,min(30000-min(20000,Y21),AB21)*0.02/12+min(30000,AB21)*0.01/12) -> 10.15641 | U22: =if(B22<55,min(60000-min(60000-min(20000,Y21),Z21)-min(20000,Y21),AA21)*0.01/12,min(30000-min(30000-min(20000,Y21),AB21)-min(20000,Y21),AA21)*0.02/12+min(30000-min(30000-min(20000,Y21),AB21)-min(20000,Y21),AA21)*0.01/12) -> 12.789994 | V22: =IF(year($A22)=year($A21), V21+S22, S22) -> 166.66667 | W22: =IF(year($A22)=year($A21), W21+T22, T22) -> 83.570996 | X22: =IF(year($A22)=year($A21), X21+U22, U22) -> 103.90174 | Y22: =IFS( B22<55, MAX( Y21 + IF(MONTH(A22)=12, P22+V22, 0) + H22 - L22 + MAX(0, IF(AA21 >= VLOOKUP(YEAR(A22), Lookup!$Q:$R, 2), Z21 + IF(MONTH(A22)=12, Q22+W22, 0) + I22 + AA21 + IF(MONTH(A22)=12, R22+X22, 0) - VLOOKUP(YEAR(A22), Lookup!$Q:$R, 2) + J22, Z21 + IF(MONTH(A22)=12, Q22+W22, 0) + I22 ) - VLOOKUP(YEAR(A22), Lookup!$K:$M, 3) ), 0), B22=55, IF(Z21>=AD22, MAX(Y21 + IF(MONTH(A22)=12, P22+V22, 0) + H22 - L22, 0), MAX(MAX(0, Y21-(AD22-Z21)) + IF(MONTH(A22)=12, P22+V22, 0) + H22 - L22, 0) ), B22>55, IF(AB21>=$AH$7, MAX(Y21 + IF(MONTH(A22)=12, P22+V22, 0) + H22 - L22 + K22 + Z21, 0), MAX(Y21 + IF(MONTH(A22)=12, P22+V22, 0) + H22 - L22, 0) ) ) -> 32094.433 | Z22: =IFS( B22<55, MIN( IF(AA21 >= VLOOKUP(YEAR(A22), Lookup!$Q:$R, 2), Z21 + IF(MONTH(A22)=12, Q22+W22, 0) + I22 + AA21 + IF(MONTH(A22)=12, R22+X22, 0) - VLOOKUP(YEAR(A22), Lookup!$Q:$R, 2) + J22, Z21 + IF(MONTH(A22)=12, Q22+W22, 0) + I22 ), VLOOKUP(YEAR(A22), Lookup!$K:$M, 3) ), B22=55, IF(Z21 >= AD22, Z21 - AD22, 0), B22>55, 0 ) -> 12667.508 | AA22: =IFS( B22<65, IF(AA21+J22 < VLOOKUP(YEAR(A22), Lookup!$Q:$R, 2), AA21 + IF(MONTH(A22)=12, R21+X21, 0) + J22, MIN( AA21 + IF(MONTH(A22)=12, R21+X21, 0) + J22 , VLOOKUP(YEAR(A22), Lookup!$Q:$R, 2) ) ), B22>=65, IF(AA21+J22 < VLOOKUP(questions!$C$5, Lookup!$Q:$R, 2), AA21 + IF(MONTH(A22)=12, R21+X21, 0) + J22 , MIN( AA21 + IF(MONTH(A22)=12, R21+X21, 0) + J22, VLOOKUP(questions!$C$5, Lookup!$Q:$R, 2) ) ) ) -> 15987.945 | AB22: =IFS( B22<55, 0, B22=55, MIN(Y21+Z21, AD22), B22>55, IF(AB21 < $AH$7, MIN(AB21 + IF(MONTH(A22)=12, Q22+W22, 0) + K22, $AH$7), AB21 + IF(MONTH(A22)=12, Q22+W22, 0) + K22 ) ) -> 0 | AC22: {=IFS(B22<66, XLOOKUP(year(A22),Lookup!$K$13:$K1000,Lookup!$L$13:$L1000,"missing",,1),B22>65,XLOOKUP(questions!$C$5,Lookup!$K$13:$K1000,Lookup!$L$13:$L1000,"missing",,1))} -> 114100 | AD22: {=IFS(B22<66, XLOOKUP(year(A22),Lookup!$K$13:$K1000,Lookup!$M$13:$M1000,"missing",,1),B22>65, XLOOKUP(questions!$C$5,Lookup!$K$13:$K1000,Lookup!$M$13:$M1000,"missing",,1))} -> 228200 | AE22: {=IFS(B22<66, XLOOKUP(year(A22),Lookup!$K$13:$K1000,Lookup!$N$13:$N1000,"missing",,1),B22>65,XLOOKUP(questions!$C$5,Lookup!$K$13:$K1000,Lookup!$N$13:$N1000,"missing",,1))} -> 456400
A23: =eomonth(EDATE(A22,1),0) -> 46721 | B23: =round(YEARFRAC(EOMONTH(questions!$C$3, 0),A23,1),2) -> 29 | C23: =IF(B23<questions!$C$6,if(MONTH(A23)=1,C22*(1+questions!$C$12),C22),0) -> 10300 | D23: =IF(MONTH(A23)=12,C23*questions!$C$11,0) -> 0 | E23: =MIN(C23,IF(YEAR(A23)=2025,7600,8000)) -> 8000 | F23: =MIN(102000-E23*12,D23) -> 0 | G23: {=if(YEAR(A23)=2025,XLOOKUP(B23,Lookup!$A$3:$A$7,Lookup!$D$3:$D$7,,1)*SUM(E23:F23), XLOOKUP(B23,Lookup!$A$14:$A$18,Lookup!$D$14:$D$18,,1)*SUM(E23:F23))} -> 2960 | H23: {=if(YEAR(A23)=2025,XLOOKUP(B23,Lookup!$F$3:$F$10,Lookup!$G$3:$G$10,,1)*G23, XLOOKUP(B23,Lookup!$F$14:$F$21,Lookup!$G$14:$G$21,,1)*G23)} -> 1840.232 | I23: {=if(B23<55, if(YEAR(A23)=2025,XLOOKUP(B23,Lookup!$F$3:$F$10,Lookup!$H$3:$H$10,,1)*G23, XLOOKUP(B23,Lookup!$F$14:$F$21,Lookup!$H$14:$H$21,,1)*G23),0)} -> 479.816 | J23: {=if(YEAR(A23)=2025,XLOOKUP(B23,Lookup!$F$3:$F$10,Lookup!$I$3:$I$10,,1)*G23, XLOOKUP(B23,Lookup!$F$14:$F$21,Lookup!$I$14:$I$21,,1)*G23)} -> 639.952 | K23: {=if(B23>54, if(YEAR(A23)=2025,XLOOKUP(B23,Lookup!$F$3:$F$10,Lookup!$H$3:$H$10,,1)*G23, XLOOKUP(B23,Lookup!$F$14:$F$21,Lookup!$H$14:$H$21,,1)*G23),0)} -> 0 | L23: =IF(and(A23<questions!$C$19,questions!$C$18="yes"),questions!$C$20,0) -> 700 | M23: =(Y22+H23)*Lookup!A$26/12 -> 70.697219 | N23: =if(B23<55, (Z22+I23)*Lookup!B$26/12, (AB22+K23)*Lookup!B$26/12) -> 43.824412 | O23: =(AA22+J23)*Lookup!C$26/12 -> 55.426325 | P23: =IF(year(A23)=year(A22), P22+M23, M23) -> 647.01782 | Q23: =IF(year(A23)=year(A22), Q22+N23, N23) -> 394.10226 | R23: =IF(year(A23)=year(A22), R22+O23, O23) -> 492.36504 | S23: =if(B23<55,min(20000,Y22)*0.01/12,min(20000,Y22)*0.02/12) -> 16.666667 | T23: =if(B23<=55,min(60000-min(20000,Y22),Z22)*0.01/12,min(30000-min(20000,Y22),AB22)*0.02/12+min(30000,AB22)*0.01/12) -> 10.556256 | U23: =if(B23<55,min(60000-min(60000-min(20000,Y22),Z22)-min(20000,Y22),AA22)*0.01/12,min(30000-min(30000-min(20000,Y22),AB22)-min(20000,Y22),AA22)*0.02/12+min(30000-min(30000-min(20000,Y22),AB22)-min(20000,Y22),AA22)*0.01/12) -> 13.323288 | V23: =IF(year($A23)=year($A22), V22+S23, S23) -> 183.33333 | W23: =IF(year($A23)=year($A22), W22+T23, T23) -> 94.127253 | X23: =IF(year($A23)=year($A22), X22+U23, U23) -> 117.22503 | Y23: =IFS( B23<55, MAX( Y22 + IF(MONTH(A23)=12, P23+V23, 0) + H23 - L23 + MAX(0, IF(AA22 >= VLOOKUP(YEAR(A23), Lookup!$Q:$R, 2), Z22 + IF(MONTH(A23)=12, Q23+W23, 0) + I23 + AA22 + IF(MONTH(A23)=12, R23+X23, 0) - VLOOKUP(YEAR(A23), Lookup!$Q:$R, 2) + J23, Z22 + IF(MONTH(A23)=12, Q23+W23, 0) + I23 ) - VLOOKUP(YEAR(A23), Lookup!$K:$M, 3) ), 0), B23=55, IF(Z22>=AD23, MAX(Y22 + IF(MONTH(A23)=12, P23+V23, 0) + H23 - L23, 0), MAX(MAX(0, Y22-(AD23-Z22)) + IF(MONTH(A23)=12, P23+V23, 0) + H23 - L23, 0) ), B23>55, IF(AB22>=$AH$7, MAX(Y22 + IF(MONTH(A23)=12, P23+V23, 0) + H23 - L23 + K23 + Z22, 0), MAX(Y22 + IF(MONTH(A23)=12, P23+V23, 0) + H23 - L23, 0) ) ) -> 33234.665 | Z23: =IFS( B23<55, MIN( IF(AA22 >= VLOOKUP(YEAR(A23), Lookup!$Q:$R, 2), Z22 + IF(MONTH(A23)=12, Q23+W23, 0) + I23 + AA22 + IF(MONTH(A23)=12, R23+X23, 0) - VLOOKUP(YEAR(A23), Lookup!$Q:$R, 2) + J23, Z22 + IF(MONTH(A23)=12, Q23+W23, 0) + I23 ), VLOOKUP(YEAR(A23), Lookup!$K:$M, 3) ), B23=55, IF(Z22 >= AD23, Z22 - AD23, 0), B23>55, 0 ) -> 13147.324 | AA23: =IFS( B23<65, IF(AA22+J23 < VLOOKUP(YEAR(A23), Lookup!$Q:$R, 2), AA22 + IF(MONTH(A23)=12, R22+X22, 0) + J23, MIN( AA22 + IF(MONTH(A23)=12, R22+X22, 0) + J23 , VLOOKUP(YEAR(A23), Lookup!$Q:$R, 2) ) ), B23>=65, IF(AA22+J23 < VLOOKUP(questions!$C$5, Lookup!$Q:$R, 2), AA22 + IF(MONTH(A23)=12, R22+X22, 0) + J23 , MIN( AA22 + IF(MONTH(A23)=12, R22+X22, 0) + J23, VLOOKUP(questions!$C$5, Lookup!$Q:$R, 2) ) ) ) -> 16627.897 | AB23: =IFS( B23<55, 0, B23=55, MIN(Y22+Z22, AD23), B23>55, IF(AB22 < $AH$7, MIN(AB22 + IF(MONTH(A23)=12, Q23+W23, 0) + K23, $AH$7), AB22 + IF(MONTH(A23)=12, Q23+W23, 0) + K23 ) ) -> 0 | AC23: {=IFS(B23<66, XLOOKUP(year(A23),Lookup!$K$13:$K1000,Lookup!$L$13:$L1000,"missing",,1),B23>65,XLOOKUP(questions!$C$5,Lookup!$K$13:$K1000,Lookup!$L$13:$L1000,"missing",,1))} -> 114100 | AD23: {=IFS(B23<66, XLOOKUP(year(A23),Lookup!$K$13:$K1000,Lookup!$M$13:$M1000,"missing",,1),B23>65, XLOOKUP(questions!$C$5,Lookup!$K$13:$K1000,Lookup!$M$13:$M1000,"missing",,1))} -> 228200 | AE23: {=IFS(B23<66, XLOOKUP(year(A23),Lookup!$K$13:$K1000,Lookup!$N$13:$N1000,"missing",,1),B23>65,XLOOKUP(questions!$C$5,Lookup!$K$13:$K1000,Lookup!$N$13:$N1000,"missing",,1))} -> 456400
A24: =eomonth(EDATE(A23,1),0) -> 46752 | B24: =round(YEARFRAC(EOMONTH(questions!$C$3, 0),A24,1),2) -> 29.08 | C24: =IF(B24<questions!$C$6,if(MONTH(A24)=1,C23*(1+questions!$C$12),C23),0) -> 10300 | D24: =IF(MONTH(A24)=12,C24*questions!$C$11,0) -> 10300 | E24: =MIN(C24,IF(YEAR(A24)=2025,7600,8000)) -> 8000 | F24: =MIN(102000-E24*12,D24) -> 6000 | G24: {=if(YEAR(A24)=2025,XLOOKUP(B24,Lookup!$A$3:$A$7,Lookup!$D$3:$D$7,,1)*SUM(E24:F24), XLOOKUP(B24,Lookup!$A$14:$A$18,Lookup!$D$14:$D$18,,1)*SUM(E24:F24))} -> 5180 | H24: {=if(YEAR(A24)=2025,XLOOKUP(B24,Lookup!$F$3:$F$10,Lookup!$G$3:$G$10,,1)*G24, XLOOKUP(B24,Lookup!$F$14:$F$21,Lookup!$G$14:$G$21,,1)*G24)} -> 3220.406 | I24: {=if(B24<55, if(YEAR(A24)=2025,XLOOKUP(B24,Lookup!$F$3:$F$10,Lookup!$H$3:$H$10,,1)*G24, XLOOKUP(B24,Lookup!$F$14:$F$21,Lookup!$H$14:$H$21,,1)*G24),0)} -> 839.678 | J24: {=if(YEAR(A24)=2025,XLOOKUP(B24,Lookup!$F$3:$F$10,Lookup!$I$3:$I$10,,1)*G24, XLOOKUP(B24,Lookup!$F$14:$F$21,Lookup!$I$14:$I$21,,1)*G24)} -> 1119.916 | K24: {=if(B24>54, if(YEAR(A24)=2025,XLOOKUP(B24,Lookup!$F$3:$F$10,Lookup!$H$3:$H$10,,1)*G24, XLOOKUP(B24,Lookup!$F$14:$F$21,Lookup!$H$14:$H$21,,1)*G24),0)} -> 0 | L24: =IF(and(A24<questions!$C$19,questions!$C$18="yes"),questions!$C$20,0) -> 700 | M24: =(Y23+H24)*Lookup!A$26/12 -> 75.948065 | N24: =if(B24<55, (Z23+I24)*Lookup!B$26/12, (AB23+K24)*Lookup!B$26/12) -> 46.623339 | O24: =(AA23+J24)*Lookup!C$26/12 -> 59.159378 | P24: =IF(year(A24)=year(A23), P23+M24, M24) -> 722.96589 | Q24: =IF(year(A24)=year(A23), Q23+N24, N24) -> 440.7256 | R24: =IF(year(A24)=year(A23), R23+O24, O24) -> 551.52441 | S24: =if(B24<55,min(20000,Y23)*0.01/12,min(20000,Y23)*0.02/12) -> 16.666667 | T24: =if(B24<=55,min(60000-min(20000,Y23),Z23)*0.01/12,min(30000-min(20000,Y23),AB23)*0.02/12+min(30000,AB23)*0.01/12) -> 10.956103 | U24: =if(B24<55,min(60000-min(60000-min(20000,Y23),Z23)-min(20000,Y23),AA23)*0.01/12,min(30000-min(30000-min(20000,Y23),AB23)-min(20000,Y23),AA23)*0.02/12+min(30000-min(30000-min(20000,Y23),AB23)-min(20000,Y23),AA23)*0.01/12) -> 13.856581 | V24: =IF(year($A24)=year($A23), V23+S24, S24) -> 200 | W24: =IF(year($A24)=year($A23), W23+T24, T24) -> 105.08336 | X24: =IF(year($A24)=year($A23), X23+U24, U24) -> 131.08161 | Y24: =IFS( B24<55, MAX( Y23 + IF(MONTH(A24)=12, P24+V24, 0) + H24 - L24 + MAX(0, IF(AA23 >= VLOOKUP(YEAR(A24), Lookup!$Q:$R, 2), Z23 + IF(MONTH(A24)=12, Q24+W24, 0) + I24 + AA23 + IF(MONTH(A24)=12, R24+X24, 0) - VLOOKUP(YEAR(A24), Lookup!$Q:$R, 2) + J24, Z23 + IF(MONTH(A24)=12, Q24+W24, 0) + I24 ) - VLOOKUP(YEAR(A24), Lookup!$K:$M, 3) ), 0), B24=55, IF(Z23>=AD24, MAX(Y23 + IF(MONTH(A24)=12, P24+V24, 0) + H24 - L24, 0), MAX(MAX(0, Y23-(AD24-Z23)) + IF(MONTH(A24)=12, P24+V24, 0) + H24 - L24, 0) ), B24>55, IF(AB23>=$AH$7, MAX(Y23 + IF(MONTH(A24)=12, P24+V24, 0) + H24 - L24 + K24 + Z23, 0), MAX(Y23 + IF(MONTH(A24)=12, P24+V24, 0) + H24 - L24, 0) ) ) -> 36678.037 | Z24: =IFS( B24<55, MIN( IF(AA23 >= VLOOKUP(YEAR(A24), Lookup!$Q:$R, 2), Z23 + IF(MONTH(A24)=12, Q24+W24, 0) + I24 + AA23 + IF(MONTH(A24)=12, R24+X24, 0) - VLOOKUP(YEAR(A24), Lookup!$Q:$R, 2) + J24, Z23 + IF(MONTH(A24)=12, Q24+W24, 0) + I24 ), VLOOKUP(YEAR(A24), Lookup!$K:$M, 3) ), B24=55, IF(Z23 >= AD24, Z23 - AD24, 0), B24>55, 0 ) -> 14532.811 | AA24: =IFS( B24<65, IF(AA23+J24 < VLOOKUP(YEAR(A24), Lookup!$Q:$R, 2), AA23 + IF(MONTH(A24)=12, R23+X23, 0) + J24, MIN( AA23 + IF(MONTH(A24)=12, R23+X23, 0) + J24 , VLOOKUP(YEAR(A24), Lookup!$Q:$R, 2) ) ), B24>=65, IF(AA23+J24 < VLOOKUP(questions!$C$5, Lookup!$Q:$R, 2), AA23 + IF(MONTH(A24)=12, R23+X23, 0) + J24 , MIN( AA23 + IF(MONTH(A24)=12, R23+X23, 0) + J24, VLOOKUP(questions!$C$5, Lookup!$Q:$R, 2) ) ) ) -> 18357.403 | AB24: =IFS( B24<55, 0, B24=55, MIN(Y23+Z23, AD24), B24>55, IF(AB23 < $AH$7, MIN(AB23 + IF(MONTH(A24)=12, Q24+W24, 0) + K24, $AH$7), AB23 + IF(MONTH(A24)=12, Q24+W24, 0) + K24 ) ) -> 0 | AC24: {=IFS(B24<66, XLOOKUP(year(A24),Lookup!$K$13:$K1000,Lookup!$L$13:$L1000,"missing",,1),B24>65,XLOOKUP(questions!$C$5,Lookup!$K$13:$K1000,Lookup!$L$13:$L1000,"missing",,1))} -> 114100 | AD24: {=IFS(B24<66, XLOOKUP(year(A24),Lookup!$K$13:$K1000,Lookup!$M$13:$M1000,"missing",,1),B24>65, XLOOKUP(questions!$C$5,Lookup!$K$13:$K1000,Lookup!$M$13:$M1000,"missing",,1))} -> 228200 | AE24: {=IFS(B24<66, XLOOKUP(year(A24),Lookup!$K$13:$K1000,Lookup!$N$13:$N1000,"missing",,1),B24>65,XLOOKUP(questions!$C$5,Lookup!$K$13:$K1000,Lookup!$N$13:$N1000,"missing",,1))} -> 456400
A25: =eomonth(EDATE(A24,1),0) -> 46783 | B25: =round(YEARFRAC(EOMONTH(questions!$C$3, 0),A25,1),2) -> 29.17 | C25: =IF(B25<questions!$C$6,if(MONTH(A25)=1,C24*(1+questions!$C$12),C24),0) -> 10609 | D25: =IF(MONTH(A25)=12,C25*questions!$C$11,0) -> 0 | E25: =MIN(C25,IF(YEAR(A25)=2025,7600,8000)) -> 8000 | F25: =MIN(102000-E25*12,D25) -> 0 | G25: {=if(YEAR(A25)=2025,XLOOKUP(B25,Lookup!$A$3:$A$7,Lookup!$D$3:$D$7,,1)*SUM(E25:F25), XLOOKUP(B25,Lookup!$A$14:$A$18,Lookup!$D$14:$D$18,,1)*SUM(E25:F25))} -> 2960 | H25: {=if(YEAR(A25)=2025,XLOOKUP(B25,Lookup!$F$3:$F$10,Lookup!$G$3:$G$10,,1)*G25, XLOOKUP(B25,Lookup!$F$14:$F$21,Lookup!$G$14:$G$21,,1)*G25)} -> 1840.232 | I25: {=if(B25<55, if(YEAR(A25)=2025,XLOOKUP(B25,Lookup!$F$3:$F$10,Lookup!$H$3:$H$10,,1)*G25, XLOOKUP(B25,Lookup!$F$14:$F$21,Lookup!$H$14:$H$21,,1)*G25),0)} -> 479.816 | J25: {=if(YEAR(A25)=2025,XLOOKUP(B25,Lookup!$F$3:$F$10,Lookup!$I$3:$I$10,,1)*G25, XLOOKUP(B25,Lookup!$F$14:$F$21,Lookup!$I$14:$I$21,,1)*G25)} -> 639.952 | K25: {=if(B25>54, if(YEAR(A25)=2025,XLOOKUP(B25,Lookup!$F$3:$F$10,Lookup!$H$3:$H$10,,1)*G25, XLOOKUP(B25,Lookup!$F$14:$F$21,Lookup!$H$14:$H$21,,1)*G25),0)} -> 0 | L25: =IF(and(A25<questions!$C$19,questions!$C$18="yes"),questions!$C$20,0) -> 700 | M25: =(Y24+H25)*Lookup!A$26/12 -> 80.246393 | N25: =if(B25<55, (Z24+I25)*Lookup!B$26/12, (AB24+K25)*Lookup!B$26/12) -> 50.042088 | O25: =(AA24+J25)*Lookup!C$26/12 -> 63.324518 | P25: =IF(year(A25)=year(A24), P24+M25, M25) -> 80.246393 | Q25: =IF(year(A25)=year(A24), Q24+N25, N25) -> 50.042088 | R25: =IF(year(A25)=year(A24), R24+O25, O25) -> 63.324518 | S25: =if(B25<55,min(20000,Y24)*0.01/12,min(20000,Y24)*0.02/12) -> 16.666667 | T25: =if(B25<=55,min(60000-min(20000,Y24),Z24)*0.01/12,min(30000-min(20000,Y24),AB24)*0.02/12+min(30000,AB24)*0.01/12) -> 12.110675 | U25: =if(B25<55,min(60000-min(60000-min(20000,Y24),Z24)-min(20000,Y24),AA24)*0.01/12,min(30000-min(30000-min(20000,Y24),AB24)-min(20000,Y24),AA24)*0.02/12+min(30000-min(30000-min(20000,Y24),AB24)-min(20000,Y24),AA24)*0.01/12) -> 15.297836 | V25: =IF(year($A25)=year($A24), V24+S25, S25) -> 16.666667 | W25: =IF(year($A25)=year($A24), W24+T25, T25) -> 12.110675 | X25: =IF(year($A25)=year($A24), X24+U25, U25) -> 15.297836 | Y25: =IFS( B25<55, MAX( Y24 + IF(MONTH(A25)=12, P25+V25, 0) + H25 - L25 + MAX(0, IF(AA24 >= VLOOKUP(YEAR(A25), Lookup!$Q:$R, 2), Z24 + IF(MONTH(A25)=12, Q25+W25, 0) + I25 + AA24 + IF(MONTH(A25)=12, R25+X25, 0) - VLOOKUP(YEAR(A25), Lookup!$Q:$R, 2) + J25, Z24 + IF(MONTH(A25)=12, Q25+W25, 0) + I25 ) - VLOOKUP(YEAR(A25), Lookup!$K:$M, 3) ), 0), B25=55, IF(Z24>=AD25, MAX(Y24 + IF(MONTH(A25)=12, P25+V25, 0) + H25 - L25, 0), MAX(MAX(0, Y24-(AD25-Z24)) + IF(MONTH(A25)=12, P25+V25, 0) + H25 - L25, 0) ), B25>55, IF(AB24>=$AH$7, MAX(Y24 + IF(MONTH(A25)=12, P25+V25, 0) + H25 - L25 + K25 + Z24, 0), MAX(Y24 + IF(MONTH(A25)=12, P25+V25, 0) + H25 - L25, 0) ) ) -> 37818.269 | Z25: =IFS( B25<55, MIN( IF(AA24 >= VLOOKUP(YEAR(A25), Lookup!$Q:$R, 2), Z24 + IF(MONTH(A25)=12, Q25+W25, 0) + I25 + AA24 + IF(MONTH(A25)=12, R25+X25, 0) - VLOOKUP(YEAR(A25), Lookup!$Q:$R, 2) + J25, Z24 + IF(MONTH(A25)=12, Q25+W25, 0) + I25 ), VLOOKUP(YEAR(A25), Lookup!$K:$M, 3) ), B25=55, IF(Z24 >= AD25, Z24 - AD25, 0), B25>55, 0 ) -> 15012.627 | AA25: =IFS( B25<65, IF(AA24+J25 < VLOOKUP(YEAR(A25), Lookup!$Q:$R, 2), AA24 + IF(MONTH(A25)=12, R24+X24, 0) + J25, MIN( AA24 + IF(MONTH(A25)=12, R24+X24, 0) + J25 , VLOOKUP(YEAR(A25), Lookup!$Q:$R, 2) ) ), B25>=65, IF(AA24+J25 < VLOOKUP(questions!$C$5, Lookup!$Q:$R, 2), AA24 + IF(MONTH(A25)=12, R24+X24, 0) + J25 , MIN( AA24 + IF(MONTH(A25)=12, R24+X24, 0) + J25, VLOOKUP(questions!$C$5, Lookup!$Q:$R, 2) ) ) ) -> 18997.355 | AB25: =IFS( B25<55, 0, B25=55, MIN(Y24+Z24, AD25), B25>55, IF(AB24 < $AH$7, MIN(AB24 + IF(MONTH(A25)=12, Q25+W25, 0) + K25, $AH$7), AB24 + IF(MONTH(A25)=12, Q25+W25, 0) + K25 ) ) -> 0 | AC25: {=IFS(B25<66, XLOOKUP(year(A25),Lookup!$K$13:$K1000,Lookup!$L$13:$L1000,"missing",,1),B25>65,XLOOKUP(questions!$C$5,Lookup!$K$13:$K1000,Lookup!$L$13:$L1000,"missing",,1))} -> 118093.5 | AD25: {=IFS(B25<66, XLOOKUP(year(A25),Lookup!$K$13:$K1000,Lookup!$M$13:$M1000,"missing",,1),B25>65, XLOOKUP(questions!$C$5,Lookup!$K$13:$K1000,Lookup!$M$13:$M1000,"missing",,1))} -> 236187 | AE25: {=IFS(B25<66, XLOOKUP(year(A25),Lookup!$K$13:$K1000,Lookup!$N$13:$N1000,"missing",,1),B25>65,XLOOKUP(questions!$C$5,Lookup!$K$13:$K1000,Lookup!$N$13:$N1000,"missing",,1))} -> 472374
A26: =eomonth(EDATE(A25,1),0) -> 46812 | B26: =round(YEARFRAC(EOMONTH(questions!$C$3, 0),A26,1),2) -> 29.25 | C26: =IF(B26<questions!$C$6,if(MONTH(A26)=1,C25*(1+questions!$C$12),C25),0) -> 10609 | D26: =IF(MONTH(A26)=12,C26*questions!$C$11,0) -> 0 | E26: =MIN(C26,IF(YEAR(A26)=2025,7600,8000)) -> 8000 | F26: =MIN(102000-E26*12,D26) -> 0 | G26: {=if(YEAR(A26)=2025,XLOOKUP(B26,Lookup!$A$3:$A$7,Lookup!$D$3:$D$7,,1)*SUM(E26:F26), XLOOKUP(B26,Lookup!$A$14:$A$18,Lookup!$D$14:$D$18,,1)*SUM(E26:F26))} -> 2960 | H26: {=if(YEAR(A26)=2025,XLOOKUP(B26,Lookup!$F$3:$F$10,Lookup!$G$3:$G$10,,1)*G26, XLOOKUP(B26,Lookup!$F$14:$F$21,Lookup!$G$14:$G$21,,1)*G26)} -> 1840.232 | I26: {=if(B26<55, if(YEAR(A26)=2025,XLOOKUP(B26,Lookup!$F$3:$F$10,Lookup!$H$3:$H$10,,1)*G26, XLOOKUP(B26,Lookup!$F$14:$F$21,Lookup!$H$14:$H$21,,1)*G26),0)} -> 479.816 | J26: {=if(YEAR(A26)=2025,XLOOKUP(B26,Lookup!$F$3:$F$10,Lookup!$I$3:$I$10,,1)*G26, XLOOKUP(B26,Lookup!$F$14:$F$21,Lookup!$I$14:$I$21,,1)*G26)} -> 639.952 | K26: {=if(B26>54, if(YEAR(A26)=2025,XLOOKUP(B26,Lookup!$F$3:$F$10,Lookup!$H$3:$H$10,,1)*G26, XLOOKUP(B26,Lookup!$F$14:$F$21,Lookup!$H$14:$H$21,,1)*G26),0)} -> 0 | L26: =IF(and(A26<questions!$C$19,questions!$C$18="yes"),questions!$C$20,0) -> 700 | M26: =(Y25+H26)*Lookup!A$26/12 -> 82.621877 | N26: =if(B26<55, (Z25+I26)*Lookup!B$26/12, (AB25+K26)*Lookup!B$26/12) -> 51.641475 | O26: =(AA25+J26)*Lookup!C$26/12 -> 65.457691 | P26: =IF(year(A26)=year(A25), P25+M26, M26) -> 162.86827 | Q26: =IF(year(A26)=year(A25), Q25+N26, N26) -> 101.68356 | R26: =IF(year(A26)=year(A25), R25+O26, O26) -> 128.78221 | S26: =if(B26<55,min(20000,Y25)*0.01/12,min(20000,Y25)*0.02/12) -> 16.666667 | T26: =if(B26<=55,min(60000-min(20000,Y25),Z25)*0.01/12,min(30000-min(20000,Y25),AB25)*0.02/12+min(30000,AB25)*0.01/12) -> 12.510522 | U26: =if(B26<55,min(60000-min(60000-min(20000,Y25),Z25)-min(20000,Y25),AA25)*0.01/12,min(30000-min(30000-min(20000,Y25),AB25)-min(20000,Y25),AA25)*0.02/12+min(30000-min(30000-min(20000,Y25),AB25)-min(20000,Y25),AA25)*0.01/12) -> 15.83113 | V26: =IF(year($A26)=year($A25), V25+S26, S26) -> 33.333333 | W26: =IF(year($A26)=year($A25), W25+T26, T26) -> 24.621198 | X26: =IF(year($A26)=year($A25), X25+U26, U26) -> 31.128966 | Y26: =IFS( B26<55, MAX( Y25 + IF(MONTH(A26)=12, P26+V26, 0) + H26 - L26 + MAX(0, IF(AA25 >= VLOOKUP(YEAR(A26), Lookup!$Q:$R, 2), Z25 + IF(MONTH(A26)=12, Q26+W26, 0) + I26 + AA25 + IF(MONTH(A26)=12, R26+X26, 0) - VLOOKUP(YEAR(A26), Lookup!$Q:$R, 2) + J26, Z25 + IF(MONTH(A26)=12, Q26+W26, 0) + I26 ) - VLOOKUP(YEAR(A26), Lookup!$K:$M, 3) ), 0), B26=55, IF(Z25>=AD26, MAX(Y25 + IF(MONTH(A26)=12, P26+V26, 0) + H26 - L26, 0), MAX(MAX(0, Y25-(AD26-Z25)) + IF(MONTH(A26)=12, P26+V26, 0) + H26 - L26, 0) ), B26>55, IF(AB25>=$AH$7, MAX(Y25 + IF(MONTH(A26)=12, P26+V26, 0) + H26 - L26 + K26 + Z25, 0), MAX(Y25 + IF(MONTH(A26)=12, P26+V26, 0) + H26 - L26, 0) ) ) -> 38958.501 | Z26: =IFS( B26<55, MIN( IF(AA25 >= VLOOKUP(YEAR(A26), Lookup!$Q:$R, 2), Z25 + IF(MONTH(A26)=12, Q26+W26, 0) + I26 + AA25 + IF(MONTH(A26)=12, R26+X26, 0) - VLOOKUP(YEAR(A26), Lookup!$Q:$R, 2) + J26, Z25 + IF(MONTH(A26)=12, Q26+W26, 0) + I26 ), VLOOKUP(YEAR(A26), Lookup!$K:$M, 3) ), B26=55, IF(Z25 >= AD26, Z25 - AD26, 0), B26>55, 0 ) -> 15492.443 | AA26: =IFS( B26<65, IF(AA25+J26 < VLOOKUP(YEAR(A26), Lookup!$Q:$R, 2), AA25 + IF(MONTH(A26)=12, R25+X25, 0) + J26, MIN( AA25 + IF(MONTH(A26)=12, R25+X25, 0) + J26 , VLOOKUP(YEAR(A26), Lookup!$Q:$R, 2) ) ), B26>=65, IF(AA25+J26 < VLOOKUP(questions!$C$5, Lookup!$Q:$R, 2), AA25 + IF(MONTH(A26)=12, R25+X25, 0) + J26 , MIN( AA25 + IF(MONTH(A26)=12, R25+X25, 0) + J26, VLOOKUP(questions!$C$5, Lookup!$Q:$R, 2) ) ) ) -> 19637.307 | AB26: =IFS( B26<55, 0, B26=55, MIN(Y25+Z25, AD26), B26>55, IF(AB25 < $AH$7, MIN(AB25 + IF(MONTH(A26)=12, Q26+W26, 0) + K26, $AH$7), AB25 + IF(MONTH(A26)=12, Q26+W26, 0) + K26 ) ) -> 0 | AC26: {=IFS(B26<66, XLOOKUP(year(A26),Lookup!$K$13:$K1000,Lookup!$L$13:$L1000,"missing",,1),B26>65,XLOOKUP(questions!$C$5,Lookup!$K$13:$K1000,Lookup!$L$13:$L1000,"missing",,1))} -> 118093.5 | AD26: {=IFS(B26<66, XLOOKUP(year(A26),Lookup!$K$13:$K1000,Lookup!$M$13:$M1000,"missing",,1),B26>65, XLOOKUP(questions!$C$5,Lookup!$K$13:$K1000,Lookup!$M$13:$M1000,"missing",,1))} -> 236187 | AE26: {=IFS(B26<66, XLOOKUP(year(A26),Lookup!$K$13:$K1000,Lookup!$N$13:$N1000,"missing",,1),B26>65,XLOOKUP(questions!$C$5,Lookup!$K$13:$K1000,Lookup!$N$13:$N1000,"missing",,1))} -> 472374
A27: =eomonth(EDATE(A26,1),0) -> 46843 | B27: =round(YEARFRAC(EOMONTH(questions!$C$3, 0),A27,1),2) -> 29.33 | C27: =IF(B27<questions!$C$6,if(MONTH(A27)=1,C26*(1+questions!$C$12),C26),0) -> 10609 | D27: =IF(MONTH(A27)=12,C27*questions!$C$11,0) -> 0 | E27: =MIN(C27,IF(YEAR(A27)=2025,7600,8000)) -> 8000 | F27: =MIN(102000-E27*12,D27) -> 0 | G27: {=if(YEAR(A27)=2025,XLOOKUP(B27,Lookup!$A$3:$A$7,Lookup!$D$3:$D$7,,1)*SUM(E27:F27), XLOOKUP(B27,Lookup!$A$14:$A$18,Lookup!$D$14:$D$18,,1)*SUM(E27:F27))} -> 2960 | H27: {=if(YEAR(A27)=2025,XLOOKUP(B27,Lookup!$F$3:$F$10,Lookup!$G$3:$G$10,,1)*G27, XLOOKUP(B27,Lookup!$F$14:$F$21,Lookup!$G$14:$G$21,,1)*G27)} -> 1840.232 | I27: {=if(B27<55, if(YEAR(A27)=2025,XLOOKUP(B27,Lookup!$F$3:$F$10,Lookup!$H$3:$H$10,,1)*G27, XLOOKUP(B27,Lookup!$F$14:$F$21,Lookup!$H$14:$H$21,,1)*G27),0)} -> 479.816 | J27: {=if(YEAR(A27)=2025,XLOOKUP(B27,Lookup!$F$3:$F$10,Lookup!$I$3:$I$10,,1)*G27, XLOOKUP(B27,Lookup!$F$14:$F$21,Lookup!$I$14:$I$21,,1)*G27)} -> 639.952 | K27: {=if(B27>54, if(YEAR(A27)=2025,XLOOKUP(B27,Lookup!$F$3:$F$10,Lookup!$H$3:$H$10,,1)*G27, XLOOKUP(B27,Lookup!$F$14:$F$21,Lookup!$H$14:$H$21,,1)*G27),0)} -> 0 | L27: =IF(and(A27<questions!$C$19,questions!$C$18="yes"),questions!$C$20,0) -> 700 | M27: =(Y26+H27)*Lookup!A$26/12 -> 84.99736 | N27: =if(B27<55, (Z26+I27)*Lookup!B$26/12, (AB26+K27)*Lookup!B$26/12) -> 53.240862 | O27: =(AA26+J27)*Lookup!C$26/12 -> 67.590865 | P27: =IF(year(A27)=year(A26), P26+M27, M27) -> 247.86563 | Q27: =IF(year(A27)=year(A26), Q26+N27, N27) -> 154.92443 | R27: =IF(year(A27)=year(A26), R26+O27, O27) -> 196.37307 | S27: =if(B27<55,min(20000,Y26)*0.01/12,min(20000,Y26)*0.02/12) -> 16.666667 | T27: =if(B27<=55,min(60000-min(20000,Y26),Z26)*0.01/12,min(30000-min(20000,Y26),AB26)*0.02/12+min(30000,AB26)*0.01/12) -> 12.910369 | U27: =if(B27<55,min(60000-min(60000-min(20000,Y26),Z26)-min(20000,Y26),AA26)*0.01/12,min(30000-min(30000-min(20000,Y26),AB26)-min(20000,Y26),AA26)*0.02/12+min(30000-min(30000-min(20000,Y26),AB26)-min(20000,Y26),AA26)*0.01/12) -> 16.364423 | V27: =IF(year($A27)=year($A26), V26+S27, S27) -> 50 | W27: =IF(year($A27)=year($A26), W26+T27, T27) -> 37.531566 | X27: =IF(year($A27)=year($A26), X26+U27, U27) -> 47.493389 | Y27: =IFS( B27<55, MAX( Y26 + IF(MONTH(A27)=12, P27+V27, 0) + H27 - L27 + MAX(0, IF(AA26 >= VLOOKUP(YEAR(A27), Lookup!$Q:$R, 2), Z26 + IF(MONTH(A27)=12, Q27+W27, 0) + I27 + AA26 + IF(MONTH(A27)=12, R27+X27, 0) - VLOOKUP(YEAR(A27), Lookup!$Q:$R, 2) + J27, Z26 + IF(MONTH(A27)=12, Q27+W27, 0) + I27 ) - VLOOKUP(YEAR(A27), Lookup!$K:$M, 3) ), 0), B27=55, IF(Z26>=AD27, MAX(Y26 + IF(MONTH(A27)=12, P27+V27, 0) + H27 - L27, 0), MAX(MAX(0, Y26-(AD27-Z26)) + IF(MONTH(A27)=12, P27+V27, 0) + H27 - L27, 0) ), B27>55, IF(AB26>=$AH$7, MAX(Y26 + IF(MONTH(A27)=12, P27+V27, 0) + H27 - L27 + K27 + Z26, 0), MAX(Y26 + IF(MONTH(A27)=12, P27+V27, 0) + H27 - L27, 0) ) ) -> 40098.733 | Z27: =IFS( B27<55, MIN( IF(AA26 >= VLOOKUP(YEAR(A27), Lookup!$Q:$R, 2), Z26 + IF(MONTH(A27)=12, Q27+W27, 0) + I27 + AA26 + IF(MONTH(A27)=12, R27+X27, 0) - VLOOKUP(YEAR(A27), Lookup!$Q:$R, 2) + J27, Z26 + IF(MONTH(A27)=12, Q27+W27, 0) + I27 ), VLOOKUP(YEAR(A27), Lookup!$K:$M, 3) ), B27=55, IF(Z26 >= AD27, Z26 - AD27, 0), B27>55, 0 ) -> 15972.259 | AA27: =IFS( B27<65, IF(AA26+J27 < VLOOKUP(YEAR(A27), Lookup!$Q:$R, 2), AA26 + IF(MONTH(A27)=12, R26+X26, 0) + J27, MIN( AA26 + IF(MONTH(A27)=12, R26+X26, 0) + J27 , VLOOKUP(YEAR(A27), Lookup!$Q:$R, 2) ) ), B27>=65, IF(AA26+J27 < VLOOKUP(questions!$C$5, Lookup!$Q:$R, 2), AA26 + IF(MONTH(A27)=12, R26+X26, 0) + J27 , MIN( AA26 + IF(MONTH(A27)=12, R26+X26, 0) + J27, VLOOKUP(questions!$C$5, Lookup!$Q:$R, 2) ) ) ) -> 20277.259 | AB27: =IFS( B27<55, 0, B27=55, MIN(Y26+Z26, AD27), B27>55, IF(AB26 < $AH$7, MIN(AB26 + IF(MONTH(A27)=12, Q27+W27, 0) + K27, $AH$7), AB26 + IF(MONTH(A27)=12, Q27+W27, 0) + K27 ) ) -> 0 | AC27: {=IFS(B27<66, XLOOKUP(year(A27),Lookup!$K$13:$K1000,Lookup!$L$13:$L1000,"missing",,1),B27>65,XLOOKUP(questions!$C$5,Lookup!$K$13:$K1000,Lookup!$L$13:$L1000,"missing",,1))} -> 118093.5 | AD27: {=IFS(B27<66, XLOOKUP(year(A27),Lookup!$K$13:$K1000,Lookup!$M$13:$M1000,"missing",,1),B27>65, XLOOKUP(questions!$C$5,Lookup!$K$13:$K1000,Lookup!$M$13:$M1000,"missing",,1))} -> 236187 | AE27: {=IFS(B27<66, XLOOKUP(year(A27),Lookup!$K$13:$K1000,Lookup!$N$13:$N1000,"missing",,1),B27>65,XLOOKUP(questions!$C$5,Lookup!$K$13:$K1000,Lookup!$N$13:$N1000,"missing",,1))} -> 472374
A28: =eomonth(EDATE(A27,1),0) -> 46873 | B28: =round(YEARFRAC(EOMONTH(questions!$C$3, 0),A28,1),2) -> 29.42 | C28: =IF(B28<questions!$C$6,if(MONTH(A28)=1,C27*(1+questions!$C$12),C27),0) -> 10609 | D28: =IF(MONTH(A28)=12,C28*questions!$C$11,0) -> 0 | E28: =MIN(C28,IF(YEAR(A28)=2025,7600,8000)) -> 8000 | F28: =MIN(102000-E28*12,D28) -> 0 | G28: {=if(YEAR(A28)=2025,XLOOKUP(B28,Lookup!$A$3:$A$7,Lookup!$D$3:$D$7,,1)*SUM(E28:F28), XLOOKUP(B28,Lookup!$A$14:$A$18,Lookup!$D$14:$D$18,,1)*SUM(E28:F28))} -> 2960 | H28: {=if(YEAR(A28)=2025,XLOOKUP(B28,Lookup!$F$3:$F$10,Lookup!$G$3:$G$10,,1)*G28, XLOOKUP(B28,Lookup!$F$14:$F$21,Lookup!$G$14:$G$21,,1)*G28)} -> 1840.232 | I28: {=if(B28<55, if(YEAR(A28)=2025,XLOOKUP(B28,Lookup!$F$3:$F$10,Lookup!$H$3:$H$10,,1)*G28, XLOOKUP(B28,Lookup!$F$14:$F$21,Lookup!$H$14:$H$21,,1)*G28),0)} -> 479.816 | J28: {=if(YEAR(A28)=2025,XLOOKUP(B28,Lookup!$F$3:$F$10,Lookup!$I$3:$I$10,,1)*G28, XLOOKUP(B28,Lookup!$F$14:$F$21,Lookup!$I$14:$I$21,,1)*G28)} -> 639.952 | K28: {=if(B28>54, if(YEAR(A28)=2025,XLOOKUP(B28,Lookup!$F$3:$F$10,Lookup!$H$3:$H$10,,1)*G28, XLOOKUP(B28,Lookup!$F$14:$F$21,Lookup!$H$14:$H$21,,1)*G28),0)} -> 0 | L28: =IF(and(A28<questions!$C$19,questions!$C$18="yes"),questions!$C$20,0) -> 700 | M28: =(Y27+H28)*Lookup!A$26/12 -> 87.372843 | N28: =if(B28<55, (Z27+I28)*Lookup!B$26/12, (AB27+K28)*Lookup!B$26/12) -> 54.840248 | O28: =(AA27+J28)*Lookup!C$26/12 -> 69.724038 | P28: =IF(year(A28)=year(A27), P27+M28, M28) -> 335.23847 | Q28: =IF(year(A28)=year(A27), Q27+N28, N28) -> 209.76467 | R28: =IF(year(A28)=year(A27), R27+O28, O28) -> 266.09711 | S28: =if(B28<55,min(20000,Y27)*0.01/12,min(20000,Y27)*0.02/12) -> 16.666667 | T28: =if(B28<=55,min(60000-min(20000,Y27),Z27)*0.01/12,min(30000-min(20000,Y27),AB27)*0.02/12+min(30000,AB27)*0.01/12) -> 13.310215 | U28: =if(B28<55,min(60000-min(60000-min(20000,Y27),Z27)-min(20000,Y27),AA27)*0.01/12,min(30000-min(30000-min(20000,Y27),AB27)-min(20000,Y27),AA27)*0.02/12+min(30000-min(30000-min(20000,Y27),AB27)-min(20000,Y27),AA27)*0.01/12) -> 16.897716 | V28: =IF(year($A28)=year($A27), V27+S28, S28) -> 66.666667 | W28: =IF(year($A28)=year($A27), W27+T28, T28) -> 50.841782 | X28: =IF(year($A28)=year($A27), X27+U28, U28) -> 64.391105 | Y28: =IFS( B28<55, MAX( Y27 + IF(MONTH(A28)=12, P28+V28, 0) + H28 - L28 + MAX(0, IF(AA27 >= VLOOKUP(YEAR(A28), Lookup!$Q:$R, 2), Z27 + IF(MONTH(A28)=12, Q28+W28, 0) + I28 + AA27 + IF(MONTH(A28)=12, R28+X28, 0) - VLOOKUP(YEAR(A28), Lookup!$Q:$R, 2) + J28, Z27 + IF(MONTH(A28)=12, Q28+W28, 0) + I28 ) - VLOOKUP(YEAR(A28), Lookup!$K:$M, 3) ), 0), B28=55, IF(Z27>=AD28, MAX(Y27 + IF(MONTH(A28)=12, P28+V28, 0) + H28 - L28, 0), MAX(MAX(0, Y27-(AD28-Z27)) + IF(MONTH(A28)=12, P28+V28, 0) + H28 - L28, 0) ), B28>55, IF(AB27>=$AH$7, MAX(Y27 + IF(MONTH(A28)=12, P28+V28, 0) + H28 - L28 + K28 + Z27, 0), MAX(Y27 + IF(MONTH(A28)=12, P28+V28, 0) + H28 - L28, 0) ) ) -> 41238.965 | Z28: =IFS( B28<55, MIN( IF(AA27 >= VLOOKUP(YEAR(A28), Lookup!$Q:$R, 2), Z27 + IF(MONTH(A28)=12, Q28+W28, 0) + I28 + AA27 + IF(MONTH(A28)=12, R28+X28, 0) - VLOOKUP(YEAR(A28), Lookup!$Q:$R, 2) + J28, Z27 + IF(MONTH(A28)=12, Q28+W28, 0) + I28 ), VLOOKUP(YEAR(A28), Lookup!$K:$M, 3) ), B28=55, IF(Z27 >= AD28, Z27 - AD28, 0), B28>55, 0 ) -> 16452.075 | AA28: =IFS( B28<65, IF(AA27+J28 < VLOOKUP(YEAR(A28), Lookup!$Q:$R, 2), AA27 + IF(MONTH(A28)=12, R27+X27, 0) + J28, MIN( AA27 + IF(MONTH(A28)=12, R27+X27, 0) + J28 , VLOOKUP(YEAR(A28), Lookup!$Q:$R, 2) ) ), B28>=65, IF(AA27+J28 < VLOOKUP(questions!$C$5, Lookup!$Q:$R, 2), AA27 + IF(MONTH(A28)=12, R27+X27, 0) + J28 , MIN( AA27 + IF(MONTH(A28)=12, R27+X27, 0) + J28, VLOOKUP(questions!$C$5, Lookup!$Q:$R, 2) ) ) ) -> 20917.211 | AB28: =IFS( B28<55, 0, B28=55, MIN(Y27+Z27, AD28), B28>55, IF(AB27 < $AH$7, MIN(AB27 + IF(MONTH(A28)=12, Q28+W28, 0) + K28, $AH$7), AB27 + IF(MONTH(A28)=12, Q28+W28, 0) + K28 ) ) -> 0 | AC28: {=IFS(B28<66, XLOOKUP(year(A28),Lookup!$K$13:$K1000,Lookup!$L$13:$L1000,"missing",,1),B28>65,XLOOKUP(questions!$C$5,Lookup!$K$13:$K1000,Lookup!$L$13:$L1000,"missing",,1))} -> 118093.5 | AD28: {=IFS(B28<66, XLOOKUP(year(A28),Lookup!$K$13:$K1000,Lookup!$M$13:$M1000,"missing",,1),B28>65, XLOOKUP(questions!$C$5,Lookup!$K$13:$K1000,Lookup!$M$13:$M1000,"missing",,1))} -> 236187 | AE28: {=IFS(B28<66, XLOOKUP(year(A28),Lookup!$K$13:$K1000,Lookup!$N$13:$N1000,"missing",,1),B28>65,XLOOKUP(questions!$C$5,Lookup!$K$13:$K1000,Lookup!$N$13:$N1000,"missing",,1))} -> 472374
A29: =eomonth(EDATE(A28,1),0) -> 46904 | B29: =round(YEARFRAC(EOMONTH(questions!$C$3, 0),A29,1),2) -> 29.5 | C29: =IF(B29<questions!$C$6,if(MONTH(A29)=1,C28*(1+questions!$C$12),C28),0) -> 10609 | D29: =IF(MONTH(A29)=12,C29*questions!$C$11,0) -> 0 | E29: =MIN(C29,IF(YEAR(A29)=2025,7600,8000)) -> 8000 | F29: =MIN(102000-E29*12,D29) -> 0 | G29: {=if(YEAR(A29)=2025,XLOOKUP(B29,Lookup!$A$3:$A$7,Lookup!$D$3:$D$7,,1)*SUM(E29:F29), XLOOKUP(B29,Lookup!$A$14:$A$18,Lookup!$D$14:$D$18,,1)*SUM(E29:F29))} -> 2960 | H29: {=if(YEAR(A29)=2025,XLOOKUP(B29,Lookup!$F$3:$F$10,Lookup!$G$3:$G$10,,1)*G29, XLOOKUP(B29,Lookup!$F$14:$F$21,Lookup!$G$14:$G$21,,1)*G29)} -> 1840.232 | I29: {=if(B29<55, if(YEAR(A29)=2025,XLOOKUP(B29,Lookup!$F$3:$F$10,Lookup!$H$3:$H$10,,1)*G29, XLOOKUP(B29,Lookup!$F$14:$F$21,Lookup!$H$14:$H$21,,1)*G29),0)} -> 479.816 | J29: {=if(YEAR(A29)=2025,XLOOKUP(B29,Lookup!$F$3:$F$10,Lookup!$I$3:$I$10,,1)*G29, XLOOKUP(B29,Lookup!$F$14:$F$21,Lookup!$I$14:$I$21,,1)*G29)} -> 639.952 | K29: {=if(B29>54, if(YEAR(A29)=2025,XLOOKUP(B29,Lookup!$F$3:$F$10,Lookup!$H$3:$H$10,,1)*G29, XLOOKUP(B29,Lookup!$F$14:$F$21,Lookup!$H$14:$H$21,,1)*G29),0)} -> 0 | L29: =IF(and(A29<questions!$C$19,questions!$C$18="yes"),questions!$C$20,0) -> 700 | M29: =(Y28+H29)*Lookup!A$26/12 -> 89.748327 | N29: =if(B29<55, (Z28+I29)*Lookup!B$26/12, (AB28+K29)*Lookup!B$26/12) -> 56.439635 | O29: =(AA28+J29)*Lookup!C$26/12 -> 71.857211 | P29: =IF(year(A29)=year(A28), P28+M29, M29) -> 424.9868 | Q29: =IF(year(A29)=year(A28), Q28+N29, N29) -> 266.20431 | R29: =IF(year(A29)=year(A28), R28+O29, O29) -> 337.95432 | S29: =if(B29<55,min(20000,Y28)*0.01/12,min(20000,Y28)*0.02/12) -> 16.666667 | T29: =if(B29<=55,min(60000-min(20000,Y28),Z28)*0.01/12,min(30000-min(20000,Y28),AB28)*0.02/12+min(30000,AB28)*0.01/12) -> 13.710062 | U29: =if(B29<55,min(60000-min(60000-min(20000,Y28),Z28)-min(20000,Y28),AA28)*0.01/12,min(30000-min(30000-min(20000,Y28),AB28)-min(20000,Y28),AA28)*0.02/12+min(30000-min(30000-min(20000,Y28),AB28)-min(20000,Y28),AA28)*0.01/12) -> 17.43101 | V29: =IF(year($A29)=year($A28), V28+S29, S29) -> 83.333333 | W29: =IF(year($A29)=year($A28), W28+T29, T29) -> 64.551844 | X29: =IF(year($A29)=year($A28), X28+U29, U29) -> 81.822114 | Y29: =IFS( B29<55, MAX( Y28 + IF(MONTH(A29)=12, P29+V29, 0) + H29 - L29 + MAX(0, IF(AA28 >= VLOOKUP(YEAR(A29), Lookup!$Q:$R, 2), Z28 + IF(MONTH(A29)=12, Q29+W29, 0) + I29 + AA28 + IF(MONTH(A29)=12, R29+X29, 0) - VLOOKUP(YEAR(A29), Lookup!$Q:$R, 2) + J29, Z28 + IF(MONTH(A29)=12, Q29+W29, 0) + I29 ) - VLOOKUP(YEAR(A29), Lookup!$K:$M, 3) ), 0), B29=55, IF(Z28>=AD29, MAX(Y28 + IF(MONTH(A29)=12, P29+V29, 0) + H29 - L29, 0), MAX(MAX(0, Y28-(AD29-Z28)) + IF(MONTH(A29)=12, P29+V29, 0) + H29 - L29, 0) ), B29>55, IF(AB28>=$AH$7, MAX(Y28 + IF(MONTH(A29)=12, P29+V29, 0) + H29 - L29 + K29 + Z28, 0), MAX(Y28 + IF(MONTH(A29)=12, P29+V29, 0) + H29 - L29, 0) ) ) -> 42379.197 | Z29: =IFS( B29<55, MIN( IF(AA28 >= VLOOKUP(YEAR(A29), Lookup!$Q:$R, 2), Z28 + IF(MONTH(A29)=12, Q29+W29, 0) + I29 + AA28 + IF(MONTH(A29)=12, R29+X29, 0) - VLOOKUP(YEAR(A29), Lookup!$Q:$R, 2) + J29, Z28 + IF(MONTH(A29)=12, Q29+W29, 0) + I29 ), VLOOKUP(YEAR(A29), Lookup!$K:$M, 3) ), B29=55, IF(Z28 >= AD29, Z28 - AD29, 0), B29>55, 0 ) -> 16931.891 | AA29: =IFS( B29<65, IF(AA28+J29 < VLOOKUP(YEAR(A29), Lookup!$Q:$R, 2), AA28 + IF(MONTH(A29)=12, R28+X28, 0) + J29, MIN( AA28 + IF(MONTH(A29)=12, R28+X28, 0) + J29 , VLOOKUP(YEAR(A29), Lookup!$Q:$R, 2) ) ), B29>=65, IF(AA28+J29 < VLOOKUP(questions!$C$5, Lookup!$Q:$R, 2), AA28 + IF(MONTH(A29)=12, R28+X28, 0) + J29 , MIN( AA28 + IF(MONTH(A29)=12, R28+X28, 0) + J29, VLOOKUP(questions!$C$5, Lookup!$Q:$R, 2) ) ) ) -> 21557.163 | AB29: =IFS( B29<55, 0, B29=55, MIN(Y28+Z28, AD29), B29>55, IF(AB28 < $AH$7, MIN(AB28 + IF(MONTH(A29)=12, Q29+W29, 0) + K29, $AH$7), AB28 + IF(MONTH(A29)=12, Q29+W29, 0) + K29 ) ) -> 0 | AC29: {=IFS(B29<66, XLOOKUP(year(A29),Lookup!$K$13:$K1000,Lookup!$L$13:$L1000,"missing",,1),B29>65,XLOOKUP(questions!$C$5,Lookup!$K$13:$K1000,Lookup!$L$13:$L1000,"missing",,1))} -> 118093.5 | AD29: {=IFS(B29<66, XLOOKUP(year(A29),Lookup!$K$13:$K1000,Lookup!$M$13:$M1000,"missing",,1),B29>65, XLOOKUP(questions!$C$5,Lookup!$K$13:$K1000,Lookup!$M$13:$M1000,"missing",,1))} -> 236187 | AE29: {=IFS(B29<66, XLOOKUP(year(A29),Lookup!$K$13:$K1000,Lookup!$N$13:$N1000,"missing",,1),B29>65,XLOOKUP(questions!$C$5,Lookup!$K$13:$K1000,Lookup!$N$13:$N1000,"missing",,1))} -> 472374
A30: =eomonth(EDATE(A29,1),0) -> 46934 | B30: =round(YEARFRAC(EOMONTH(questions!$C$3, 0),A30,1),2) -> 29.58 | C30: =IF(B30<questions!$C$6,if(MONTH(A30)=1,C29*(1+questions!$C$12),C29),0) -> 10609 | D30: =IF(MONTH(A30)=12,C30*questions!$C$11,0) -> 0 | E30: =MIN(C30,IF(YEAR(A30)=2025,7600,8000)) -> 8000 | F30: =MIN(102000-E30*12,D30) -> 0 | G30: {=if(YEAR(A30)=2025,XLOOKUP(B30,Lookup!$A$3:$A$7,Lookup!$D$3:$D$7,,1)*SUM(E30:F30), XLOOKUP(B30,Lookup!$A$14:$A$18,Lookup!$D$14:$D$18,,1)*SUM(E30:F30))} -> 2960 | H30: {=if(YEAR(A30)=2025,XLOOKUP(B30,Lookup!$F$3:$F$10,Lookup!$G$3:$G$10,,1)*G30, XLOOKUP(B30,Lookup!$F$14:$F$21,Lookup!$G$14:$G$21,,1)*G30)} -> 1840.232 | I30: {=if(B30<55, if(YEAR(A30)=2025,XLOOKUP(B30,Lookup!$F$3:$F$10,Lookup!$H$3:$H$10,,1)*G30, XLOOKUP(B30,Lookup!$F$14:$F$21,Lookup!$H$14:$H$21,,1)*G30),0)} -> 479.816 | J30: {=if(YEAR(A30)=2025,XLOOKUP(B30,Lookup!$F$3:$F$10,Lookup!$I$3:$I$10,,1)*G30, XLOOKUP(B30,Lookup!$F$14:$F$21,Lookup!$I$14:$I$21,,1)*G30)} -> 639.952 | K30: {=if(B30>54, if(YEAR(A30)=2025,XLOOKUP(B30,Lookup!$F$3:$F$10,Lookup!$H$3:$H$10,,1)*G30, XLOOKUP(B30,Lookup!$F$14:$F$21,Lookup!$H$14:$H$21,,1)*G30),0)} -> 0 | L30: =IF(and(A30<questions!$C$19,questions!$C$18="yes"),questions!$C$20,0) -> 700 | M30: =(Y29+H30)*Lookup!A$26/12 -> 92.12381 | N30: =if(B30<55, (Z29+I30)*Lookup!B$26/12, (AB29+K30)*Lookup!B$26/12) -> 58.039022 | O30: =(AA29+J30)*Lookup!C$26/12 -> 73.990385 | P30: =IF(year(A30)=year(A29), P29+M30, M30) -> 517.11061 | Q30: =IF(year(A30)=year(A29), Q29+N30, N30) -> 324.24333 | R30: =IF(year(A30)=year(A29), R29+O30, O30) -> 411.94471 | S30: =if(B30<55,min(20000,Y29)*0.01/12,min(20000,Y29)*0.02/12) -> 16.666667 | T30: =if(B30<=55,min(60000-min(20000,Y29),Z29)*0.01/12,min(30000-min(20000,Y29),AB29)*0.02/12+min(30000,AB29)*0.01/12) -> 14.109909 | U30: =if(B30<55,min(60000-min(60000-min(20000,Y29),Z29)-min(20000,Y29),AA29)*0.01/12,min(30000-min(30000-min(20000,Y29),AB29)-min(20000,Y29),AA29)*0.02/12+min(30000-min(30000-min(20000,Y29),AB29)-min(20000,Y29),AA29)*0.01/12) -> 17.964303 | V30: =IF(year($A30)=year($A29), V29+S30, S30) -> 100 | W30: =IF(year($A30)=year($A29), W29+T30, T30) -> 78.661753 | X30: =IF(year($A30)=year($A29), X29+U30, U30) -> 99.786417 | Y30: =IFS( B30<55, MAX( Y29 + IF(MONTH(A30)=12, P30+V30, 0) + H30 - L30 + MAX(0, IF(AA29 >= VLOOKUP(YEAR(A30), Lookup!$Q:$R, 2), Z29 + IF(MONTH(A30)=12, Q30+W30, 0) + I30 + AA29 + IF(MONTH(A30)=12, R30+X30, 0) - VLOOKUP(YEAR(A30), Lookup!$Q:$R, 2) + J30, Z29 + IF(MONTH(A30)=12, Q30+W30, 0) + I30 ) - VLOOKUP(YEAR(A30), Lookup!$K:$M, 3) ), 0), B30=55, IF(Z29>=AD30, MAX(Y29 + IF(MONTH(A30)=12, P30+V30, 0) + H30 - L30, 0), MAX(MAX(0, Y29-(AD30-Z29)) + IF(MONTH(A30)=12, P30+V30, 0) + H30 - L30, 0) ), B30>55, IF(AB29>=$AH$7, MAX(Y29 + IF(MONTH(A30)=12, P30+V30, 0) + H30 - L30 + K30 + Z29, 0), MAX(Y29 + IF(MONTH(A30)=12, P30+V30, 0) + H30 - L30, 0) ) ) -> 43519.429 | Z30: =IFS( B30<55, MIN( IF(AA29 >= VLOOKUP(YEAR(A30), Lookup!$Q:$R, 2), Z29 + IF(MONTH(A30)=12, Q30+W30, 0) + I30 + AA29 + IF(MONTH(A30)=12, R30+X30, 0) - VLOOKUP(YEAR(A30), Lookup!$Q:$R, 2) + J30, Z29 + IF(MONTH(A30)=12, Q30+W30, 0) + I30 ), VLOOKUP(YEAR(A30), Lookup!$K:$M, 3) ), B30=55, IF(Z29 >= AD30, Z29 - AD30, 0), B30>55, 0 ) -> 17411.707 | AA30: =IFS( B30<65, IF(AA29+J30 < VLOOKUP(YEAR(A30), Lookup!$Q:$R, 2), AA29 + IF(MONTH(A30)=12, R29+X29, 0) + J30, MIN( AA29 + IF(MONTH(A30)=12, R29+X29, 0) + J30 , VLOOKUP(YEAR(A30), Lookup!$Q:$R, 2) ) ), B30>=65, IF(AA29+J30 < VLOOKUP(questions!$C$5, Lookup!$Q:$R, 2), AA29 + IF(MONTH(A30)=12, R29+X29, 0) + J30 , MIN( AA29 + IF(MONTH(A30)=12, R29+X29, 0) + J30, VLOOKUP(questions!$C$5, Lookup!$Q:$R, 2) ) ) ) -> 22197.115 | AB30: =IFS( B30<55, 0, B30=55, MIN(Y29+Z29, AD30), B30>55, IF(AB29 < $AH$7, MIN(AB29 + IF(MONTH(A30)=12, Q30+W30, 0) + K30, $AH$7), AB29 + IF(MONTH(A30)=12, Q30+W30, 0) + K30 ) ) -> 0 | AC30: {=IFS(B30<66, XLOOKUP(year(A30),Lookup!$K$13:$K1000,Lookup!$L$13:$L1000,"missing",,1),B30>65,XLOOKUP(questions!$C$5,Lookup!$K$13:$K1000,Lookup!$L$13:$L1000,"missing",,1))} -> 118093.5 | AD30: {=IFS(B30<66, XLOOKUP(year(A30),Lookup!$K$13:$K1000,Lookup!$M$13:$M1000,"missing",,1),B30>65, XLOOKUP(questions!$C$5,Lookup!$K$13:$K1000,Lookup!$M$13:$M1000,"missing",,1))} -> 236187 | AE30: {=IFS(B30<66, XLOOKUP(year(A30),Lookup!$K$13:$K1000,Lookup!$N$13:$N1000,"missing",,1),B30>65,XLOOKUP(questions!$C$5,Lookup!$K$13:$K1000,Lookup!$N$13:$N1000,"missing",,1))} -> 472374
A31: =eomonth(EDATE(A30,1),0) -> 46965 | B31: =round(YEARFRAC(EOMONTH(questions!$C$3, 0),A31,1),2) -> 29.67 | C31: =IF(B31<questions!$C$6,if(MONTH(A31)=1,C30*(1+questions!$C$12),C30),0) -> 10609 | D31: =IF(MONTH(A31)=12,C31*questions!$C$11,0) -> 0 | E31: =MIN(C31,IF(YEAR(A31)=2025,7600,8000)) -> 8000 | F31: =MIN(102000-E31*12,D31) -> 0 | G31: {=if(YEAR(A31)=2025,XLOOKUP(B31,Lookup!$A$3:$A$7,Lookup!$D$3:$D$7,,1)*SUM(E31:F31), XLOOKUP(B31,Lookup!$A$14:$A$18,Lookup!$D$14:$D$18,,1)*SUM(E31:F31))} -> 2960 | H31: {=if(YEAR(A31)=2025,XLOOKUP(B31,Lookup!$F$3:$F$10,Lookup!$G$3:$G$10,,1)*G31, XLOOKUP(B31,Lookup!$F$14:$F$21,Lookup!$G$14:$G$21,,1)*G31)} -> 1840.232 | I31: {=if(B31<55, if(YEAR(A31)=2025,XLOOKUP(B31,Lookup!$F$3:$F$10,Lookup!$H$3:$H$10,,1)*G31, XLOOKUP(B31,Lookup!$F$14:$F$21,Lookup!$H$14:$H$21,,1)*G31),0)} -> 479.816 | J31: {=if(YEAR(A31)=2025,XLOOKUP(B31,Lookup!$F$3:$F$10,Lookup!$I$3:$I$10,,1)*G31, XLOOKUP(B31,Lookup!$F$14:$F$21,Lookup!$I$14:$I$21,,1)*G31)} -> 639.952 | K31: {=if(B31>54, if(YEAR(A31)=2025,XLOOKUP(B31,Lookup!$F$3:$F$10,Lookup!$H$3:$H$10,,1)*G31, XLOOKUP(B31,Lookup!$F$14:$F$21,Lookup!$H$14:$H$21,,1)*G31),0)} -> 0 | L31: =IF(and(A31<questions!$C$19,questions!$C$18="yes"),questions!$C$20,0) -> 700 | M31: =(Y30+H31)*Lookup!A$26/12 -> 94.499293 | N31: =if(B31<55, (Z30+I31)*Lookup!B$26/12, (AB30+K31)*Lookup!B$26/12) -> 59.638408 | O31: =(AA30+J31)*Lookup!C$26/12 -> 76.123558 | P31: =IF(year(A31)=year(A30), P30+M31, M31) -> 611.6099 | Q31: =IF(year(A31)=year(A30), Q30+N31, N31) -> 383.88174 | R31: =IF(year(A31)=year(A30), R30+O31, O31) -> 488.06827 | S31: =if(B31<55,min(20000,Y30)*0.01/12,min(20000,Y30)*0.02/12) -> 16.666667 | T31: =if(B31<=55,min(60000-min(20000,Y30),Z30)*0.01/12,min(30000-min(20000,Y30),AB30)*0.02/12+min(30000,AB30)*0.01/12) -> 14.509755 | U31: =if(B31<55,min(60000-min(60000-min(20000,Y30),Z30)-min(20000,Y30),AA30)*0.01/12,min(30000-min(30000-min(20000,Y30),AB30)-min(20000,Y30),AA30)*0.02/12+min(30000-min(30000-min(20000,Y30),AB30)-min(20000,Y30),AA30)*0.01/12) -> 18.497596 | V31: =IF(year($A31)=year($A30), V30+S31, S31) -> 116.66667 | W31: =IF(year($A31)=year($A30), W30+T31, T31) -> 93.171508 | X31: =IF(year($A31)=year($A30), X30+U31, U31) -> 118.28401 | Y31: =IFS( B31<55, MAX( Y30 + IF(MONTH(A31)=12, P31+V31, 0) + H31 - L31 + MAX(0, IF(AA30 >= VLOOKUP(YEAR(A31), Lookup!$Q:$R, 2), Z30 + IF(MONTH(A31)=12, Q31+W31, 0) + I31 + AA30 + IF(MONTH(A31)=12, R31+X31, 0) - VLOOKUP(YEAR(A31), Lookup!$Q:$R, 2) + J31, Z30 + IF(MONTH(A31)=12, Q31+W31, 0) + I31 ) - VLOOKUP(YEAR(A31), Lookup!$K:$M, 3) ), 0), B31=55, IF(Z30>=AD31, MAX(Y30 + IF(MONTH(A31)=12, P31+V31, 0) + H31 - L31, 0), MAX(MAX(0, Y30-(AD31-Z30)) + IF(MONTH(A31)=12, P31+V31, 0) + H31 - L31, 0) ), B31>55, IF(AB30>=$AH$7, MAX(Y30 + IF(MONTH(A31)=12, P31+V31, 0) + H31 - L31 + K31 + Z30, 0), MAX(Y30 + IF(MONTH(A31)=12, P31+V31, 0) + H31 - L31, 0) ) ) -> 44659.661 | Z31: =IFS( B31<55, MIN( IF(AA30 >= VLOOKUP(YEAR(A31), Lookup!$Q:$R, 2), Z30 + IF(MONTH(A31)=12, Q31+W31, 0) + I31 + AA30 + IF(MONTH(A31)=12, R31+X31, 0) - VLOOKUP(YEAR(A31), Lookup!$Q:$R, 2) + J31, Z30 + IF(MONTH(A31)=12, Q31+W31, 0) + I31 ), VLOOKUP(YEAR(A31), Lookup!$K:$M, 3) ), B31=55, IF(Z30 >= AD31, Z30 - AD31, 0), B31>55, 0 ) -> 17891.523 | AA31: =IFS( B31<65, IF(AA30+J31 < VLOOKUP(YEAR(A31), Lookup!$Q:$R, 2), AA30 + IF(MONTH(A31)=12, R30+X30, 0) + J31, MIN( AA30 + IF(MONTH(A31)=12, R30+X30, 0) + J31 , VLOOKUP(YEAR(A31), Lookup!$Q:$R, 2) ) ), B31>=65, IF(AA30+J31 < VLOOKUP(questions!$C$5, Lookup!$Q:$R, 2), AA30 + IF(MONTH(A31)=12, R30+X30, 0) + J31 , MIN( AA30 + IF(MONTH(A31)=12, R30+X30, 0) + J31, VLOOKUP(questions!$C$5, Lookup!$Q:$R, 2) ) ) ) -> 22837.067 | AB31: =IFS( B31<55, 0, B31=55, MIN(Y30+Z30, AD31), B31>55, IF(AB30 < $AH$7, MIN(AB30 + IF(MONTH(A31)=12, Q31+W31, 0) + K31, $AH$7), AB30 + IF(MONTH(A31)=12, Q31+W31, 0) + K31 ) ) -> 0 | AC31: {=IFS(B31<66, XLOOKUP(year(A31),Lookup!$K$13:$K1000,Lookup!$L$13:$L1000,"missing",,1),B31>65,XLOOKUP(questions!$C$5,Lookup!$K$13:$K1000,Lookup!$L$13:$L1000,"missing",,1))} -> 118093.5 | AD31: {=IFS(B31<66, XLOOKUP(year(A31),Lookup!$K$13:$K1000,Lookup!$M$13:$M1000,"missing",,1),B31>65, XLOOKUP(questions!$C$5,Lookup!$K$13:$K1000,Lookup!$M$13:$M1000,"missing",,1))} -> 236187 | AE31: {=IFS(B31<66, XLOOKUP(year(A31),Lookup!$K$13:$K1000,Lookup!$N$13:$N1000,"missing",,1),B31>65,XLOOKUP(questions!$C$5,Lookup!$K$13:$K1000,Lookup!$N$13:$N1000,"missing",,1))} -> 472374
A32: =eomonth(EDATE(A31,1),0) -> 46996 | B32: =round(YEARFRAC(EOMONTH(questions!$C$3, 0),A32,1),2) -> 29.75 | C32: =IF(B32<questions!$C$6,if(MONTH(A32)=1,C31*(1+questions!$C$12),C31),0) -> 10609 | D32: =IF(MONTH(A32)=12,C32*questions!$C$11,0) -> 0 | E32: =MIN(C32,IF(YEAR(A32)=2025,7600,8000)) -> 8000 | F32: =MIN(102000-E32*12,D32) -> 0 | G32: {=if(YEAR(A32)=2025,XLOOKUP(B32,Lookup!$A$3:$A$7,Lookup!$D$3:$D$7,,1)*SUM(E32:F32), XLOOKUP(B32,Lookup!$A$14:$A$18,Lookup!$D$14:$D$18,,1)*SUM(E32:F32))} -> 2960 | H32: {=if(YEAR(A32)=2025,XLOOKUP(B32,Lookup!$F$3:$F$10,Lookup!$G$3:$G$10,,1)*G32, XLOOKUP(B32,Lookup!$F$14:$F$21,Lookup!$G$14:$G$21,,1)*G32)} -> 1840.232 | I32: {=if(B32<55, if(YEAR(A32)=2025,XLOOKUP(B32,Lookup!$F$3:$F$10,Lookup!$H$3:$H$10,,1)*G32, XLOOKUP(B32,Lookup!$F$14:$F$21,Lookup!$H$14:$H$21,,1)*G32),0)} -> 479.816 | J32: {=if(YEAR(A32)=2025,XLOOKUP(B32,Lookup!$F$3:$F$10,Lookup!$I$3:$I$10,,1)*G32, XLOOKUP(B32,Lookup!$F$14:$F$21,Lookup!$I$14:$I$21,,1)*G32)} -> 639.952 | K32: {=if(B32>54, if(YEAR(A32)=2025,XLOOKUP(B32,Lookup!$F$3:$F$10,Lookup!$H$3:$H$10,,1)*G32, XLOOKUP(B32,Lookup!$F$14:$F$21,Lookup!$H$14:$H$21,,1)*G32),0)} -> 0 | L32: =IF(and(A32<questions!$C$19,questions!$C$18="yes"),questions!$C$20,0) -> 700 | M32: =(Y31+H32)*Lookup!A$26/12 -> 96.874777 | N32: =if(B32<55, (Z31+I32)*Lookup!B$26/12, (AB31+K32)*Lookup!B$26/12) -> 61.237795 | O32: =(AA31+J32)*Lookup!C$26/12 -> 78.256731 | P32: =IF(year(A32)=year(A31), P31+M32, M32) -> 708.48468 | Q32: =IF(year(A32)=year(A31), Q31+N32, N32) -> 445.11953 | R32: =IF(year(A32)=year(A31), R31+O32, O32) -> 566.325 | S32: =if(B32<55,min(20000,Y31)*0.01/12,min(20000,Y31)*0.02/12) -> 16.666667 | T32: =if(B32<=55,min(60000-min(20000,Y31),Z31)*0.01/12,min(30000-min(20000,Y31),AB31)*0.02/12+min(30000,AB31)*0.01/12) -> 14.909602 | U32: =if(B32<55,min(60000-min(60000-min(20000,Y31),Z31)-min(20000,Y31),AA31)*0.01/12,min(30000-min(30000-min(20000,Y31),AB31)-min(20000,Y31),AA31)*0.02/12+min(30000-min(30000-min(20000,Y31),AB31)-min(20000,Y31),AA31)*0.01/12) -> 18.423731 | V32: =IF(year($A32)=year($A31), V31+S32, S32) -> 133.33333 | W32: =IF(year($A32)=year($A31), W31+T32, T32) -> 108.08111 | X32: =IF(year($A32)=year($A31), X31+U32, U32) -> 136.70774 | Y32: =IFS( B32<55, MAX( Y31 + IF(MONTH(A32)=12, P32+V32, 0) + H32 - L32 + MAX(0, IF(AA31 >= VLOOKUP(YEAR(A32), Lookup!$Q:$R, 2), Z31 + IF(MONTH(A32)=12, Q32+W32, 0) + I32 + AA31 + IF(MONTH(A32)=12, R32+X32, 0) - VLOOKUP(YEAR(A32), Lookup!$Q:$R, 2) + J32, Z31 + IF(MONTH(A32)=12, Q32+W32, 0) + I32 ) - VLOOKUP(YEAR(A32), Lookup!$K:$M, 3) ), 0), B32=55, IF(Z31>=AD32, MAX(Y31 + IF(MONTH(A32)=12, P32+V32, 0) + H32 - L32, 0), MAX(MAX(0, Y31-(AD32-Z31)) + IF(MONTH(A32)=12, P32+V32, 0) + H32 - L32, 0) ), B32>55, IF(AB31>=$AH$7, MAX(Y31 + IF(MONTH(A32)=12, P32+V32, 0) + H32 - L32 + K32 + Z31, 0), MAX(Y31 + IF(MONTH(A32)=12, P32+V32, 0) + H32 - L32, 0) ) ) -> 45799.893 | Z32: =IFS( B32<55, MIN( IF(AA31 >= VLOOKUP(YEAR(A32), Lookup!$Q:$R, 2), Z31 + IF(MONTH(A32)=12, Q32+W32, 0) + I32 + AA31 + IF(MONTH(A32)=12, R32+X32, 0) - VLOOKUP(YEAR(A32), Lookup!$Q:$R, 2) + J32, Z31 + IF(MONTH(A32)=12, Q32+W32, 0) + I32 ), VLOOKUP(YEAR(A32), Lookup!$K:$M, 3) ), B32=55, IF(Z31 >= AD32, Z31 - AD32, 0), B32>55, 0 ) -> 18371.339 | AA32: =IFS( B32<65, IF(AA31+J32 < VLOOKUP(YEAR(A32), Lookup!$Q:$R, 2), AA31 + IF(MONTH(A32)=12, R31+X31, 0) + J32, MIN( AA31 + IF(MONTH(A32)=12, R31+X31, 0) + J32 , VLOOKUP(YEAR(A32), Lookup!$Q:$R, 2) ) ), B32>=65, IF(AA31+J32 < VLOOKUP(questions!$C$5, Lookup!$Q:$R, 2), AA31 + IF(MONTH(A32)=12, R31+X31, 0) + J32 , MIN( AA31 + IF(MONTH(A32)=12, R31+X31, 0) + J32, VLOOKUP(questions!$C$5, Lookup!$Q:$R, 2) ) ) ) -> 23477.019 | AB32: =IFS( B32<55, 0, B32=55, MIN(Y31+Z31, AD32), B32>55, IF(AB31 < $AH$7, MIN(AB31 + IF(MONTH(A32)=12, Q32+W32, 0) + K32, $AH$7), AB31 + IF(MONTH(A32)=12, Q32+W32, 0) + K32 ) ) -> 0 | AC32: {=IFS(B32<66, XLOOKUP(year(A32),Lookup!$K$13:$K1000,Lookup!$L$13:$L1000,"missing",,1),B32>65,XLOOKUP(questions!$C$5,Lookup!$K$13:$K1000,Lookup!$L$13:$L1000,"missing",,1))} -> 118093.5 | AD32: {=IFS(B32<66, XLOOKUP(year(A32),Lookup!$K$13:$K1000,Lookup!$M$13:$M1000,"missing",,1),B32>65, XLOOKUP(questions!$C$5,Lookup!$K$13:$K1000,Lookup!$M$13:$M1000,"missing",,1))} -> 236187 | AE32: {=IFS(B32<66, XLOOKUP(year(A32),Lookup!$K$13:$K1000,Lookup!$N$13:$N1000,"missing",,1),B32>65,XLOOKUP(questions!$C$5,Lookup!$K$13:$K1000,Lookup!$N$13:$N1000,"missing",,1))} -> 472374
A33: =eomonth(EDATE(A32,1),0) -> 47026 | B33: =round(YEARFRAC(EOMONTH(questions!$C$3, 0),A33,1),2) -> 29.83 | C33: =IF(B33<questions!$C$6,if(MONTH(A33)=1,C32*(1+questions!$C$12),C32),0) -> 10609 | D33: =IF(MONTH(A33)=12,C33*questions!$C$11,0) -> 0 | E33: =MIN(C33,IF(YEAR(A33)=2025,7600,8000)) -> 8000 | F33: =MIN(102000-E33*12,D33) -> 0 | G33: {=if(YEAR(A33)=2025,XLOOKUP(B33,Lookup!$A$3:$A$7,Lookup!$D$3:$D$7,,1)*SUM(E33:F33), XLOOKUP(B33,Lookup!$A$14:$A$18,Lookup!$D$14:$D$18,,1)*SUM(E33:F33))} -> 2960 | H33: {=if(YEAR(A33)=2025,XLOOKUP(B33,Lookup!$F$3:$F$10,Lookup!$G$3:$G$10,,1)*G33, XLOOKUP(B33,Lookup!$F$14:$F$21,Lookup!$G$14:$G$21,,1)*G33)} -> 1840.232 | I33: {=if(B33<55, if(YEAR(A33)=2025,XLOOKUP(B33,Lookup!$F$3:$F$10,Lookup!$H$3:$H$10,,1)*G33, XLOOKUP(B33,Lookup!$F$14:$F$21,Lookup!$H$14:$H$21,,1)*G33),0)} -> 479.816 | J33: {=if(YEAR(A33)=2025,XLOOKUP(B33,Lookup!$F$3:$F$10,Lookup!$I$3:$I$10,,1)*G33, XLOOKUP(B33,Lookup!$F$14:$F$21,Lookup!$I$14:$I$21,,1)*G33)} -> 639.952 | K33: {=if(B33>54, if(YEAR(A33)=2025,XLOOKUP(B33,Lookup!$F$3:$F$10,Lookup!$H$3:$H$10,,1)*G33, XLOOKUP(B33,Lookup!$F$14:$F$21,Lookup!$H$14:$H$21,,1)*G33),0)} -> 0 | L33: =IF(and(A33<questions!$C$19,questions!$C$18="yes"),questions!$C$20,0) -> 700 | M33: =(Y32+H33)*Lookup!A$26/12 -> 99.25026 | N33: =if(B33<55, (Z32+I33)*Lookup!B$26/12, (AB32+K33)*Lookup!B$26/12) -> 62.837182 | O33: =(AA32+J33)*Lookup!C$26/12 -> 80.389905 | P33: =IF(year(A33)=year(A32), P32+M33, M33) -> 807.73494 | Q33: =IF(year(A33)=year(A32), Q32+N33, N33) -> 507.95672 | R33: =IF(year(A33)=year(A32), R32+O33, O33) -> 646.7149 | S33: =if(B33<55,min(20000,Y32)*0.01/12,min(20000,Y32)*0.02/12) -> 16.666667 | T33: =if(B33<=55,min(60000-min(20000,Y32),Z32)*0.01/12,min(30000-min(20000,Y32),AB32)*0.02/12+min(30000,AB32)*0.01/12) -> 15.309449 | U33: =if(B33<55,min(60000-min(60000-min(20000,Y32),Z32)-min(20000,Y32),AA32)*0.01/12,min(30000-min(30000-min(20000,Y32),AB32)-min(20000,Y32),AA32)*0.02/12+min(30000-min(30000-min(20000,Y32),AB32)-min(20000,Y32),AA32)*0.01/12) -> 18.023885 | V33: =IF(year($A33)=year($A32), V32+S33, S33) -> 150 | W33: =IF(year($A33)=year($A32), W32+T33, T33) -> 123.39056 | X33: =IF(year($A33)=year($A32), X32+U33, U33) -> 154.73163 | Y33: =IFS( B33<55, MAX( Y32 + IF(MONTH(A33)=12, P33+V33, 0) + H33 - L33 + MAX(0, IF(AA32 >= VLOOKUP(YEAR(A33), Lookup!$Q:$R, 2), Z32 + IF(MONTH(A33)=12, Q33+W33, 0) + I33 + AA32 + IF(MONTH(A33)=12, R33+X33, 0) - VLOOKUP(YEAR(A33), Lookup!$Q:$R, 2) + J33, Z32 + IF(MONTH(A33)=12, Q33+W33, 0) + I33 ) - VLOOKUP(YEAR(A33), Lookup!$K:$M, 3) ), 0), B33=55, IF(Z32>=AD33, MAX(Y32 + IF(MONTH(A33)=12, P33+V33, 0) + H33 - L33, 0), MAX(MAX(0, Y32-(AD33-Z32)) + IF(MONTH(A33)=12, P33+V33, 0) + H33 - L33, 0) ), B33>55, IF(AB32>=$AH$7, MAX(Y32 + IF(MONTH(A33)=12, P33+V33, 0) + H33 - L33 + K33 + Z32, 0), MAX(Y32 + IF(MONTH(A33)=12, P33+V33, 0) + H33 - L33, 0) ) ) -> 46940.125 | Z33: =IFS( B33<55, MIN( IF(AA32 >= VLOOKUP(YEAR(A33), Lookup!$Q:$R, 2), Z32 + IF(MONTH(A33)=12, Q33+W33, 0) + I33 + AA32 + IF(MONTH(A33)=12, R33+X33, 0) - VLOOKUP(YEAR(A33), Lookup!$Q:$R, 2) + J33, Z32 + IF(MONTH(A33)=12, Q33+W33, 0) + I33 ), VLOOKUP(YEAR(A33), Lookup!$K:$M, 3) ), B33=55, IF(Z32 >= AD33, Z32 - AD33, 0), B33>55, 0 ) -> 18851.155 | AA33: =IFS( B33<65, IF(AA32+J33 < VLOOKUP(YEAR(A33), Lookup!$Q:$R, 2), AA32 + IF(MONTH(A33)=12, R32+X32, 0) + J33, MIN( AA32 + IF(MONTH(A33)=12, R32+X32, 0) + J33 , VLOOKUP(YEAR(A33), Lookup!$Q:$R, 2) ) ), B33>=65, IF(AA32+J33 < VLOOKUP(questions!$C$5, Lookup!$Q:$R, 2), AA32 + IF(MONTH(A33)=12, R32+X32, 0) + J33 , MIN( AA32 + IF(MONTH(A33)=12, R32+X32, 0) + J33, VLOOKUP(questions!$C$5, Lookup!$Q:$R, 2) ) ) ) -> 24116.971 | AB33: =IFS( B33<55, 0, B33=55, MIN(Y32+Z32, AD33), B33>55, IF(AB32 < $AH$7, MIN(AB32 + IF(MONTH(A33)=12, Q33+W33, 0) + K33, $AH$7), AB32 + IF(MONTH(A33)=12, Q33+W33, 0) + K33 ) ) -> 0 | AC33: {=IFS(B33<66, XLOOKUP(year(A33),Lookup!$K$13:$K1000,Lookup!$L$13:$L1000,"missing",,1),B33>65,XLOOKUP(questions!$C$5,Lookup!$K$13:$K1000,Lookup!$L$13:$L1000,"missing",,1))} -> 118093.5 | AD33: {=IFS(B33<66, XLOOKUP(year(A33),Lookup!$K$13:$K1000,Lookup!$M$13:$M1000,"missing",,1),B33>65, XLOOKUP(questions!$C$5,Lookup!$K$13:$K1000,Lookup!$M$13:$M1000,"missing",,1))} -> 236187 | AE33: {=IFS(B33<66, XLOOKUP(year(A33),Lookup!$K$13:$K1000,Lookup!$N$13:$N1000,"missing",,1),B33>65,XLOOKUP(questions!$C$5,Lookup!$K$13:$K1000,Lookup!$N$13:$N1000,"missing",,1))} -> 472374
A34: =eomonth(EDATE(A33,1),0) -> 47057 | B34: =round(YEARFRAC(EOMONTH(questions!$C$3, 0),A34,1),2) -> 29.92 | C34: =IF(B34<questions!$C$6,if(MONTH(A34)=1,C33*(1+questions!$C$12),C33),0) -> 10609 | D34: =IF(MONTH(A34)=12,C34*questions!$C$11,0) -> 0 | E34: =MIN(C34,IF(YEAR(A34)=2025,7600,8000)) -> 8000 | F34: =MIN(102000-E34*12,D34) -> 0 | G34: {=if(YEAR(A34)=2025,XLOOKUP(B34,Lookup!$A$3:$A$7,Lookup!$D$3:$D$7,,1)*SUM(E34:F34), XLOOKUP(B34,Lookup!$A$14:$A$18,Lookup!$D$14:$D$18,,1)*SUM(E34:F34))} -> 2960 | H34: {=if(YEAR(A34)=2025,XLOOKUP(B34,Lookup!$F$3:$F$10,Lookup!$G$3:$G$10,,1)*G34, XLOOKUP(B34,Lookup!$F$14:$F$21,Lookup!$G$14:$G$21,,1)*G34)} -> 1840.232 | I34: {=if(B34<55, if(YEAR(A34)=2025,XLOOKUP(B34,Lookup!$F$3:$F$10,Lookup!$H$3:$H$10,,1)*G34, XLOOKUP(B34,Lookup!$F$14:$F$21,Lookup!$H$14:$H$21,,1)*G34),0)} -> 479.816 | J34: {=if(YEAR(A34)=2025,XLOOKUP(B34,Lookup!$F$3:$F$10,Lookup!$I$3:$I$10,,1)*G34, XLOOKUP(B34,Lookup!$F$14:$F$21,Lookup!$I$14:$I$21,,1)*G34)} -> 639.952 | K34: {=if(B34>54, if(YEAR(A34)=2025,XLOOKUP(B34,Lookup!$F$3:$F$10,Lookup!$H$3:$H$10,,1)*G34, XLOOKUP(B34,Lookup!$F$14:$F$21,Lookup!$H$14:$H$21,,1)*G34),0)} -> 0 | L34: =IF(and(A34<questions!$C$19,questions!$C$18="yes"),questions!$C$20,0) -> 700 | M34: =(Y33+H34)*Lookup!A$26/12 -> 101.62574 | N34: =if(B34<55, (Z33+I34)*Lookup!B$26/12, (AB33+K34)*Lookup!B$26/12) -> 64.436568 | O34: =(AA33+J34)*Lookup!C$26/12 -> 82.523078 | P34: =IF(year(A34)=year(A33), P33+M34, M34) -> 909.36068 | Q34: =IF(year(A34)=year(A33), Q33+N34, N34) -> 572.39328 | R34: =IF(year(A34)=year(A33), R33+O34, O34) -> 729.23798 | S34: =if(B34<55,min(20000,Y33)*0.01/12,min(20000,Y33)*0.02/12) -> 16.666667 | T34: =if(B34<=55,min(60000-min(20000,Y33),Z33)*0.01/12,min(30000-min(20000,Y33),AB33)*0.02/12+min(30000,AB33)*0.01/12) -> 15.709295 | U34: =if(B34<55,min(60000-min(60000-min(20000,Y33),Z33)-min(20000,Y33),AA33)*0.01/12,min(30000-min(30000-min(20000,Y33),AB33)-min(20000,Y33),AA33)*0.02/12+min(30000-min(30000-min(20000,Y33),AB33)-min(20000,Y33),AA33)*0.01/12) -> 17.624038 | V34: =IF(year($A34)=year($A33), V33+S34, S34) -> 166.66667 | W34: =IF(year($A34)=year($A33), W33+T34, T34) -> 139.09985 | X34: =IF(year($A34)=year($A33), X33+U34, U34) -> 172.35567 | Y34: =IFS( B34<55, MAX( Y33 + IF(MONTH(A34)=12, P34+V34, 0) + H34 - L34 + MAX(0, IF(AA33 >= VLOOKUP(YEAR(A34), Lookup!$Q:$R, 2), Z33 + IF(MONTH(A34)=12, Q34+W34, 0) + I34 + AA33 + IF(MONTH(A34)=12, R34+X34, 0) - VLOOKUP(YEAR(A34), Lookup!$Q:$R, 2) + J34, Z33 + IF(MONTH(A34)=12, Q34+W34, 0) + I34 ) - VLOOKUP(YEAR(A34), Lookup!$K:$M, 3) ), 0), B34=55, IF(Z33>=AD34, MAX(Y33 + IF(MONTH(A34)=12, P34+V34, 0) + H34 - L34, 0), MAX(MAX(0, Y33-(AD34-Z33)) + IF(MONTH(A34)=12, P34+V34, 0) + H34 - L34, 0) ), B34>55, IF(AB33>=$AH$7, MAX(Y33 + IF(MONTH(A34)=12, P34+V34, 0) + H34 - L34 + K34 + Z33, 0), MAX(Y33 + IF(MONTH(A34)=12, P34+V34, 0) + H34 - L34, 0) ) ) -> 48080.357 | Z34: =IFS( B34<55, MIN( IF(AA33 >= VLOOKUP(YEAR(A34), Lookup!$Q:$R, 2), Z33 + IF(MONTH(A34)=12, Q34+W34, 0) + I34 + AA33 + IF(MONTH(A34)=12, R34+X34, 0) - VLOOKUP(YEAR(A34), Lookup!$Q:$R, 2) + J34, Z33 + IF(MONTH(A34)=12, Q34+W34, 0) + I34 ), VLOOKUP(YEAR(A34), Lookup!$K:$M, 3) ), B34=55, IF(Z33 >= AD34, Z33 - AD34, 0), B34>55, 0 ) -> 19330.971 | AA34: =IFS( B34<65, IF(AA33+J34 < VLOOKUP(YEAR(A34), Lookup!$Q:$R, 2), AA33 + IF(MONTH(A34)=12, R33+X33, 0) + J34, MIN( AA33 + IF(MONTH(A34)=12, R33+X33, 0) + J34 , VLOOKUP(YEAR(A34), Lookup!$Q:$R, 2) ) ), B34>=65, IF(AA33+J34 < VLOOKUP(questions!$C$5, Lookup!$Q:$R, 2), AA33 + IF(MONTH(A34)=12, R33+X33, 0) + J34 , MIN( AA33 + IF(MONTH(A34)=12, R33+X33, 0) + J34, VLOOKUP(questions!$C$5, Lookup!$Q:$R, 2) ) ) ) -> 24756.923 | AB34: =IFS( B34<55, 0, B34=55, MIN(Y33+Z33, AD34), B34>55, IF(AB33 < $AH$7, MIN(AB33 + IF(MONTH(A34)=12, Q34+W34, 0) + K34, $AH$7), AB33 + IF(MONTH(A34)=12, Q34+W34, 0) + K34 ) ) -> 0 | AC34: {=IFS(B34<66, XLOOKUP(year(A34),Lookup!$K$13:$K1000,Lookup!$L$13:$L1000,"missing",,1),B34>65,XLOOKUP(questions!$C$5,Lookup!$K$13:$K1000,Lookup!$L$13:$L1000,"missing",,1))} -> 118093.5 | AD34: {=IFS(B34<66, XLOOKUP(year(A34),Lookup!$K$13:$K1000,Lookup!$M$13:$M1000,"missing",,1),B34>65, XLOOKUP(questions!$C$5,Lookup!$K$13:$K1000,Lookup!$M$13:$M1000,"missing",,1))} -> 236187 | AE34: {=IFS(B34<66, XLOOKUP(year(A34),Lookup!$K$13:$K1000,Lookup!$N$13:$N1000,"missing",,1),B34>65,XLOOKUP(questions!$C$5,Lookup!$K$13:$K1000,Lookup!$N$13:$N1000,"missing",,1))} -> 472374
A35: =eomonth(EDATE(A34,1),0) -> 47087 | B35: =round(YEARFRAC(EOMONTH(questions!$C$3, 0),A35,1),2) -> 30 | C35: =IF(B35<questions!$C$6,if(MONTH(A35)=1,C34*(1+questions!$C$12),C34),0) -> 10609 | D35: =IF(MONTH(A35)=12,C35*questions!$C$11,0) -> 0 | E35: =MIN(C35,IF(YEAR(A35)=2025,7600,8000)) -> 8000 | F35: =MIN(102000-E35*12,D35) -> 0 | G35: {=if(YEAR(A35)=2025,XLOOKUP(B35,Lookup!$A$3:$A$7,Lookup!$D$3:$D$7,,1)*SUM(E35:F35), XLOOKUP(B35,Lookup!$A$14:$A$18,Lookup!$D$14:$D$18,,1)*SUM(E35:F35))} -> 2960 | H35: {=if(YEAR(A35)=2025,XLOOKUP(B35,Lookup!$F$3:$F$10,Lookup!$G$3:$G$10,,1)*G35, XLOOKUP(B35,Lookup!$F$14:$F$21,Lookup!$G$14:$G$21,,1)*G35)} -> 1840.232 | I35: {=if(B35<55, if(YEAR(A35)=2025,XLOOKUP(B35,Lookup!$F$3:$F$10,Lookup!$H$3:$H$10,,1)*G35, XLOOKUP(B35,Lookup!$F$14:$F$21,Lookup!$H$14:$H$21,,1)*G35),0)} -> 479.816 | J35: {=if(YEAR(A35)=2025,XLOOKUP(B35,Lookup!$F$3:$F$10,Lookup!$I$3:$I$10,,1)*G35, XLOOKUP(B35,Lookup!$F$14:$F$21,Lookup!$I$14:$I$21,,1)*G35)} -> 639.952 | K35: {=if(B35>54, if(YEAR(A35)=2025,XLOOKUP(B35,Lookup!$F$3:$F$10,Lookup!$H$3:$H$10,,1)*G35, XLOOKUP(B35,Lookup!$F$14:$F$21,Lookup!$H$14:$H$21,,1)*G35),0)} -> 0 | L35: =IF(and(A35<questions!$C$19,questions!$C$18="yes"),questions!$C$20,0) -> 700 | M35: =(Y34+H35)*Lookup!A$26/12 -> 104.00123 | N35: =if(B35<55, (Z34+I35)*Lookup!B$26/12, (AB34+K35)*Lookup!B$26/12) -> 66.035955 | O35: =(AA34+J35)*Lookup!C$26/12 -> 84.656251 | P35: =IF(year(A35)=year(A34), P34+M35, M35) -> 1013.3619 | Q35: =IF(year(A35)=year(A34), Q34+N35, N35) -> 638.42924 | R35: =IF(year(A35)=year(A34), R34+O35, O35) -> 813.89423 | S35: =if(B35<55,min(20000,Y34)*0.01/12,min(20000,Y34)*0.02/12) -> 16.666667 | T35: =if(B35<=55,min(60000-min(20000,Y34),Z34)*0.01/12,min(30000-min(20000,Y34),AB34)*0.02/12+min(30000,AB34)*0.01/12) -> 16.109142 | U35: =if(B35<55,min(60000-min(60000-min(20000,Y34),Z34)-min(20000,Y34),AA34)*0.01/12,min(30000-min(30000-min(20000,Y34),AB34)-min(20000,Y34),AA34)*0.02/12+min(30000-min(30000-min(20000,Y34),AB34)-min(20000,Y34),AA34)*0.01/12) -> 17.224191 | V35: =IF(year($A35)=year($A34), V34+S35, S35) -> 183.33333 | W35: =IF(year($A35)=year($A34), W34+T35, T35) -> 155.209 | X35: =IF(year($A35)=year($A34), X34+U35, U35) -> 189.57986 | Y35: =IFS( B35<55, MAX( Y34 + IF(MONTH(A35)=12, P35+V35, 0) + H35 - L35 + MAX(0, IF(AA34 >= VLOOKUP(YEAR(A35), Lookup!$Q:$R, 2), Z34 + IF(MONTH(A35)=12, Q35+W35, 0) + I35 + AA34 + IF(MONTH(A35)=12, R35+X35, 0) - VLOOKUP(YEAR(A35), Lookup!$Q:$R, 2) + J35, Z34 + IF(MONTH(A35)=12, Q35+W35, 0) + I35 ) - VLOOKUP(YEAR(A35), Lookup!$K:$M, 3) ), 0), B35=55, IF(Z34>=AD35, MAX(Y34 + IF(MONTH(A35)=12, P35+V35, 0) + H35 - L35, 0), MAX(MAX(0, Y34-(AD35-Z34)) + IF(MONTH(A35)=12, P35+V35, 0) + H35 - L35, 0) ), B35>55, IF(AB34>=$AH$7, MAX(Y34 + IF(MONTH(A35)=12, P35+V35, 0) + H35 - L35 + K35 + Z34, 0), MAX(Y34 + IF(MONTH(A35)=12, P35+V35, 0) + H35 - L35, 0) ) ) -> 49220.589 | Z35: =IFS( B35<55, MIN( IF(AA34 >= VLOOKUP(YEAR(A35), Lookup!$Q:$R, 2), Z34 + IF(MONTH(A35)=12, Q35+W35, 0) + I35 + AA34 + IF(MONTH(A35)=12, R35+X35, 0) - VLOOKUP(YEAR(A35), Lookup!$Q:$R, 2) + J35, Z34 + IF(MONTH(A35)=12, Q35+W35, 0) + I35 ), VLOOKUP(YEAR(A35), Lookup!$K:$M, 3) ), B35=55, IF(Z34 >= AD35, Z34 - AD35, 0), B35>55, 0 ) -> 19810.787 | AA35: =IFS( B35<65, IF(AA34+J35 < VLOOKUP(YEAR(A35), Lookup!$Q:$R, 2), AA34 + IF(MONTH(A35)=12, R34+X34, 0) + J35, MIN( AA34 + IF(MONTH(A35)=12, R34+X34, 0) + J35 , VLOOKUP(YEAR(A35), Lookup!$Q:$R, 2) ) ), B35>=65, IF(AA34+J35 < VLOOKUP(questions!$C$5, Lookup!$Q:$R, 2), AA34 + IF(MONTH(A35)=12, R34+X34, 0) + J35 , MIN( AA34 + IF(MONTH(A35)=12, R34+X34, 0) + J35, VLOOKUP(questions!$C$5, Lookup!$Q:$R, 2) ) ) ) -> 25396.875 | AB35: =IFS( B35<55, 0, B35=55, MIN(Y34+Z34, AD35), B35>55, IF(AB34 < $AH$7, MIN(AB34 + IF(MONTH(A35)=12, Q35+W35, 0) + K35, $AH$7), AB34 + IF(MONTH(A35)=12, Q35+W35, 0) + K35 ) ) -> 0 | AC35: {=IFS(B35<66, XLOOKUP(year(A35),Lookup!$K$13:$K1000,Lookup!$L$13:$L1000,"missing",,1),B35>65,XLOOKUP(questions!$C$5,Lookup!$K$13:$K1000,Lookup!$L$13:$L1000,"missing",,1))} -> 118093.5 | AD35: {=IFS(B35<66, XLOOKUP(year(A35),Lookup!$K$13:$K1000,Lookup!$M$13:$M1000,"missing",,1),B35>65, XLOOKUP(questions!$C$5,Lookup!$K$13:$K1000,Lookup!$M$13:$M1000,"missing",,1))} -> 236187 | AE35: {=IFS(B35<66, XLOOKUP(year(A35),Lookup!$K$13:$K1000,Lookup!$N$13:$N1000,"missing",,1),B35>65,XLOOKUP(questions!$C$5,Lookup!$K$13:$K1000,Lookup!$N$13:$N1000,"missing",,1))} -> 472374
A36: =eomonth(EDATE(A35,1),0) -> 47118 | B36: =round(YEARFRAC(EOMONTH(questions!$C$3, 0),A36,1),2) -> 30.08 | C36: =IF(B36<questions!$C$6,if(MONTH(A36)=1,C35*(1+questions!$C$12),C35),0) -> 10609 | D36: =IF(MONTH(A36)=12,C36*questions!$C$11,0) -> 10609 | E36: =MIN(C36,IF(YEAR(A36)=2025,7600,8000)) -> 8000 | F36: =MIN(102000-E36*12,D36) -> 6000 | G36: {=if(YEAR(A36)=2025,XLOOKUP(B36,Lookup!$A$3:$A$7,Lookup!$D$3:$D$7,,1)*SUM(E36:F36), XLOOKUP(B36,Lookup!$A$14:$A$18,Lookup!$D$14:$D$18,,1)*SUM(E36:F36))} -> 5180 | H36: {=if(YEAR(A36)=2025,XLOOKUP(B36,Lookup!$F$3:$F$10,Lookup!$G$3:$G$10,,1)*G36, XLOOKUP(B36,Lookup!$F$14:$F$21,Lookup!$G$14:$G$21,,1)*G36)} -> 3220.406 | I36: {=if(B36<55, if(YEAR(A36)=2025,XLOOKUP(B36,Lookup!$F$3:$F$10,Lookup!$H$3:$H$10,,1)*G36, XLOOKUP(B36,Lookup!$F$14:$F$21,Lookup!$H$14:$H$21,,1)*G36),0)} -> 839.678 | J36: {=if(YEAR(A36)=2025,XLOOKUP(B36,Lookup!$F$3:$F$10,Lookup!$I$3:$I$10,,1)*G36, XLOOKUP(B36,Lookup!$F$14:$F$21,Lookup!$I$14:$I$21,,1)*G36)} -> 1119.916 | K36: {=if(B36>54, if(YEAR(A36)=2025,XLOOKUP(B36,Lookup!$F$3:$F$10,Lookup!$H$3:$H$10,,1)*G36, XLOOKUP(B36,Lookup!$F$14:$F$21,Lookup!$H$14:$H$21,,1)*G36),0)} -> 0 | L36: =IF(and(A36<questions!$C$19,questions!$C$18="yes"),questions!$C$20,0) -> 700 | M36: =(Y35+H36)*Lookup!A$26/12 -> 109.25207 | N36: =if(B36<55, (Z35+I36)*Lookup!B$26/12, (AB35+K36)*Lookup!B$26/12) -> 68.834882 | O36: =(AA35+J36)*Lookup!C$26/12 -> 88.389305 | P36: =IF(year(A36)=year(A35), P35+M36, M36) -> 1122.614 | Q36: =IF(year(A36)=year(A35), Q35+N36, N36) -> 707.26412 | R36: =IF(year(A36)=year(A35), R35+O36, O36) -> 902.28354 | S36: =if(B36<55,min(20000,Y35)*0.01/12,min(20000,Y35)*0.02/12) -> 16.666667 | T36: =if(B36<=55,min(60000-min(20000,Y35),Z35)*0.01/12,min(30000-min(20000,Y35),AB35)*0.02/12+min(30000,AB35)*0.01/12) -> 16.508989 | U36: =if(B36<55,min(60000-min(60000-min(20000,Y35),Z35)-min(20000,Y35),AA35)*0.01/12,min(30000-min(30000-min(20000,Y35),AB35)-min(20000,Y35),AA35)*0.02/12+min(30000-min(30000-min(20000,Y35),AB35)-min(20000,Y35),AA35)*0.01/12) -> 16.824345 | V36: =IF(year($A36)=year($A35), V35+S36, S36) -> 200 | W36: =IF(year($A36)=year($A35), W35+T36, T36) -> 171.71799 | X36: =IF(year($A36)=year($A35), X35+U36, U36) -> 206.4042 | Y36: =IFS( B36<55, MAX( Y35 + IF(MONTH(A36)=12, P36+V36, 0) + H36 - L36 + MAX(0, IF(AA35 >= VLOOKUP(YEAR(A36), Lookup!$Q:$R, 2), Z35 + IF(MONTH(A36)=12, Q36+W36, 0) + I36 + AA35 + IF(MONTH(A36)=12, R36+X36, 0) - VLOOKUP(YEAR(A36), Lookup!$Q:$R, 2) + J36, Z35 + IF(MONTH(A36)=12, Q36+W36, 0) + I36 ) - VLOOKUP(YEAR(A36), Lookup!$K:$M, 3) ), 0), B36=55, IF(Z35>=AD36, MAX(Y35 + IF(MONTH(A36)=12, P36+V36, 0) + H36 - L36, 0), MAX(MAX(0, Y35-(AD36-Z35)) + IF(MONTH(A36)=12, P36+V36, 0) + H36 - L36, 0) ), B36>55, IF(AB35>=$AH$7, MAX(Y35 + IF(MONTH(A36)=12, P36+V36, 0) + H36 - L36 + K36 + Z35, 0), MAX(Y35 + IF(MONTH(A36)=12, P36+V36, 0) + H36 - L36, 0) ) ) -> 53063.609 | Z36: =IFS( B36<55, MIN( IF(AA35 >= VLOOKUP(YEAR(A36), Lookup!$Q:$R, 2), Z35 + IF(MONTH(A36)=12, Q36+W36, 0) + I36 + AA35 + IF(MONTH(A36)=12, R36+X36, 0) - VLOOKUP(YEAR(A36), Lookup!$Q:$R, 2) + J36, Z35 + IF(MONTH(A36)=12, Q36+W36, 0) + I36 ), VLOOKUP(YEAR(A36), Lookup!$K:$M, 3) ), B36=55, IF(Z35 >= AD36, Z35 - AD36, 0), B36>55, 0 ) -> 21529.447 | AA36: =IFS( B36<65, IF(AA35+J36 < VLOOKUP(YEAR(A36), Lookup!$Q:$R, 2), AA35 + IF(MONTH(A36)=12, R35+X35, 0) + J36, MIN( AA35 + IF(MONTH(A36)=12, R35+X35, 0) + J36 , VLOOKUP(YEAR(A36), Lookup!$Q:$R, 2) ) ), B36>=65, IF(AA35+J36 < VLOOKUP(questions!$C$5, Lookup!$Q:$R, 2), AA35 + IF(MONTH(A36)=12, R35+X35, 0) + J36 , MIN( AA35 + IF(MONTH(A36)=12, R35+X35, 0) + J36, VLOOKUP(questions!$C$5, Lookup!$Q:$R, 2) ) ) ) -> 27520.266 | AB36: =IFS( B36<55, 0, B36=55, MIN(Y35+Z35, AD36), B36>55, IF(AB35 < $AH$7, MIN(AB35 + IF(MONTH(A36)=12, Q36+W36, 0) + K36, $AH$7), AB35 + IF(MONTH(A36)=12, Q36+W36, 0) + K36 ) ) -> 0 | AC36: {=IFS(B36<66, XLOOKUP(year(A36),Lookup!$K$13:$K1000,Lookup!$L$13:$L1000,"missing",,1),B36>65,XLOOKUP(questions!$C$5,Lookup!$K$13:$K1000,Lookup!$L$13:$L1000,"missing",,1))} -> 118093.5 | AD36: {=IFS(B36<66, XLOOKUP(year(A36),Lookup!$K$13:$K1000,Lookup!$M$13:$M1000,"missing",,1),B36>65, XLOOKUP(questions!$C$5,Lookup!$K$13:$K1000,Lookup!$M$13:$M1000,"missing",,1))} -> 236187 | AE36: {=IFS(B36<66, XLOOKUP(year(A36),Lookup!$K$13:$K1000,Lookup!$N$13:$N1000,"missing",,1),B36>65,XLOOKUP(questions!$C$5,Lookup!$K$13:$K1000,Lookup!$N$13:$N1000,"missing",,1))} -> 472374
A37: =eomonth(EDATE(A36,1),0) -> 47149 | B37: =round(YEARFRAC(EOMONTH(questions!$C$3, 0),A37,1),2) -> 30.17 | C37: =IF(B37<questions!$C$6,if(MONTH(A37)=1,C36*(1+questions!$C$12),C36),0) -> 10927.27 | D37: =IF(MONTH(A37)=12,C37*questions!$C$11,0) -> 0 | E37: =MIN(C37,IF(YEAR(A37)=2025,7600,8000)) -> 8000 | F37: =MIN(102000-E37*12,D37) -> 0 | G37: {=if(YEAR(A37)=2025,XLOOKUP(B37,Lookup!$A$3:$A$7,Lookup!$D$3:$D$7,,1)*SUM(E37:F37), XLOOKUP(B37,Lookup!$A$14:$A$18,Lookup!$D$14:$D$18,,1)*SUM(E37:F37))} -> 2960 | H37: {=if(YEAR(A37)=2025,XLOOKUP(B37,Lookup!$F$3:$F$10,Lookup!$G$3:$G$10,,1)*G37, XLOOKUP(B37,Lookup!$F$14:$F$21,Lookup!$G$14:$G$21,,1)*G37)} -> 1840.232 | I37: {=if(B37<55, if(YEAR(A37)=2025,XLOOKUP(B37,Lookup!$F$3:$F$10,Lookup!$H$3:$H$10,,1)*G37, XLOOKUP(B37,Lookup!$F$14:$F$21,Lookup!$H$14:$H$21,,1)*G37),0)} -> 479.816 | J37: {=if(YEAR(A37)=2025,XLOOKUP(B37,Lookup!$F$3:$F$10,Lookup!$I$3:$I$10,,1)*G37, XLOOKUP(B37,Lookup!$F$14:$F$21,Lookup!$I$14:$I$21,,1)*G37)} -> 639.952 | K37: {=if(B37>54, if(YEAR(A37)=2025,XLOOKUP(B37,Lookup!$F$3:$F$10,Lookup!$H$3:$H$10,,1)*G37, XLOOKUP(B37,Lookup!$F$14:$F$21,Lookup!$H$14:$H$21,,1)*G37),0)} -> 0 | L37: =IF(and(A37<questions!$C$19,questions!$C$18="yes"),questions!$C$20,0) -> 700 | M37: =(Y36+H37)*Lookup!A$26/12 -> 114.383 | N37: =if(B37<55, (Z36+I37)*Lookup!B$26/12, (AB36+K37)*Lookup!B$26/12) -> 73.364209 | O37: =(AA36+J37)*Lookup!C$26/12 -> 93.867392 | P37: =IF(year(A37)=year(A36), P36+M37, M37) -> 114.383 | Q37: =IF(year(A37)=year(A36), Q36+N37, N37) -> 73.364209 | R37: =IF(year(A37)=year(A36), R36+O37, O37) -> 93.867392 | S37: =if(B37<55,min(20000,Y36)*0.01/12,min(20000,Y36)*0.02/12) -> 16.666667 | T37: =if(B37<=55,min(60000-min(20000,Y36),Z36)*0.01/12,min(30000-min(20000,Y36),AB36)*0.02/12+min(30000,AB36)*0.01/12) -> 17.941206 | U37: =if(B37<55,min(60000-min(60000-min(20000,Y36),Z36)-min(20000,Y36),AA36)*0.01/12,min(30000-min(30000-min(20000,Y36),AB36)-min(20000,Y36),AA36)*0.02/12+min(30000-min(30000-min(20000,Y36),AB36)-min(20000,Y36),AA36)*0.01/12) -> 15.392128 | V37: =IF(year($A37)=year($A36), V36+S37, S37) -> 16.666667 | W37: =IF(year($A37)=year($A36), W36+T37, T37) -> 17.941206 | X37: =IF(year($A37)=year($A36), X36+U37, U37) -> 15.392128 | Y37: =IFS( B37<55, MAX( Y36 + IF(MONTH(A37)=12, P37+V37, 0) + H37 - L37 + MAX(0, IF(AA36 >= VLOOKUP(YEAR(A37), Lookup!$Q:$R, 2), Z36 + IF(MONTH(A37)=12, Q37+W37, 0) + I37 + AA36 + IF(MONTH(A37)=12, R37+X37, 0) - VLOOKUP(YEAR(A37), Lookup!$Q:$R, 2) + J37, Z36 + IF(MONTH(A37)=12, Q37+W37, 0) + I37 ) - VLOOKUP(YEAR(A37), Lookup!$K:$M, 3) ), 0), B37=55, IF(Z36>=AD37, MAX(Y36 + IF(MONTH(A37)=12, P37+V37, 0) + H37 - L37, 0), MAX(MAX(0, Y36-(AD37-Z36)) + IF(MONTH(A37)=12, P37+V37, 0) + H37 - L37, 0) ), B37>55, IF(AB36>=$AH$7, MAX(Y36 + IF(MONTH(A37)=12, P37+V37, 0) + H37 - L37 + K37 + Z36, 0), MAX(Y36 + IF(MONTH(A37)=12, P37+V37, 0) + H37 - L37, 0) ) ) -> 54203.841 | Z37: =IFS( B37<55, MIN( IF(AA36 >= VLOOKUP(YEAR(A37), Lookup!$Q:$R, 2), Z36 + IF(MONTH(A37)=12, Q37+W37, 0) + I37 + AA36 + IF(MONTH(A37)=12, R37+X37, 0) - VLOOKUP(YEAR(A37), Lookup!$Q:$R, 2) + J37, Z36 + IF(MONTH(A37)=12, Q37+W37, 0) + I37 ), VLOOKUP(YEAR(A37), Lookup!$K:$M, 3) ), B37=55, IF(Z36 >= AD37, Z36 - AD37, 0), B37>55, 0 ) -> 22009.263 | AA37: =IFS( B37<65, IF(AA36+J37 < VLOOKUP(YEAR(A37), Lookup!$Q:$R, 2), AA36 + IF(MONTH(A37)=12, R36+X36, 0) + J37, MIN( AA36 + IF(MONTH(A37)=12, R36+X36, 0) + J37 , VLOOKUP(YEAR(A37), Lookup!$Q:$R, 2) ) ), B37>=65, IF(AA36+J37 < VLOOKUP(questions!$C$5, Lookup!$Q:$R, 2), AA36 + IF(MONTH(A37)=12, R36+X36, 0) + J37 , MIN( AA36 + IF(MONTH(A37)=12, R36+X36, 0) + J37, VLOOKUP(questions!$C$5, Lookup!$Q:$R, 2) ) ) ) -> 28160.218 | AB37: =IFS( B37<55, 0, B37=55, MIN(Y36+Z36, AD37), B37>55, IF(AB36 < $AH$7, MIN(AB36 + IF(MONTH(A37)=12, Q37+W37, 0) + K37, $AH$7), AB36 + IF(MONTH(A37)=12, Q37+W37, 0) + K37 ) ) -> 0 | AC37: {=IFS(B37<66, XLOOKUP(year(A37),Lookup!$K$13:$K1000,Lookup!$L$13:$L1000,"missing",,1),B37>65,XLOOKUP(questions!$C$5,Lookup!$K$13:$K1000,Lookup!$L$13:$L1000,"missing",,1))} -> 122226.77 | AD37: {=IFS(B37<66, XLOOKUP(year(A37),Lookup!$K$13:$K1000,Lookup!$M$13:$M1000,"missing",,1),B37>65, XLOOKUP(questions!$C$5,Lookup!$K$13:$K1000,Lookup!$M$13:$M1000,"missing",,1))} -> 244453.55 | AE37: {=IFS(B37<66, XLOOKUP(year(A37),Lookup!$K$13:$K1000,Lookup!$N$13:$N1000,"missing",,1),B37>65,XLOOKUP(questions!$C$5,Lookup!$K$13:$K1000,Lookup!$N$13:$N1000,"missing",,1))} -> 488907.09
A38: =eomonth(EDATE(A37,1),0) -> 47177 | B38: =round(YEARFRAC(EOMONTH(questions!$C$3, 0),A38,1),2) -> 30.25 | C38: =IF(B38<questions!$C$6,if(MONTH(A38)=1,C37*(1+questions!$C$12),C37),0) -> 10927.27 | D38: =IF(MONTH(A38)=12,C38*questions!$C$11,0) -> 0 | E38: =MIN(C38,IF(YEAR(A38)=2025,7600,8000)) -> 8000 | F38: =MIN(102000-E38*12,D38) -> 0 | G38: {=if(YEAR(A38)=2025,XLOOKUP(B38,Lookup!$A$3:$A$7,Lookup!$D$3:$D$7,,1)*SUM(E38:F38), XLOOKUP(B38,Lookup!$A$14:$A$18,Lookup!$D$14:$D$18,,1)*SUM(E38:F38))} -> 2960 | H38: {=if(YEAR(A38)=2025,XLOOKUP(B38,Lookup!$F$3:$F$10,Lookup!$G$3:$G$10,,1)*G38, XLOOKUP(B38,Lookup!$F$14:$F$21,Lookup!$G$14:$G$21,,1)*G38)} -> 1840.232 | I38: {=if(B38<55, if(YEAR(A38)=2025,XLOOKUP(B38,Lookup!$F$3:$F$10,Lookup!$H$3:$H$10,,1)*G38, XLOOKUP(B38,Lookup!$F$14:$F$21,Lookup!$H$14:$H$21,,1)*G38),0)} -> 479.816 | J38: {=if(YEAR(A38)=2025,XLOOKUP(B38,Lookup!$F$3:$F$10,Lookup!$I$3:$I$10,,1)*G38, XLOOKUP(B38,Lookup!$F$14:$F$21,Lookup!$I$14:$I$21,,1)*G38)} -> 639.952 | K38: {=if(B38>54, if(YEAR(A38)=2025,XLOOKUP(B38,Lookup!$F$3:$F$10,Lookup!$H$3:$H$10,,1)*G38, XLOOKUP(B38,Lookup!$F$14:$F$21,Lookup!$H$14:$H$21,,1)*G38),0)} -> 0 | L38: =IF(and(A38<questions!$C$19,questions!$C$18="yes"),questions!$C$20,0) -> 700 | M38: =(Y37+H38)*Lookup!A$26/12 -> 116.75849 | N38: =if(B38<55, (Z37+I38)*Lookup!B$26/12, (AB37+K38)*Lookup!B$26/12) -> 74.963595 | O38: =(AA37+J38)*Lookup!C$26/12 -> 96.000565 | P38: =IF(year(A38)=year(A37), P37+M38, M38) -> 231.14149 | Q38: =IF(year(A38)=year(A37), Q37+N38, N38) -> 148.3278 | R38: =IF(year(A38)=year(A37), R37+O38, O38) -> 189.86796 | S38: =if(B38<55,min(20000,Y37)*0.01/12,min(20000,Y37)*0.02/12) -> 16.666667 | T38: =if(B38<=55,min(60000-min(20000,Y37),Z37)*0.01/12,min(30000-min(20000,Y37),AB37)*0.02/12+min(30000,AB37)*0.01/12) -> 18.341052 | U38: =if(B38<55,min(60000-min(60000-min(20000,Y37),Z37)-min(20000,Y37),AA37)*0.01/12,min(30000-min(30000-min(20000,Y37),AB37)-min(20000,Y37),AA37)*0.02/12+min(30000-min(30000-min(20000,Y37),AB37)-min(20000,Y37),AA37)*0.01/12) -> 14.992281 | V38: =IF(year($A38)=year($A37), V37+S38, S38) -> 33.333333 | W38: =IF(year($A38)=year($A37), W37+T38, T38) -> 36.282258 | X38: =IF(year($A38)=year($A37), X37+U38, U38) -> 30.384409 | Y38: =IFS( B38<55, MAX( Y37 + IF(MONTH(A38)=12, P38+V38, 0) + H38 - L38 + MAX(0, IF(AA37 >= VLOOKUP(YEAR(A38), Lookup!$Q:$R, 2), Z37 + IF(MONTH(A38)=12, Q38+W38, 0) + I38 + AA37 + IF(MONTH(A38)=12, R38+X38, 0) - VLOOKUP(YEAR(A38), Lookup!$Q:$R, 2) + J38, Z37 + IF(MONTH(A38)=12, Q38+W38, 0) + I38 ) - VLOOKUP(YEAR(A38), Lookup!$K:$M, 3) ), 0), B38=55, IF(Z37>=AD38, MAX(Y37 + IF(MONTH(A38)=12, P38+V38, 0) + H38 - L38, 0), MAX(MAX(0, Y37-(AD38-Z37)) + IF(MONTH(A38)=12, P38+V38, 0) + H38 - L38, 0) ), B38>55, IF(AB37>=$AH$7, MAX(Y37 + IF(MONTH(A38)=12, P38+V38, 0) + H38 - L38 + K38 + Z37, 0), MAX(Y37 + IF(MONTH(A38)=12, P38+V38, 0) + H38 - L38, 0) ) ) -> 55344.073 | Z38: =IFS( B38<55, MIN( IF(AA37 >= VLOOKUP(YEAR(A38), Lookup!$Q:$R, 2), Z37 + IF(MONTH(A38)=12, Q38+W38, 0) + I38 + AA37 + IF(MONTH(A38)=12, R38+X38, 0) - VLOOKUP(YEAR(A38), Lookup!$Q:$R, 2) + J38, Z37 + IF(MONTH(A38)=12, Q38+W38, 0) + I38 ), VLOOKUP(YEAR(A38), Lookup!$K:$M, 3) ), B38=55, IF(Z37 >= AD38, Z37 - AD38, 0), B38>55, 0 ) -> 22489.079 | AA38: =IFS( B38<65, IF(AA37+J38 < VLOOKUP(YEAR(A38), Lookup!$Q:$R, 2), AA37 + IF(MONTH(A38)=12, R37+X37, 0) + J38, MIN( AA37 + IF(MONTH(A38)=12, R37+X37, 0) + J38 , VLOOKUP(YEAR(A38), Lookup!$Q:$R, 2) ) ), B38>=65, IF(AA37+J38 < VLOOKUP(questions!$C$5, Lookup!$Q:$R, 2), AA37 + IF(MONTH(A38)=12, R37+X37, 0) + J38 , MIN( AA37 + IF(MONTH(A38)=12, R37+X37, 0) + J38, VLOOKUP(questions!$C$5, Lookup!$Q:$R, 2) ) ) ) -> 28800.17 | AB38: =IFS( B38<55, 0, B38=55, MIN(Y37+Z37, AD38), B38>55, IF(AB37 < $AH$7, MIN(AB37 + IF(MONTH(A38)=12, Q38+W38, 0) + K38, $AH$7), AB37 + IF(MONTH(A38)=12, Q38+W38, 0) + K38 ) ) -> 0 | AC38: {=IFS(B38<66, XLOOKUP(year(A38),Lookup!$K$13:$K1000,Lookup!$L$13:$L1000,"missing",,1),B38>65,XLOOKUP(questions!$C$5,Lookup!$K$13:$K1000,Lookup!$L$13:$L1000,"missing",,1))} -> 122226.77 | AD38: {=IFS(B38<66, XLOOKUP(year(A38),Lookup!$K$13:$K1000,Lookup!$M$13:$M1000,"missing",,1),B38>65, XLOOKUP(questions!$C$5,Lookup!$K$13:$K1000,Lookup!$M$13:$M1000,"missing",,1))} -> 244453.55 | AE38: {=IFS(B38<66, XLOOKUP(year(A38),Lookup!$K$13:$K1000,Lookup!$N$13:$N1000,"missing",,1),B38>65,XLOOKUP(questions!$C$5,Lookup!$K$13:$K1000,Lookup!$N$13:$N1000,"missing",,1))} -> 488907.09
A39: =eomonth(EDATE(A38,1),0) -> 47208 | B39: =round(YEARFRAC(EOMONTH(questions!$C$3, 0),A39,1),2) -> 30.33 | C39: =IF(B39<questions!$C$6,if(MONTH(A39)=1,C38*(1+questions!$C$12),C38),0) -> 10927.27 | D39: =IF(MONTH(A39)=12,C39*questions!$C$11,0) -> 0 | E39: =MIN(C39,IF(YEAR(A39)=2025,7600,8000)) -> 8000 | F39: =MIN(102000-E39*12,D39) -> 0 | G39: {=if(YEAR(A39)=2025,XLOOKUP(B39,Lookup!$A$3:$A$7,Lookup!$D$3:$D$7,,1)*SUM(E39:F39), XLOOKUP(B39,Lookup!$A$14:$A$18,Lookup!$D$14:$D$18,,1)*SUM(E39:F39))} -> 2960 | H39: {=if(YEAR(A39)=2025,XLOOKUP(B39,Lookup!$F$3:$F$10,Lookup!$G$3:$G$10,,1)*G39, XLOOKUP(B39,Lookup!$F$14:$F$21,Lookup!$G$14:$G$21,,1)*G39)} -> 1840.232 | I39: {=if(B39<55, if(YEAR(A39)=2025,XLOOKUP(B39,Lookup!$F$3:$F$10,Lookup!$H$3:$H$10,,1)*G39, XLOOKUP(B39,Lookup!$F$14:$F$21,Lookup!$H$14:$H$21,,1)*G39),0)} -> 479.816 | J39: {=if(YEAR(A39)=2025,XLOOKUP(B39,Lookup!$F$3:$F$10,Lookup!$I$3:$I$10,,1)*G39, XLOOKUP(B39,Lookup!$F$14:$F$21,Lookup!$I$14:$I$21,,1)*G39)} -> 639.952 | K39: {=if(B39>54, if(YEAR(A39)=2025,XLOOKUP(B39,Lookup!$F$3:$F$10,Lookup!$H$3:$H$10,,1)*G39, XLOOKUP(B39,Lookup!$F$14:$F$21,Lookup!$H$14:$H$21,,1)*G39),0)} -> 0 | L39: =IF(and(A39<questions!$C$19,questions!$C$18="yes"),questions!$C$20,0) -> 700 | M39: =(Y38+H39)*Lookup!A$26/12 -> 119.13397 | N39: =if(B39<55, (Z38+I39)*Lookup!B$26/12, (AB38+K39)*Lookup!B$26/12) -> 76.562982 | O39: =(AA38+J39)*Lookup!C$26/12 -> 98.133738 | P39: =IF(year(A39)=year(A38), P38+M39, M39) -> 350.27546 | Q39: =IF(year(A39)=year(A38), Q38+N39, N39) -> 224.89079 | R39: =IF(year(A39)=year(A38), R38+O39, O39) -> 288.0017 | S39: =if(B39<55,min(20000,Y38)*0.01/12,min(20000,Y38)*0.02/12) -> 16.666667 | T39: =if(B39<=55,min(60000-min(20000,Y38),Z38)*0.01/12,min(30000-min(20000,Y38),AB38)*0.02/12+min(30000,AB38)*0.01/12) -> 18.740899 | U39: =if(B39<55,min(60000-min(60000-min(20000,Y38),Z38)-min(20000,Y38),AA38)*0.01/12,min(30000-min(30000-min(20000,Y38),AB38)-min(20000,Y38),AA38)*0.02/12+min(30000-min(30000-min(20000,Y38),AB38)-min(20000,Y38),AA38)*0.01/12) -> 14.592434 | V39: =IF(year($A39)=year($A38), V38+S39, S39) -> 50 | W39: =IF(year($A39)=year($A38), W38+T39, T39) -> 55.023157 | X39: =IF(year($A39)=year($A38), X38+U39, U39) -> 44.976843 | Y39: =IFS( B39<55, MAX( Y38 + IF(MONTH(A39)=12, P39+V39, 0) + H39 - L39 + MAX(0, IF(AA38 >= VLOOKUP(YEAR(A39), Lookup!$Q:$R, 2), Z38 + IF(MONTH(A39)=12, Q39+W39, 0) + I39 + AA38 + IF(MONTH(A39)=12, R39+X39, 0) - VLOOKUP(YEAR(A39), Lookup!$Q:$R, 2) + J39, Z38 + IF(MONTH(A39)=12, Q39+W39, 0) + I39 ) - VLOOKUP(YEAR(A39), Lookup!$K:$M, 3) ), 0), B39=55, IF(Z38>=AD39, MAX(Y38 + IF(MONTH(A39)=12, P39+V39, 0) + H39 - L39, 0), MAX(MAX(0, Y38-(AD39-Z38)) + IF(MONTH(A39)=12, P39+V39, 0) + H39 - L39, 0) ), B39>55, IF(AB38>=$AH$7, MAX(Y38 + IF(MONTH(A39)=12, P39+V39, 0) + H39 - L39 + K39 + Z38, 0), MAX(Y38 + IF(MONTH(A39)=12, P39+V39, 0) + H39 - L39, 0) ) ) -> 56484.305 | Z39: =IFS( B39<55, MIN( IF(AA38 >= VLOOKUP(YEAR(A39), Lookup!$Q:$R, 2), Z38 + IF(MONTH(A39)=12, Q39+W39, 0) + I39 + AA38 + IF(MONTH(A39)=12, R39+X39, 0) - VLOOKUP(YEAR(A39), Lookup!$Q:$R, 2) + J39, Z38 + IF(MONTH(A39)=12, Q39+W39, 0) + I39 ), VLOOKUP(YEAR(A39), Lookup!$K:$M, 3) ), B39=55, IF(Z38 >= AD39, Z38 - AD39, 0), B39>55, 0 ) -> 22968.895 | AA39: =IFS( B39<65, IF(AA38+J39 < VLOOKUP(YEAR(A39), Lookup!$Q:$R, 2), AA38 + IF(MONTH(A39)=12, R38+X38, 0) + J39, MIN( AA38 + IF(MONTH(A39)=12, R38+X38, 0) + J39 , VLOOKUP(YEAR(A39), Lookup!$Q:$R, 2) ) ), B39>=65, IF(AA38+J39 < VLOOKUP(questions!$C$5, Lookup!$Q:$R, 2), AA38 + IF(MONTH(A39)=12, R38+X38, 0) + J39 , MIN( AA38 + IF(MONTH(A39)=12, R38+X38, 0) + J39, VLOOKUP(questions!$C$5, Lookup!$Q:$R, 2) ) ) ) -> 29440.122 | AB39: =IFS( B39<55, 0, B39=55, MIN(Y38+Z38, AD39), B39>55, IF(AB38 < $AH$7, MIN(AB38 + IF(MONTH(A39)=12, Q39+W39, 0) + K39, $AH$7), AB38 + IF(MONTH(A39)=12, Q39+W39, 0) + K39 ) ) -> 0 | AC39: {=IFS(B39<66, XLOOKUP(year(A39),Lookup!$K$13:$K1000,Lookup!$L$13:$L1000,"missing",,1),B39>65,XLOOKUP(questions!$C$5,Lookup!$K$13:$K1000,Lookup!$L$13:$L1000,"missing",,1))} -> 122226.77 | AD39: {=IFS(B39<66, XLOOKUP(year(A39),Lookup!$K$13:$K1000,Lookup!$M$13:$M1000,"missing",,1),B39>65, XLOOKUP(questions!$C$5,Lookup!$K$13:$K1000,Lookup!$M$13:$M1000,"missing",,1))} -> 244453.55 | AE39: {=IFS(B39<66, XLOOKUP(year(A39),Lookup!$K$13:$K1000,Lookup!$N$13:$N1000,"missing",,1),B39>65,XLOOKUP(questions!$C$5,Lookup!$K$13:$K1000,Lookup!$N$13:$N1000,"missing",,1))} -> 488907.09
A40: =eomonth(EDATE(A39,1),0) -> 47238 | B40: =round(YEARFRAC(EOMONTH(questions!$C$3, 0),A40,1),2) -> 30.41 | C40: =IF(B40<questions!$C$6,if(MONTH(A40)=1,C39*(1+questions!$C$12),C39),0) -> 10927.27 | D40: =IF(MONTH(A40)=12,C40*questions!$C$11,0) -> 0 | E40: =MIN(C40,IF(YEAR(A40)=2025,7600,8000)) -> 8000 | F40: =MIN(102000-E40*12,D40) -> 0 | G40: {=if(YEAR(A40)=2025,XLOOKUP(B40,Lookup!$A$3:$A$7,Lookup!$D$3:$D$7,,1)*SUM(E40:F40), XLOOKUP(B40,Lookup!$A$14:$A$18,Lookup!$D$14:$D$18,,1)*SUM(E40:F40))} -> 2960 | H40: {=if(YEAR(A40)=2025,XLOOKUP(B40,Lookup!$F$3:$F$10,Lookup!$G$3:$G$10,,1)*G40, XLOOKUP(B40,Lookup!$F$14:$F$21,Lookup!$G$14:$G$21,,1)*G40)} -> 1840.232 | I40: {=if(B40<55, if(YEAR(A40)=2025,XLOOKUP(B40,Lookup!$F$3:$F$10,Lookup!$H$3:$H$10,,1)*G40, XLOOKUP(B40,Lookup!$F$14:$F$21,Lookup!$H$14:$H$21,,1)*G40),0)} -> 479.816 | J40: {=if(YEAR(A40)=2025,XLOOKUP(B40,Lookup!$F$3:$F$10,Lookup!$I$3:$I$10,,1)*G40, XLOOKUP(B40,Lookup!$F$14:$F$21,Lookup!$I$14:$I$21,,1)*G40)} -> 639.952 | K40: {=if(B40>54, if(YEAR(A40)=2025,XLOOKUP(B40,Lookup!$F$3:$F$10,Lookup!$H$3:$H$10,,1)*G40, XLOOKUP(B40,Lookup!$F$14:$F$21,Lookup!$H$14:$H$21,,1)*G40),0)} -> 0 | L40: =IF(and(A40<questions!$C$19,questions!$C$18="yes"),questions!$C$20,0) -> 700 | M40: =(Y39+H40)*Lookup!A$26/12 -> 121.50945 | N40: =if(B40<55, (Z39+I40)*Lookup!B$26/12, (AB39+K40)*Lookup!B$26/12) -> 78.162369 | O40: =(AA39+J40)*Lookup!C$26/12 -> 100.26691 | P40: =IF(year(A40)=year(A39), P39+M40, M40) -> 471.78491 | Q40: =IF(year(A40)=year(A39), Q39+N40, N40) -> 303.05316 | R40: =IF(year(A40)=year(A39), R39+O40, O40) -> 388.26861 | S40: =if(B40<55,min(20000,Y39)*0.01/12,min(20000,Y39)*0.02/12) -> 16.666667 | T40: =if(B40<=55,min(60000-min(20000,Y39),Z39)*0.01/12,min(30000-min(20000,Y39),AB39)*0.02/12+min(30000,AB39)*0.01/12) -> 19.140746 | U40: =if(B40<55,min(60000-min(60000-min(20000,Y39),Z39)-min(20000,Y39),AA39)*0.01/12,min(30000-min(30000-min(20000,Y39),AB39)-min(20000,Y39),AA39)*0.02/12+min(30000-min(30000-min(20000,Y39),AB39)-min(20000,Y39),AA39)*0.01/12) -> 14.192588 | V40: =IF(year($A40)=year($A39), V39+S40, S40) -> 66.666667 | W40: =IF(year($A40)=year($A39), W39+T40, T40) -> 74.163902 | X40: =IF(year($A40)=year($A39), X39+U40, U40) -> 59.169431 | Y40: =IFS( B40<55, MAX( Y39 + IF(MONTH(A40)=12, P40+V40, 0) + H40 - L40 + MAX(0, IF(AA39 >= VLOOKUP(YEAR(A40), Lookup!$Q:$R, 2), Z39 + IF(MONTH(A40)=12, Q40+W40, 0) + I40 + AA39 + IF(MONTH(A40)=12, R40+X40, 0) - VLOOKUP(YEAR(A40), Lookup!$Q:$R, 2) + J40, Z39 + IF(MONTH(A40)=12, Q40+W40, 0) + I40 ) - VLOOKUP(YEAR(A40), Lookup!$K:$M, 3) ), 0), B40=55, IF(Z39>=AD40, MAX(Y39 + IF(MONTH(A40)=12, P40+V40, 0) + H40 - L40, 0), MAX(MAX(0, Y39-(AD40-Z39)) + IF(MONTH(A40)=12, P40+V40, 0) + H40 - L40, 0) ), B40>55, IF(AB39>=$AH$7, MAX(Y39 + IF(MONTH(A40)=12, P40+V40, 0) + H40 - L40 + K40 + Z39, 0), MAX(Y39 + IF(MONTH(A40)=12, P40+V40, 0) + H40 - L40, 0) ) ) -> 57624.537 | Z40: =IFS( B40<55, MIN( IF(AA39 >= VLOOKUP(YEAR(A40), Lookup!$Q:$R, 2), Z39 + IF(MONTH(A40)=12, Q40+W40, 0) + I40 + AA39 + IF(MONTH(A40)=12, R40+X40, 0) - VLOOKUP(YEAR(A40), Lookup!$Q:$R, 2) + J40, Z39 + IF(MONTH(A40)=12, Q40+W40, 0) + I40 ), VLOOKUP(YEAR(A40), Lookup!$K:$M, 3) ), B40=55, IF(Z39 >= AD40, Z39 - AD40, 0), B40>55, 0 ) -> 23448.711 | AA40: =IFS( B40<65, IF(AA39+J40 < VLOOKUP(YEAR(A40), Lookup!$Q:$R, 2), AA39 + IF(MONTH(A40)=12, R39+X39, 0) + J40, MIN( AA39 + IF(MONTH(A40)=12, R39+X39, 0) + J40 , VLOOKUP(YEAR(A40), Lookup!$Q:$R, 2) ) ), B40>=65, IF(AA39+J40 < VLOOKUP(questions!$C$5, Lookup!$Q:$R, 2), AA39 + IF(MONTH(A40)=12, R39+X39, 0) + J40 , MIN( AA39 + IF(MONTH(A40)=12, R39+X39, 0) + J40, VLOOKUP(questions!$C$5, Lookup!$Q:$R, 2) ) ) ) -> 30080.074 | AB40: =IFS( B40<55, 0, B40=55, MIN(Y39+Z39, AD40), B40>55, IF(AB39 < $AH$7, MIN(AB39 + IF(MONTH(A40)=12, Q40+W40, 0) + K40, $AH$7), AB39 + IF(MONTH(A40)=12, Q40+W40, 0) + K40 ) ) -> 0 | AC40: {=IFS(B40<66, XLOOKUP(year(A40),Lookup!$K$13:$K1000,Lookup!$L$13:$L1000,"missing",,1),B40>65,XLOOKUP(questions!$C$5,Lookup!$K$13:$K1000,Lookup!$L$13:$L1000,"missing",,1))} -> 122226.77 | AD40: {=IFS(B40<66, XLOOKUP(year(A40),Lookup!$K$13:$K1000,Lookup!$M$13:$M1000,"missing",,1),B40>65, XLOOKUP(questions!$C$5,Lookup!$K$13:$K1000,Lookup!$M$13:$M1000,"missing",,1))} -> 244453.55 | AE40: {=IFS(B40<66, XLOOKUP(year(A40),Lookup!$K$13:$K1000,Lookup!$N$13:$N1000,"missing",,1),B40>65,XLOOKUP(questions!$C$5,Lookup!$K$13:$K1000,Lookup!$N$13:$N1000,"missing",,1))} -> 488907.09
A41: =eomonth(EDATE(A40,1),0) -> 47269 | B41: =round(YEARFRAC(EOMONTH(questions!$C$3, 0),A41,1),2) -> 30.5 | C41: =IF(B41<questions!$C$6,if(MONTH(A41)=1,C40*(1+questions!$C$12),C40),0) -> 10927.27 | D41: =IF(MONTH(A41)=12,C41*questions!$C$11,0) -> 0 | E41: =MIN(C41,IF(YEAR(A41)=2025,7600,8000)) -> 8000 | F41: =MIN(102000-E41*12,D41) -> 0 | G41: {=if(YEAR(A41)=2025,XLOOKUP(B41,Lookup!$A$3:$A$7,Lookup!$D$3:$D$7,,1)*SUM(E41:F41), XLOOKUP(B41,Lookup!$A$14:$A$18,Lookup!$D$14:$D$18,,1)*SUM(E41:F41))} -> 2960 | H41: {=if(YEAR(A41)=2025,XLOOKUP(B41,Lookup!$F$3:$F$10,Lookup!$G$3:$G$10,,1)*G41, XLOOKUP(B41,Lookup!$F$14:$F$21,Lookup!$G$14:$G$21,,1)*G41)} -> 1840.232 | I41: {=if(B41<55, if(YEAR(A41)=2025,XLOOKUP(B41,Lookup!$F$3:$F$10,Lookup!$H$3:$H$10,,1)*G41, XLOOKUP(B41,Lookup!$F$14:$F$21,Lookup!$H$14:$H$21,,1)*G41),0)} -> 479.816 | J41: {=if(YEAR(A41)=2025,XLOOKUP(B41,Lookup!$F$3:$F$10,Lookup!$I$3:$I$10,,1)*G41, XLOOKUP(B41,Lookup!$F$14:$F$21,Lookup!$I$14:$I$21,,1)*G41)} -> 639.952 | K41: {=if(B41>54, if(YEAR(A41)=2025,XLOOKUP(B41,Lookup!$F$3:$F$10,Lookup!$H$3:$H$10,,1)*G41, XLOOKUP(B41,Lookup!$F$14:$F$21,Lookup!$H$14:$H$21,,1)*G41),0)} -> 0 | L41: =IF(and(A41<questions!$C$19,questions!$C$18="yes"),questions!$C$20,0) -> 700 | M41: =(Y40+H41)*Lookup!A$26/12 -> 123.88494 | N41: =if(B41<55, (Z40+I41)*Lookup!B$26/12, (AB40+K41)*Lookup!B$26/12) -> 79.761755 | O41: =(AA40+J41)*Lookup!C$26/12 -> 102.40009 | P41: =IF(year(A41)=year(A40), P40+M41, M41) -> 595.66984 | Q41: =IF(year(A41)=year(A40), Q40+N41, N41) -> 382.81491 | R41: =IF(year(A41)=year(A40), R40+O41, O41) -> 490.66869 | S41: =if(B41<55,min(20000,Y40)*0.01/12,min(20000,Y40)*0.02/12) -> 16.666667 | T41: =if(B41<=55,min(60000-min(20000,Y40),Z40)*0.01/12,min(30000-min(20000,Y40),AB40)*0.02/12+min(30000,AB40)*0.01/12) -> 19.540592 | U41: =if(B41<55,min(60000-min(60000-min(20000,Y40),Z40)-min(20000,Y40),AA40)*0.01/12,min(30000-min(30000-min(20000,Y40),AB40)-min(20000,Y40),AA40)*0.02/12+min(30000-min(30000-min(20000,Y40),AB40)-min(20000,Y40),AA40)*0.01/12) -> 13.792741 | V41: =IF(year($A41)=year($A40), V40+S41, S41) -> 83.333333 | W41: =IF(year($A41)=year($A40), W40+T41, T41) -> 93.704494 | X41: =IF(year($A41)=year($A40), X40+U41, U41) -> 72.962172 | Y41: =IFS( B41<55, MAX( Y40 + IF(MONTH(A41)=12, P41+V41, 0) + H41 - L41 + MAX(0, IF(AA40 >= VLOOKUP(YEAR(A41), Lookup!$Q:$R, 2), Z40 + IF(MONTH(A41)=12, Q41+W41, 0) + I41 + AA40 + IF(MONTH(A41)=12, R41+X41, 0) - VLOOKUP(YEAR(A41), Lookup!$Q:$R, 2) + J41, Z40 + IF(MONTH(A41)=12, Q41+W41, 0) + I41 ) - VLOOKUP(YEAR(A41), Lookup!$K:$M, 3) ), 0), B41=55, IF(Z40>=AD41, MAX(Y40 + IF(MONTH(A41)=12, P41+V41, 0) + H41 - L41, 0), MAX(MAX(0, Y40-(AD41-Z40)) + IF(MONTH(A41)=12, P41+V41, 0) + H41 - L41, 0) ), B41>55, IF(AB40>=$AH$7, MAX(Y40 + IF(MONTH(A41)=12, P41+V41, 0) + H41 - L41 + K41 + Z40, 0), MAX(Y40 + IF(MONTH(A41)=12, P41+V41, 0) + H41 - L41, 0) ) ) -> 58764.769 | Z41: =IFS( B41<55, MIN( IF(AA40 >= VLOOKUP(YEAR(A41), Lookup!$Q:$R, 2), Z40 + IF(MONTH(A41)=12, Q41+W41, 0) + I41 + AA40 + IF(MONTH(A41)=12, R41+X41, 0) - VLOOKUP(YEAR(A41), Lookup!$Q:$R, 2) + J41, Z40 + IF(MONTH(A41)=12, Q41+W41, 0) + I41 ), VLOOKUP(YEAR(A41), Lookup!$K:$M, 3) ), B41=55, IF(Z40 >= AD41, Z40 - AD41, 0), B41>55, 0 ) -> 23928.527 | AA41: =IFS( B41<65, IF(AA40+J41 < VLOOKUP(YEAR(A41), Lookup!$Q:$R, 2), AA40 + IF(MONTH(A41)=12, R40+X40, 0) + J41, MIN( AA40 + IF(MONTH(A41)=12, R40+X40, 0) + J41 , VLOOKUP(YEAR(A41), Lookup!$Q:$R, 2) ) ), B41>=65, IF(AA40+J41 < VLOOKUP(questions!$C$5, Lookup!$Q:$R, 2), AA40 + IF(MONTH(A41)=12, R40+X40, 0) + J41 , MIN( AA40 + IF(MONTH(A41)=12, R40+X40, 0) + J41, VLOOKUP(questions!$C$5, Lookup!$Q:$R, 2) ) ) ) -> 30720.026 | AB41: =IFS( B41<55, 0, B41=55, MIN(Y40+Z40, AD41), B41>55, IF(AB40 < $AH$7, MIN(AB40 + IF(MONTH(A41)=12, Q41+W41, 0) + K41, $AH$7), AB40 + IF(MONTH(A41)=12, Q41+W41, 0) + K41 ) ) -> 0 | AC41: {=IFS(B41<66, XLOOKUP(year(A41),Lookup!$K$13:$K1000,Lookup!$L$13:$L1000,"missing",,1),B41>65,XLOOKUP(questions!$C$5,Lookup!$K$13:$K1000,Lookup!$L$13:$L1000,"missing",,1))} -> 122226.77 | AD41: {=IFS(B41<66, XLOOKUP(year(A41),Lookup!$K$13:$K1000,Lookup!$M$13:$M1000,"missing",,1),B41>65, XLOOKUP(questions!$C$5,Lookup!$K$13:$K1000,Lookup!$M$13:$M1000,"missing",,1))} -> 244453.55 | AE41: {=IFS(B41<66, XLOOKUP(year(A41),Lookup!$K$13:$K1000,Lookup!$N$13:$N1000,"missing",,1),B41>65,XLOOKUP(questions!$C$5,Lookup!$K$13:$K1000,Lookup!$N$13:$N1000,"missing",,1))} -> 488907.09
A42: =eomonth(EDATE(A41,1),0) -> 47299 | B42: =round(YEARFRAC(EOMONTH(questions!$C$3, 0),A42,1),2) -> 30.58 | C42: =IF(B42<questions!$C$6,if(MONTH(A42)=1,C41*(1+questions!$C$12),C41),0) -> 10927.27 | D42: =IF(MONTH(A42)=12,C42*questions!$C$11,0) -> 0 | E42: =MIN(C42,IF(YEAR(A42)=2025,7600,8000)) -> 8000 | F42: =MIN(102000-E42*12,D42) -> 0 | G42: {=if(YEAR(A42)=2025,XLOOKUP(B42,Lookup!$A$3:$A$7,Lookup!$D$3:$D$7,,1)*SUM(E42:F42), XLOOKUP(B42,Lookup!$A$14:$A$18,Lookup!$D$14:$D$18,,1)*SUM(E42:F42))} -> 2960 | H42: {=if(YEAR(A42)=2025,XLOOKUP(B42,Lookup!$F$3:$F$10,Lookup!$G$3:$G$10,,1)*G42, XLOOKUP(B42,Lookup!$F$14:$F$21,Lookup!$G$14:$G$21,,1)*G42)} -> 1840.232 | I42: {=if(B42<55, if(YEAR(A42)=2025,XLOOKUP(B42,Lookup!$F$3:$F$10,Lookup!$H$3:$H$10,,1)*G42, XLOOKUP(B42,Lookup!$F$14:$F$21,Lookup!$H$14:$H$21,,1)*G42),0)} -> 479.816 | J42: {=if(YEAR(A42)=2025,XLOOKUP(B42,Lookup!$F$3:$F$10,Lookup!$I$3:$I$10,,1)*G42, XLOOKUP(B42,Lookup!$F$14:$F$21,Lookup!$I$14:$I$21,,1)*G42)} -> 639.952 | K42: {=if(B42>54, if(YEAR(A42)=2025,XLOOKUP(B42,Lookup!$F$3:$F$10,Lookup!$H$3:$H$10,,1)*G42, XLOOKUP(B42,Lookup!$F$14:$F$21,Lookup!$H$14:$H$21,,1)*G42),0)} -> 0 | L42: =IF(and(A42<questions!$C$19,questions!$C$18="yes"),questions!$C$20,0) -> 700 | M42: =(Y41+H42)*Lookup!A$26/12 -> 126.26042 | N42: =if(B42<55, (Z41+I42)*Lookup!B$26/12, (AB41+K42)*Lookup!B$26/12) -> 81.361142 | O42: =(AA41+J42)*Lookup!C$26/12 -> 104.53326 | P42: =IF(year(A42)=year(A41), P41+M42, M42) -> 721.93026 | Q42: =IF(year(A42)=year(A41), Q41+N42, N42) -> 464.17605 | R42: =IF(year(A42)=year(A41), R41+O42, O42) -> 595.20195 | S42: =if(B42<55,min(20000,Y41)*0.01/12,min(20000,Y41)*0.02/12) -> 16.666667 | T42: =if(B42<=55,min(60000-min(20000,Y41),Z41)*0.01/12,min(30000-min(20000,Y41),AB41)*0.02/12+min(30000,AB41)*0.01/12) -> 19.940439 | U42: =if(B42<55,min(60000-min(60000-min(20000,Y41),Z41)-min(20000,Y41),AA41)*0.01/12,min(30000-min(30000-min(20000,Y41),AB41)-min(20000,Y41),AA41)*0.02/12+min(30000-min(30000-min(20000,Y41),AB41)-min(20000,Y41),AA41)*0.01/12) -> 13.392894 | V42: =IF(year($A42)=year($A41), V41+S42, S42) -> 100 | W42: =IF(year($A42)=year($A41), W41+T42, T42) -> 113.64493 | X42: =IF(year($A42)=year($A41), X41+U42, U42) -> 86.355067 | Y42: =IFS( B42<55, MAX( Y41 + IF(MONTH(A42)=12, P42+V42, 0) + H42 - L42 + MAX(0, IF(AA41 >= VLOOKUP(YEAR(A42), Lookup!$Q:$R, 2), Z41 + IF(MONTH(A42)=12, Q42+W42, 0) + I42 + AA41 + IF(MONTH(A42)=12, R42+X42, 0) - VLOOKUP(YEAR(A42), Lookup!$Q:$R, 2) + J42, Z41 + IF(MONTH(A42)=12, Q42+W42, 0) + I42 ) - VLOOKUP(YEAR(A42), Lookup!$K:$M, 3) ), 0), B42=55, IF(Z41>=AD42, MAX(Y41 + IF(MONTH(A42)=12, P42+V42, 0) + H42 - L42, 0), MAX(MAX(0, Y41-(AD42-Z41)) + IF(MONTH(A42)=12, P42+V42, 0) + H42 - L42, 0) ), B42>55, IF(AB41>=$AH$7, MAX(Y41 + IF(MONTH(A42)=12, P42+V42, 0) + H42 - L42 + K42 + Z41, 0), MAX(Y41 + IF(MONTH(A42)=12, P42+V42, 0) + H42 - L42, 0) ) ) -> 59905.001 | Z42: =IFS( B42<55, MIN( IF(AA41 >= VLOOKUP(YEAR(A42), Lookup!$Q:$R, 2), Z41 + IF(MONTH(A42)=12, Q42+W42, 0) + I42 + AA41 + IF(MONTH(A42)=12, R42+X42, 0) - VLOOKUP(YEAR(A42), Lookup!$Q:$R, 2) + J42, Z41 + IF(MONTH(A42)=12, Q42+W42, 0) + I42 ), VLOOKUP(YEAR(A42), Lookup!$K:$M, 3) ), B42=55, IF(Z41 >= AD42, Z41 - AD42, 0), B42>55, 0 ) -> 24408.343 | AA42: =IFS( B42<65, IF(AA41+J42 < VLOOKUP(YEAR(A42), Lookup!$Q:$R, 2), AA41 + IF(MONTH(A42)=12, R41+X41, 0) + J42, MIN( AA41 + IF(MONTH(A42)=12, R41+X41, 0) + J42 , VLOOKUP(YEAR(A42), Lookup!$Q:$R, 2) ) ), B42>=65, IF(AA41+J42 < VLOOKUP(questions!$C$5, Lookup!$Q:$R, 2), AA41 + IF(MONTH(A42)=12, R41+X41, 0) + J42 , MIN( AA41 + IF(MONTH(A42)=12, R41+X41, 0) + J42, VLOOKUP(questions!$C$5, Lookup!$Q:$R, 2) ) ) ) -> 31359.978 | AB42: =IFS( B42<55, 0, B42=55, MIN(Y41+Z41, AD42), B42>55, IF(AB41 < $AH$7, MIN(AB41 + IF(MONTH(A42)=12, Q42+W42, 0) + K42, $AH$7), AB41 + IF(MONTH(A42)=12, Q42+W42, 0) + K42 ) ) -> 0 | AC42: {=IFS(B42<66, XLOOKUP(year(A42),Lookup!$K$13:$K1000,Lookup!$L$13:$L1000,"missing",,1),B42>65,XLOOKUP(questions!$C$5,Lookup!$K$13:$K1000,Lookup!$L$13:$L1000,"missing",,1))} -> 122226.77 | AD42: {=IFS(B42<66, XLOOKUP(year(A42),Lookup!$K$13:$K1000,Lookup!$M$13:$M1000,"missing",,1),B42>65, XLOOKUP(questions!$C$5,Lookup!$K$13:$K1000,Lookup!$M$13:$M1000,"missing",,1))} -> 244453.55 | AE42: {=IFS(B42<66, XLOOKUP(year(A42),Lookup!$K$13:$K1000,Lookup!$N$13:$N1000,"missing",,1),B42>65,XLOOKUP(questions!$C$5,Lookup!$K$13:$K1000,Lookup!$N$13:$N1000,"missing",,1))} -> 488907.09
A43: =eomonth(EDATE(A42,1),0) -> 47330 | B43: =round(YEARFRAC(EOMONTH(questions!$C$3, 0),A43,1),2) -> 30.67 | C43: =IF(B43<questions!$C$6,if(MONTH(A43)=1,C42*(1+questions!$C$12),C42),0) -> 10927.27 | D43: =IF(MONTH(A43)=12,C43*questions!$C$11,0) -> 0 | E43: =MIN(C43,IF(YEAR(A43)=2025,7600,8000)) -> 8000 | F43: =MIN(102000-E43*12,D43) -> 0 | G43: {=if(YEAR(A43)=2025,XLOOKUP(B43,Lookup!$A$3:$A$7,Lookup!$D$3:$D$7,,1)*SUM(E43:F43), XLOOKUP(B43,Lookup!$A$14:$A$18,Lookup!$D$14:$D$18,,1)*SUM(E43:F43))} -> 2960 | H43: {=if(YEAR(A43)=2025,XLOOKUP(B43,Lookup!$F$3:$F$10,Lookup!$G$3:$G$10,,1)*G43, XLOOKUP(B43,Lookup!$F$14:$F$21,Lookup!$G$14:$G$21,,1)*G43)} -> 1840.232 | I43: {=if(B43<55, if(YEAR(A43)=2025,XLOOKUP(B43,Lookup!$F$3:$F$10,Lookup!$H$3:$H$10,,1)*G43, XLOOKUP(B43,Lookup!$F$14:$F$21,Lookup!$H$14:$H$21,,1)*G43),0)} -> 479.816 | J43: {=if(YEAR(A43)=2025,XLOOKUP(B43,Lookup!$F$3:$F$10,Lookup!$I$3:$I$10,,1)*G43, XLOOKUP(B43,Lookup!$F$14:$F$21,Lookup!$I$14:$I$21,,1)*G43)} -> 639.952 | K43: {=if(B43>54, if(YEAR(A43)=2025,XLOOKUP(B43,Lookup!$F$3:$F$10,Lookup!$H$3:$H$10,,1)*G43, XLOOKUP(B43,Lookup!$F$14:$F$21,Lookup!$H$14:$H$21,,1)*G43),0)} -> 0 | L43: =IF(and(A43<questions!$C$19,questions!$C$18="yes"),questions!$C$20,0) -> 700 | M43: =(Y42+H43)*Lookup!A$26/12 -> 128.6359 | N43: =if(B43<55, (Z42+I43)*Lookup!B$26/12, (AB42+K43)*Lookup!B$26/12) -> 82.960529 | O43: =(AA42+J43)*Lookup!C$26/12 -> 106.66643 | P43: =IF(year(A43)=year(A42), P42+M43, M43) -> 850.56616 | Q43: =IF(year(A43)=year(A42), Q42+N43, N43) -> 547.13658 | R43: =IF(year(A43)=year(A42), R42+O43, O43) -> 701.86838 | S43: =if(B43<55,min(20000,Y42)*0.01/12,min(20000,Y42)*0.02/12) -> 16.666667 | T43: =if(B43<=55,min(60000-min(20000,Y42),Z42)*0.01/12,min(30000-min(20000,Y42),AB42)*0.02/12+min(30000,AB42)*0.01/12) -> 20.340286 | U43: =if(B43<55,min(60000-min(60000-min(20000,Y42),Z42)-min(20000,Y42),AA42)*0.01/12,min(30000-min(30000-min(20000,Y42),AB42)-min(20000,Y42),AA42)*0.02/12+min(30000-min(30000-min(20000,Y42),AB42)-min(20000,Y42),AA42)*0.01/12) -> 12.993048 | V43: =IF(year($A43)=year($A42), V42+S43, S43) -> 116.66667 | W43: =IF(year($A43)=year($A42), W42+T43, T43) -> 133.98522 | X43: =IF(year($A43)=year($A42), X42+U43, U43) -> 99.348115 | Y43: =IFS( B43<55, MAX( Y42 + IF(MONTH(A43)=12, P43+V43, 0) + H43 - L43 + MAX(0, IF(AA42 >= VLOOKUP(YEAR(A43), Lookup!$Q:$R, 2), Z42 + IF(MONTH(A43)=12, Q43+W43, 0) + I43 + AA42 + IF(MONTH(A43)=12, R43+X43, 0) - VLOOKUP(YEAR(A43), Lookup!$Q:$R, 2) + J43, Z42 + IF(MONTH(A43)=12, Q43+W43, 0) + I43 ) - VLOOKUP(YEAR(A43), Lookup!$K:$M, 3) ), 0), B43=55, IF(Z42>=AD43, MAX(Y42 + IF(MONTH(A43)=12, P43+V43, 0) + H43 - L43, 0), MAX(MAX(0, Y42-(AD43-Z42)) + IF(MONTH(A43)=12, P43+V43, 0) + H43 - L43, 0) ), B43>55, IF(AB42>=$AH$7, MAX(Y42 + IF(MONTH(A43)=12, P43+V43, 0) + H43 - L43 + K43 + Z42, 0), MAX(Y42 + IF(MONTH(A43)=12, P43+V43, 0) + H43 - L43, 0) ) ) -> 61045.233 | Z43: =IFS( B43<55, MIN( IF(AA42 >= VLOOKUP(YEAR(A43), Lookup!$Q:$R, 2), Z42 + IF(MONTH(A43)=12, Q43+W43, 0) + I43 + AA42 + IF(MONTH(A43)=12, R43+X43, 0) - VLOOKUP(YEAR(A43), Lookup!$Q:$R, 2) + J43, Z42 + IF(MONTH(A43)=12, Q43+W43, 0) + I43 ), VLOOKUP(YEAR(A43), Lookup!$K:$M, 3) ), B43=55, IF(Z42 >= AD43, Z42 - AD43, 0), B43>55, 0 ) -> 24888.159 | AA43: =IFS( B43<65, IF(AA42+J43 < VLOOKUP(YEAR(A43), Lookup!$Q:$R, 2), AA42 + IF(MONTH(A43)=12, R42+X42, 0) + J43, MIN( AA42 + IF(MONTH(A43)=12, R42+X42, 0) + J43 , VLOOKUP(YEAR(A43), Lookup!$Q:$R, 2) ) ), B43>=65, IF(AA42+J43 < VLOOKUP(questions!$C$5, Lookup!$Q:$R, 2), AA42 + IF(MONTH(A43)=12, R42+X42, 0) + J43 , MIN( AA42 + IF(MONTH(A43)=12, R42+X42, 0) + J43, VLOOKUP(questions!$C$5, Lookup!$Q:$R, 2) ) ) ) -> 31999.93 | AB43: =IFS( B43<55, 0, B43=55, MIN(Y42+Z42, AD43), B43>55, IF(AB42 < $AH$7, MIN(AB42 + IF(MONTH(A43)=12, Q43+W43, 0) + K43, $AH$7), AB42 + IF(MONTH(A43)=12, Q43+W43, 0) + K43 ) ) -> 0 | AC43: {=IFS(B43<66, XLOOKUP(year(A43),Lookup!$K$13:$K1000,Lookup!$L$13:$L1000,"missing",,1),B43>65,XLOOKUP(questions!$C$5,Lookup!$K$13:$K1000,Lookup!$L$13:$L1000,"missing",,1))} -> 122226.77 | AD43: {=IFS(B43<66, XLOOKUP(year(A43),Lookup!$K$13:$K1000,Lookup!$M$13:$M1000,"missing",,1),B43>65, XLOOKUP(questions!$C$5,Lookup!$K$13:$K1000,Lookup!$M$13:$M1000,"missing",,1))} -> 244453.55 | AE43: {=IFS(B43<66, XLOOKUP(year(A43),Lookup!$K$13:$K1000,Lookup!$N$13:$N1000,"missing",,1),B43>65,XLOOKUP(questions!$C$5,Lookup!$K$13:$K1000,Lookup!$N$13:$N1000,"missing",,1))} -> 488907.09
A44: =eomonth(EDATE(A43,1),0) -> 47361 | B44: =round(YEARFRAC(EOMONTH(questions!$C$3, 0),A44,1),2) -> 30.75 | C44: =IF(B44<questions!$C$6,if(MONTH(A44)=1,C43*(1+questions!$C$12),C43),0) -> 10927.27 | D44: =IF(MONTH(A44)=12,C44*questions!$C$11,0) -> 0 | E44: =MIN(C44,IF(YEAR(A44)=2025,7600,8000)) -> 8000 | F44: =MIN(102000-E44*12,D44) -> 0 | G44: {=if(YEAR(A44)=2025,XLOOKUP(B44,Lookup!$A$3:$A$7,Lookup!$D$3:$D$7,,1)*SUM(E44:F44), XLOOKUP(B44,Lookup!$A$14:$A$18,Lookup!$D$14:$D$18,,1)*SUM(E44:F44))} -> 2960 | H44: {=if(YEAR(A44)=2025,XLOOKUP(B44,Lookup!$F$3:$F$10,Lookup!$G$3:$G$10,,1)*G44, XLOOKUP(B44,Lookup!$F$14:$F$21,Lookup!$G$14:$G$21,,1)*G44)} -> 1840.232 | I44: {=if(B44<55, if(YEAR(A44)=2025,XLOOKUP(B44,Lookup!$F$3:$F$10,Lookup!$H$3:$H$10,,1)*G44, XLOOKUP(B44,Lookup!$F$14:$F$21,Lookup!$H$14:$H$21,,1)*G44),0)} -> 479.816 | J44: {=if(YEAR(A44)=2025,XLOOKUP(B44,Lookup!$F$3:$F$10,Lookup!$I$3:$I$10,,1)*G44, XLOOKUP(B44,Lookup!$F$14:$F$21,Lookup!$I$14:$I$21,,1)*G44)} -> 639.952 | K44: {=if(B44>54, if(YEAR(A44)=2025,XLOOKUP(B44,Lookup!$F$3:$F$10,Lookup!$H$3:$H$10,,1)*G44, XLOOKUP(B44,Lookup!$F$14:$F$21,Lookup!$H$14:$H$21,,1)*G44),0)} -> 0 | L44: =IF(and(A44<questions!$C$19,questions!$C$18="yes"),questions!$C$20,0) -> 700 | M44: =(Y43+H44)*Lookup!A$26/12 -> 131.01139 | N44: =if(B44<55, (Z43+I44)*Lookup!B$26/12, (AB43+K44)*Lookup!B$26/12) -> 84.559915 | O44: =(AA43+J44)*Lookup!C$26/12 -> 108.79961 | P44: =IF(year(A44)=year(A43), P43+M44, M44) -> 981.57755 | Q44: =IF(year(A44)=year(A43), Q43+N44, N44) -> 631.6965 | R44: =IF(year(A44)=year(A43), R43+O44, O44) -> 810.66799 | S44: =if(B44<55,min(20000,Y43)*0.01/12,min(20000,Y43)*0.02/12) -> 16.666667 | T44: =if(B44<=55,min(60000-min(20000,Y43),Z43)*0.01/12,min(30000-min(20000,Y43),AB43)*0.02/12+min(30000,AB43)*0.01/12) -> 20.740132 | U44: =if(B44<55,min(60000-min(60000-min(20000,Y43),Z43)-min(20000,Y43),AA43)*0.01/12,min(30000-min(30000-min(20000,Y43),AB43)-min(20000,Y43),AA43)*0.02/12+min(30000-min(30000-min(20000,Y43),AB43)-min(20000,Y43),AA43)*0.01/12) -> 12.593201 | V44: =IF(year($A44)=year($A43), V43+S44, S44) -> 133.33333 | W44: =IF(year($A44)=year($A43), W43+T44, T44) -> 154.72535 | X44: =IF(year($A44)=year($A43), X43+U44, U44) -> 111.94132 | Y44: =IFS( B44<55, MAX( Y43 + IF(MONTH(A44)=12, P44+V44, 0) + H44 - L44 + MAX(0, IF(AA43 >= VLOOKUP(YEAR(A44), Lookup!$Q:$R, 2), Z43 + IF(MONTH(A44)=12, Q44+W44, 0) + I44 + AA43 + IF(MONTH(A44)=12, R44+X44, 0) - VLOOKUP(YEAR(A44), Lookup!$Q:$R, 2) + J44, Z43 + IF(MONTH(A44)=12, Q44+W44, 0) + I44 ) - VLOOKUP(YEAR(A44), Lookup!$K:$M, 3) ), 0), B44=55, IF(Z43>=AD44, MAX(Y43 + IF(MONTH(A44)=12, P44+V44, 0) + H44 - L44, 0), MAX(MAX(0, Y43-(AD44-Z43)) + IF(MONTH(A44)=12, P44+V44, 0) + H44 - L44, 0) ), B44>55, IF(AB43>=$AH$7, MAX(Y43 + IF(MONTH(A44)=12, P44+V44, 0) + H44 - L44 + K44 + Z43, 0), MAX(Y43 + IF(MONTH(A44)=12, P44+V44, 0) + H44 - L44, 0) ) ) -> 62185.465 | Z44: =IFS( B44<55, MIN( IF(AA43 >= VLOOKUP(YEAR(A44), Lookup!$Q:$R, 2), Z43 + IF(MONTH(A44)=12, Q44+W44, 0) + I44 + AA43 + IF(MONTH(A44)=12, R44+X44, 0) - VLOOKUP(YEAR(A44), Lookup!$Q:$R, 2) + J44, Z43 + IF(MONTH(A44)=12, Q44+W44, 0) + I44 ), VLOOKUP(YEAR(A44), Lookup!$K:$M, 3) ), B44=55, IF(Z43 >= AD44, Z43 - AD44, 0), B44>55, 0 ) -> 25367.975 | AA44: =IFS( B44<65, IF(AA43+J44 < VLOOKUP(YEAR(A44), Lookup!$Q:$R, 2), AA43 + IF(MONTH(A44)=12, R43+X43, 0) + J44, MIN( AA43 + IF(MONTH(A44)=12, R43+X43, 0) + J44 , VLOOKUP(YEAR(A44), Lookup!$Q:$R, 2) ) ), B44>=65, IF(AA43+J44 < VLOOKUP(questions!$C$5, Lookup!$Q:$R, 2), AA43 + IF(MONTH(A44)=12, R43+X43, 0) + J44 , MIN( AA43 + IF(MONTH(A44)=12, R43+X43, 0) + J44, VLOOKUP(questions!$C$5, Lookup!$Q:$R, 2) ) ) ) -> 32639.882 | AB44: =IFS( B44<55, 0, B44=55, MIN(Y43+Z43, AD44), B44>55, IF(AB43 < $AH$7, MIN(AB43 + IF(MONTH(A44)=12, Q44+W44, 0) + K44, $AH$7), AB43 + IF(MONTH(A44)=12, Q44+W44, 0) + K44 ) ) -> 0 | AC44: {=IFS(B44<66, XLOOKUP(year(A44),Lookup!$K$13:$K1000,Lookup!$L$13:$L1000,"missing",,1),B44>65,XLOOKUP(questions!$C$5,Lookup!$K$13:$K1000,Lookup!$L$13:$L1000,"missing",,1))} -> 122226.77 | AD44: {=IFS(B44<66, XLOOKUP(year(A44),Lookup!$K$13:$K1000,Lookup!$M$13:$M1000,"missing",,1),B44>65, XLOOKUP(questions!$C$5,Lookup!$K$13:$K1000,Lookup!$M$13:$M1000,"missing",,1))} -> 244453.55 | AE44: {=IFS(B44<66, XLOOKUP(year(A44),Lookup!$K$13:$K1000,Lookup!$N$13:$N1000,"missing",,1),B44>65,XLOOKUP(questions!$C$5,Lookup!$K$13:$K1000,Lookup!$N$13:$N1000,"missing",,1))} -> 488907.09
A45: =eomonth(EDATE(A44,1),0) -> 47391 | B45: =round(YEARFRAC(EOMONTH(questions!$C$3, 0),A45,1),2) -> 30.83 | C45: =IF(B45<questions!$C$6,if(MONTH(A45)=1,C44*(1+questions!$C$12),C44),0) -> 10927.27 | D45: =IF(MONTH(A45)=12,C45*questions!$C$11,0) -> 0 | E45: =MIN(C45,IF(YEAR(A45)=2025,7600,8000)) -> 8000 | F45: =MIN(102000-E45*12,D45) -> 0 | G45: {=if(YEAR(A45)=2025,XLOOKUP(B45,Lookup!$A$3:$A$7,Lookup!$D$3:$D$7,,1)*SUM(E45:F45), XLOOKUP(B45,Lookup!$A$14:$A$18,Lookup!$D$14:$D$18,,1)*SUM(E45:F45))} -> 2960 | H45: {=if(YEAR(A45)=2025,XLOOKUP(B45,Lookup!$F$3:$F$10,Lookup!$G$3:$G$10,,1)*G45, XLOOKUP(B45,Lookup!$F$14:$F$21,Lookup!$G$14:$G$21,,1)*G45)} -> 1840.232 | I45: {=if(B45<55, if(YEAR(A45)=2025,XLOOKUP(B45,Lookup!$F$3:$F$10,Lookup!$H$3:$H$10,,1)*G45, XLOOKUP(B45,Lookup!$F$14:$F$21,Lookup!$H$14:$H$21,,1)*G45),0)} -> 479.816 | J45: {=if(YEAR(A45)=2025,XLOOKUP(B45,Lookup!$F$3:$F$10,Lookup!$I$3:$I$10,,1)*G45, XLOOKUP(B45,Lookup!$F$14:$F$21,Lookup!$I$14:$I$21,,1)*G45)} -> 639.952 | K45: {=if(B45>54, if(YEAR(A45)=2025,XLOOKUP(B45,Lookup!$F$3:$F$10,Lookup!$H$3:$H$10,,1)*G45, XLOOKUP(B45,Lookup!$F$14:$F$21,Lookup!$H$14:$H$21,,1)*G45),0)} -> 0 | L45: =IF(and(A45<questions!$C$19,questions!$C$18="yes"),questions!$C$20,0) -> 700 | M45: =(Y44+H45)*Lookup!A$26/12 -> 133.38687 | N45: =if(B45<55, (Z44+I45)*Lookup!B$26/12, (AB44+K45)*Lookup!B$26/12) -> 86.159302 | O45: =(AA44+J45)*Lookup!C$26/12 -> 110.93278 | P45: =IF(year(A45)=year(A44), P44+M45, M45) -> 1114.9644 | Q45: =IF(year(A45)=year(A44), Q44+N45, N45) -> 717.8558 | R45: =IF(year(A45)=year(A44), R44+O45, O45) -> 921.60077 | S45: =if(B45<55,min(20000,Y44)*0.01/12,min(20000,Y44)*0.02/12) -> 16.666667 | T45: =if(B45<=55,min(60000-min(20000,Y44),Z44)*0.01/12,min(30000-min(20000,Y44),AB44)*0.02/12+min(30000,AB44)*0.01/12) -> 21.139979 | U45: =if(B45<55,min(60000-min(60000-min(20000,Y44),Z44)-min(20000,Y44),AA44)*0.01/12,min(30000-min(30000-min(20000,Y44),AB44)-min(20000,Y44),AA44)*0.02/12+min(30000-min(30000-min(20000,Y44),AB44)-min(20000,Y44),AA44)*0.01/12) -> 12.193354 | V45: =IF(year($A45)=year($A44), V44+S45, S45) -> 150 | W45: =IF(year($A45)=year($A44), W44+T45, T45) -> 175.86533 | X45: =IF(year($A45)=year($A44), X44+U45, U45) -> 124.13467 | Y45: =IFS( B45<55, MAX( Y44 + IF(MONTH(A45)=12, P45+V45, 0) + H45 - L45 + MAX(0, IF(AA44 >= VLOOKUP(YEAR(A45), Lookup!$Q:$R, 2), Z44 + IF(MONTH(A45)=12, Q45+W45, 0) + I45 + AA44 + IF(MONTH(A45)=12, R45+X45, 0) - VLOOKUP(YEAR(A45), Lookup!$Q:$R, 2) + J45, Z44 + IF(MONTH(A45)=12, Q45+W45, 0) + I45 ) - VLOOKUP(YEAR(A45), Lookup!$K:$M, 3) ), 0), B45=55, IF(Z44>=AD45, MAX(Y44 + IF(MONTH(A45)=12, P45+V45, 0) + H45 - L45, 0), MAX(MAX(0, Y44-(AD45-Z44)) + IF(MONTH(A45)=12, P45+V45, 0) + H45 - L45, 0) ), B45>55, IF(AB44>=$AH$7, MAX(Y44 + IF(MONTH(A45)=12, P45+V45, 0) + H45 - L45 + K45 + Z44, 0), MAX(Y44 + IF(MONTH(A45)=12, P45+V45, 0) + H45 - L45, 0) ) ) -> 63325.697 | Z45: =IFS( B45<55, MIN( IF(AA44 >= VLOOKUP(YEAR(A45), Lookup!$Q:$R, 2), Z44 + IF(MONTH(A45)=12, Q45+W45, 0) + I45 + AA44 + IF(MONTH(A45)=12, R45+X45, 0) - VLOOKUP(YEAR(A45), Lookup!$Q:$R, 2) + J45, Z44 + IF(MONTH(A45)=12, Q45+W45, 0) + I45 ), VLOOKUP(YEAR(A45), Lookup!$K:$M, 3) ), B45=55, IF(Z44 >= AD45, Z44 - AD45, 0), B45>55, 0 ) -> 25847.791 | AA45: =IFS( B45<65, IF(AA44+J45 < VLOOKUP(YEAR(A45), Lookup!$Q:$R, 2), AA44 + IF(MONTH(A45)=12, R44+X44, 0) + J45, MIN( AA44 + IF(MONTH(A45)=12, R44+X44, 0) + J45 , VLOOKUP(YEAR(A45), Lookup!$Q:$R, 2) ) ), B45>=65, IF(AA44+J45 < VLOOKUP(questions!$C$5, Lookup!$Q:$R, 2), AA44 + IF(MONTH(A45)=12, R44+X44, 0) + J45 , MIN( AA44 + IF(MONTH(A45)=12, R44+X44, 0) + J45, VLOOKUP(questions!$C$5, Lookup!$Q:$R, 2) ) ) ) -> 33279.834 | AB45: =IFS( B45<55, 0, B45=55, MIN(Y44+Z44, AD45), B45>55, IF(AB44 < $AH$7, MIN(AB44 + IF(MONTH(A45)=12, Q45+W45, 0) + K45, $AH$7), AB44 + IF(MONTH(A45)=12, Q45+W45, 0) + K45 ) ) -> 0 | AC45: {=IFS(B45<66, XLOOKUP(year(A45),Lookup!$K$13:$K1000,Lookup!$L$13:$L1000,"missing",,1),B45>65,XLOOKUP(questions!$C$5,Lookup!$K$13:$K1000,Lookup!$L$13:$L1000,"missing",,1))} -> 122226.77 | AD45: {=IFS(B45<66, XLOOKUP(year(A45),Lookup!$K$13:$K1000,Lookup!$M$13:$M1000,"missing",,1),B45>65, XLOOKUP(questions!$C$5,Lookup!$K$13:$K1000,Lookup!$M$13:$M1000,"missing",,1))} -> 244453.55 | AE45: {=IFS(B45<66, XLOOKUP(year(A45),Lookup!$K$13:$K1000,Lookup!$N$13:$N1000,"missing",,1),B45>65,XLOOKUP(questions!$C$5,Lookup!$K$13:$K1000,Lookup!$N$13:$N1000,"missing",,1))} -> 488907.09
A46: =eomonth(EDATE(A45,1),0) -> 47422 | B46: =round(YEARFRAC(EOMONTH(questions!$C$3, 0),A46,1),2) -> 30.92 | C46: =IF(B46<questions!$C$6,if(MONTH(A46)=1,C45*(1+questions!$C$12),C45),0) -> 10927.27 | D46: =IF(MONTH(A46)=12,C46*questions!$C$11,0) -> 0 | E46: =MIN(C46,IF(YEAR(A46)=2025,7600,8000)) -> 8000 | F46: =MIN(102000-E46*12,D46) -> 0 | G46: {=if(YEAR(A46)=2025,XLOOKUP(B46,Lookup!$A$3:$A$7,Lookup!$D$3:$D$7,,1)*SUM(E46:F46), XLOOKUP(B46,Lookup!$A$14:$A$18,Lookup!$D$14:$D$18,,1)*SUM(E46:F46))} -> 2960 | H46: {=if(YEAR(A46)=2025,XLOOKUP(B46,Lookup!$F$3:$F$10,Lookup!$G$3:$G$10,,1)*G46, XLOOKUP(B46,Lookup!$F$14:$F$21,Lookup!$G$14:$G$21,,1)*G46)} -> 1840.232 | I46: {=if(B46<55, if(YEAR(A46)=2025,XLOOKUP(B46,Lookup!$F$3:$F$10,Lookup!$H$3:$H$10,,1)*G46, XLOOKUP(B46,Lookup!$F$14:$F$21,Lookup!$H$14:$H$21,,1)*G46),0)} -> 479.816 | J46: {=if(YEAR(A46)=2025,XLOOKUP(B46,Lookup!$F$3:$F$10,Lookup!$I$3:$I$10,,1)*G46, XLOOKUP(B46,Lookup!$F$14:$F$21,Lookup!$I$14:$I$21,,1)*G46)} -> 639.952 | K46: {=if(B46>54, if(YEAR(A46)=2025,XLOOKUP(B46,Lookup!$F$3:$F$10,Lookup!$H$3:$H$10,,1)*G46, XLOOKUP(B46,Lookup!$F$14:$F$21,Lookup!$H$14:$H$21,,1)*G46),0)} -> 0 | L46: =IF(and(A46<questions!$C$19,questions!$C$18="yes"),questions!$C$20,0) -> 700 | M46: =(Y45+H46)*Lookup!A$26/12 -> 135.76235 | N46: =if(B46<55, (Z45+I46)*Lookup!B$26/12, (AB45+K46)*Lookup!B$26/12) -> 87.758689 | O46: =(AA45+J46)*Lookup!C$26/12 -> 113.06595 | P46: =IF(year(A46)=year(A45), P45+M46, M46) -> 1250.7268 | Q46: =IF(year(A46)=year(A45), Q45+N46, N46) -> 805.61449 | R46: =IF(year(A46)=year(A45), R45+O46, O46) -> 1034.6667 | S46: =if(B46<55,min(20000,Y45)*0.01/12,min(20000,Y45)*0.02/12) -> 16.666667 | T46: =if(B46<=55,min(60000-min(20000,Y45),Z45)*0.01/12,min(30000-min(20000,Y45),AB45)*0.02/12+min(30000,AB45)*0.01/12) -> 21.539826 | U46: =if(B46<55,min(60000-min(60000-min(20000,Y45),Z45)-min(20000,Y45),AA45)*0.01/12,min(30000-min(30000-min(20000,Y45),AB45)-min(20000,Y45),AA45)*0.02/12+min(30000-min(30000-min(20000,Y45),AB45)-min(20000,Y45),AA45)*0.01/12) -> 11.793508 | V46: =IF(year($A46)=year($A45), V45+S46, S46) -> 166.66667 | W46: =IF(year($A46)=year($A45), W45+T46, T46) -> 197.40516 | X46: =IF(year($A46)=year($A45), X45+U46, U46) -> 135.92818 | Y46: =IFS( B46<55, MAX( Y45 + IF(MONTH(A46)=12, P46+V46, 0) + H46 - L46 + MAX(0, IF(AA45 >= VLOOKUP(YEAR(A46), Lookup!$Q:$R, 2), Z45 + IF(MONTH(A46)=12, Q46+W46, 0) + I46 + AA45 + IF(MONTH(A46)=12, R46+X46, 0) - VLOOKUP(YEAR(A46), Lookup!$Q:$R, 2) + J46, Z45 + IF(MONTH(A46)=12, Q46+W46, 0) + I46 ) - VLOOKUP(YEAR(A46), Lookup!$K:$M, 3) ), 0), B46=55, IF(Z45>=AD46, MAX(Y45 + IF(MONTH(A46)=12, P46+V46, 0) + H46 - L46, 0), MAX(MAX(0, Y45-(AD46-Z45)) + IF(MONTH(A46)=12, P46+V46, 0) + H46 - L46, 0) ), B46>55, IF(AB45>=$AH$7, MAX(Y45 + IF(MONTH(A46)=12, P46+V46, 0) + H46 - L46 + K46 + Z45, 0), MAX(Y45 + IF(MONTH(A46)=12, P46+V46, 0) + H46 - L46, 0) ) ) -> 64465.929 | Z46: =IFS( B46<55, MIN( IF(AA45 >= VLOOKUP(YEAR(A46), Lookup!$Q:$R, 2), Z45 + IF(MONTH(A46)=12, Q46+W46, 0) + I46 + AA45 + IF(MONTH(A46)=12, R46+X46, 0) - VLOOKUP(YEAR(A46), Lookup!$Q:$R, 2) + J46, Z45 + IF(MONTH(A46)=12, Q46+W46, 0) + I46 ), VLOOKUP(YEAR(A46), Lookup!$K:$M, 3) ), B46=55, IF(Z45 >= AD46, Z45 - AD46, 0), B46>55, 0 ) -> 26327.607 | AA46: =IFS( B46<65, IF(AA45+J46 < VLOOKUP(YEAR(A46), Lookup!$Q:$R, 2), AA45 + IF(MONTH(A46)=12, R45+X45, 0) + J46, MIN( AA45 + IF(MONTH(A46)=12, R45+X45, 0) + J46 , VLOOKUP(YEAR(A46), Lookup!$Q:$R, 2) ) ), B46>=65, IF(AA45+J46 < VLOOKUP(questions!$C$5, Lookup!$Q:$R, 2), AA45 + IF(MONTH(A46)=12, R45+X45, 0) + J46 , MIN( AA45 + IF(MONTH(A46)=12, R45+X45, 0) + J46, VLOOKUP(questions!$C$5, Lookup!$Q:$R, 2) ) ) ) -> 33919.786 | AB46: =IFS( B46<55, 0, B46=55, MIN(Y45+Z45, AD46), B46>55, IF(AB45 < $AH$7, MIN(AB45 + IF(MONTH(A46)=12, Q46+W46, 0) + K46, $AH$7), AB45 + IF(MONTH(A46)=12, Q46+W46, 0) + K46 ) ) -> 0 | AC46: {=IFS(B46<66, XLOOKUP(year(A46),Lookup!$K$13:$K1000,Lookup!$L$13:$L1000,"missing",,1),B46>65,XLOOKUP(questions!$C$5,Lookup!$K$13:$K1000,Lookup!$L$13:$L1000,"missing",,1))} -> 122226.77 | AD46: {=IFS(B46<66, XLOOKUP(year(A46),Lookup!$K$13:$K1000,Lookup!$M$13:$M1000,"missing",,1),B46>65, XLOOKUP(questions!$C$5,Lookup!$K$13:$K1000,Lookup!$M$13:$M1000,"missing",,1))} -> 244453.55 | AE46: {=IFS(B46<66, XLOOKUP(year(A46),Lookup!$K$13:$K1000,Lookup!$N$13:$N1000,"missing",,1),B46>65,XLOOKUP(questions!$C$5,Lookup!$K$13:$K1000,Lookup!$N$13:$N1000,"missing",,1))} -> 488907.09
A47: =eomonth(EDATE(A46,1),0) -> 47452 | B47: =round(YEARFRAC(EOMONTH(questions!$C$3, 0),A47,1),2) -> 31 | C47: =IF(B47<questions!$C$6,if(MONTH(A47)=1,C46*(1+questions!$C$12),C46),0) -> 10927.27 | D47: =IF(MONTH(A47)=12,C47*questions!$C$11,0) -> 0 | E47: =MIN(C47,IF(YEAR(A47)=2025,7600,8000)) -> 8000 | F47: =MIN(102000-E47*12,D47) -> 0 | G47: {=if(YEAR(A47)=2025,XLOOKUP(B47,Lookup!$A$3:$A$7,Lookup!$D$3:$D$7,,1)*SUM(E47:F47), XLOOKUP(B47,Lookup!$A$14:$A$18,Lookup!$D$14:$D$18,,1)*SUM(E47:F47))} -> 2960 | H47: {=if(YEAR(A47)=2025,XLOOKUP(B47,Lookup!$F$3:$F$10,Lookup!$G$3:$G$10,,1)*G47, XLOOKUP(B47,Lookup!$F$14:$F$21,Lookup!$G$14:$G$21,,1)*G47)} -> 1840.232 | I47: {=if(B47<55, if(YEAR(A47)=2025,XLOOKUP(B47,Lookup!$F$3:$F$10,Lookup!$H$3:$H$10,,1)*G47, XLOOKUP(B47,Lookup!$F$14:$F$21,Lookup!$H$14:$H$21,,1)*G47),0)} -> 479.816 | J47: {=if(YEAR(A47)=2025,XLOOKUP(B47,Lookup!$F$3:$F$10,Lookup!$I$3:$I$10,,1)*G47, XLOOKUP(B47,Lookup!$F$14:$F$21,Lookup!$I$14:$I$21,,1)*G47)} -> 639.952 | K47: {=if(B47>54, if(YEAR(A47)=2025,XLOOKUP(B47,Lookup!$F$3:$F$10,Lookup!$H$3:$H$10,,1)*G47, XLOOKUP(B47,Lookup!$F$14:$F$21,Lookup!$H$14:$H$21,,1)*G47),0)} -> 0 | L47: =IF(and(A47<questions!$C$19,questions!$C$18="yes"),questions!$C$20,0) -> 700 | M47: =(Y46+H47)*Lookup!A$26/12 -> 138.13784 | N47: =if(B47<55, (Z46+I47)*Lookup!B$26/12, (AB46+K47)*Lookup!B$26/12) -> 89.358075 | O47: =(AA46+J47)*Lookup!C$26/12 -> 115.19913 | P47: =IF(year(A47)=year(A46), P46+M47, M47) -> 1388.8646 | Q47: =IF(year(A47)=year(A46), Q46+N47, N47) -> 894.97256 | R47: =IF(year(A47)=year(A46), R46+O47, O47) -> 1149.8658 | S47: =if(B47<55,min(20000,Y46)*0.01/12,min(20000,Y46)*0.02/12) -> 16.666667 | T47: =if(B47<=55,min(60000-min(20000,Y46),Z46)*0.01/12,min(30000-min(20000,Y46),AB46)*0.02/12+min(30000,AB46)*0.01/12) -> 21.939672 | U47: =if(B47<55,min(60000-min(60000-min(20000,Y46),Z46)-min(20000,Y46),AA46)*0.01/12,min(30000-min(30000-min(20000,Y46),AB46)-min(20000,Y46),AA46)*0.02/12+min(30000-min(30000-min(20000,Y46),AB46)-min(20000,Y46),AA46)*0.01/12) -> 11.393661 | V47: =IF(year($A47)=year($A46), V46+S47, S47) -> 183.33333 | W47: =IF(year($A47)=year($A46), W46+T47, T47) -> 219.34483 | X47: =IF(year($A47)=year($A46), X46+U47, U47) -> 147.32184 | Y47: =IFS( B47<55, MAX( Y46 + IF(MONTH(A47)=12, P47+V47, 0) + H47 - L47 + MAX(0, IF(AA46 >= VLOOKUP(YEAR(A47), Lookup!$Q:$R, 2), Z46 + IF(MONTH(A47)=12, Q47+W47, 0) + I47 + AA46 + IF(MONTH(A47)=12, R47+X47, 0) - VLOOKUP(YEAR(A47), Lookup!$Q:$R, 2) + J47, Z46 + IF(MONTH(A47)=12, Q47+W47, 0) + I47 ) - VLOOKUP(YEAR(A47), Lookup!$K:$M, 3) ), 0), B47=55, IF(Z46>=AD47, MAX(Y46 + IF(MONTH(A47)=12, P47+V47, 0) + H47 - L47, 0), MAX(MAX(0, Y46-(AD47-Z46)) + IF(MONTH(A47)=12, P47+V47, 0) + H47 - L47, 0) ), B47>55, IF(AB46>=$AH$7, MAX(Y46 + IF(MONTH(A47)=12, P47+V47, 0) + H47 - L47 + K47 + Z46, 0), MAX(Y46 + IF(MONTH(A47)=12, P47+V47, 0) + H47 - L47, 0) ) ) -> 65606.161 | Z47: =IFS( B47<55, MIN( IF(AA46 >= VLOOKUP(YEAR(A47), Lookup!$Q:$R, 2), Z46 + IF(MONTH(A47)=12, Q47+W47, 0) + I47 + AA46 + IF(MONTH(A47)=12, R47+X47, 0) - VLOOKUP(YEAR(A47), Lookup!$Q:$R, 2) + J47, Z46 + IF(MONTH(A47)=12, Q47+W47, 0) + I47 ), VLOOKUP(YEAR(A47), Lookup!$K:$M, 3) ), B47=55, IF(Z46 >= AD47, Z46 - AD47, 0), B47>55, 0 ) -> 26807.423 | AA47: =IFS( B47<65, IF(AA46+J47 < VLOOKUP(YEAR(A47), Lookup!$Q:$R, 2), AA46 + IF(MONTH(A47)=12, R46+X46, 0) + J47, MIN( AA46 + IF(MONTH(A47)=12, R46+X46, 0) + J47 , VLOOKUP(YEAR(A47), Lookup!$Q:$R, 2) ) ), B47>=65, IF(AA46+J47 < VLOOKUP(questions!$C$5, Lookup!$Q:$R, 2), AA46 + IF(MONTH(A47)=12, R46+X46, 0) + J47 , MIN( AA46 + IF(MONTH(A47)=12, R46+X46, 0) + J47, VLOOKUP(questions!$C$5, Lookup!$Q:$R, 2) ) ) ) -> 34559.738 | AB47: =IFS( B47<55, 0, B47=55, MIN(Y46+Z46, AD47), B47>55, IF(AB46 < $AH$7, MIN(AB46 + IF(MONTH(A47)=12, Q47+W47, 0) + K47, $AH$7), AB46 + IF(MONTH(A47)=12, Q47+W47, 0) + K47 ) ) -> 0 | AC47: {=IFS(B47<66, XLOOKUP(year(A47),Lookup!$K$13:$K1000,Lookup!$L$13:$L1000,"missing",,1),B47>65,XLOOKUP(questions!$C$5,Lookup!$K$13:$K1000,Lookup!$L$13:$L1000,"missing",,1))} -> 122226.77 | AD47: {=IFS(B47<66, XLOOKUP(year(A47),Lookup!$K$13:$K1000,Lookup!$M$13:$M1000,"missing",,1),B47>65, XLOOKUP(questions!$C$5,Lookup!$K$13:$K1000,Lookup!$M$13:$M1000,"missing",,1))} -> 244453.55 | AE47: {=IFS(B47<66, XLOOKUP(year(A47),Lookup!$K$13:$K1000,Lookup!$N$13:$N1000,"missing",,1),B47>65,XLOOKUP(questions!$C$5,Lookup!$K$13:$K1000,Lookup!$N$13:$N1000,"missing",,1))} -> 488907.09
